Workbook

Sheet PART I - MODEL BUILD >>>

Sheet Financials from CIP
B3: Project Athena
B4: Quarterly and Annual Financial Statements
B5: ($s in 000s)
B7: Income Statement
D9: FY | E9: FY
D10: 2023 | E10: 2024
B11: Service Revenues | D11: 67988.162 | E11: 74320.332
B12: Parts & Other | D12: 10577.514 | E12: 16293.676
B13: Total Revenue | D13: =+SUM(D11:D12) -> 78565.676 | E13: =+SUM(E11:E12) -> 90614.008
B15: Labor | D15: 41584.93 | E15: 49665.089
B16: Materials | D16: 8321.468 | E16: 9548.864
B17: Other CoGS | D17: 1655.791 | E17: 2404.723
B19: Total Gross Profit | D19: =+D13-SUM(D15:D18) -> 27003.487 | E19: =+E13-SUM(E15:E18) -> 28995.332
B21: Total Gross Margin % | D21: =+D19/D$13 -> 0.34370591 | E21: =+E19/E$13 -> 0.3199873
B23: Payroll & Related Expenses | D23: 10567.613 | E23: 11023.057
B24: Rent & Occupancy | D24: 3246.147 | E24: 4150.1989
B25: Depreciation | D25: 1180.1621 | E25: 1161.7643
B26: Amortization | D26: 208.264 | E26: 237.952
B27: Interest | D27: 2224.955 | E27: 1472.763
B28: Other SG&A | D28: 366.155 | E28: 263.433
B29: Income Taxes | D29: 3201.039 | E29: 2809.107
B30: Total SG&A | D30: =+SUM(D23:D29) -> 20994.335 | E30: =+SUM(E23:E29) -> 21118.275
B32: Other Expense (Income) | D32: 147.371 | E32: 273.439
B34: Net Income | D34: =+D19-D30-D32 -> 5861.7809 | E34: =+E19-E30-E32 -> 7603.6178
B36: EBITDA, Unadjusted | D36: =+D34+D25+D27+D29+D26+D32 -> 12823.572 | E36: =+E34+E25+E27+E29+E26+E32 -> 13558.643
B39: Total Profit Margin % | D39: =D34/D$13 -> 0.074609947 | E39: =E34/E$13 -> 0.083912167
B40: Total EBITDA Margin % | D40: =D36/D$13 -> 0.16322105 | E40: =E36/E$13 -> 0.14963076
B42: Balance Sheet
D44: YE | E44: YE
D45: =+D10 -> 2023 | E45: =+D45+1 -> 2024
B46: Cash & Cash Equivalents | D46: 7105.652 | E46: 2957.992
B47: Accounts Receivable, Gross | D47: 17300.432 | E47: 22973.94
B48: Allowance for Doubtful Accounts | D48: -519.013 | E48: -689.218
B49: Inventory | D49: 804.901 | E49: 1161.057
B50: Prepaids & Other | D50: 269.784 | E50: 344.919
B51: Total Current Assets | D51: =+SUM(D46:D50) -> 24961.756 | E51: =+SUM(E46:E50) -> 26748.69
B53: PP&E, Net | D53: 54584.7 | E53: 55684.984
B54: Long-Term Intangible Assets | D54: 4378.482 | E54: 4504.37
B56: Total Assets | D56: =+SUM(D51:D55) -> 83924.938 | E56: =+SUM(E51:E55) -> 86938.044
B58: Accounts Payable | D58: 2805.817 | E58: 2360.71
B59: Wages Payable | D59: 2383.933 | E59: 2788.038
B60: Accrued Expenses & Other | D60: 2057.908 | E60: 3202.031
B61: Total Current Liabilities | D61: =+SUM(D58:D60) -> 7247.658 | E61: =+SUM(E58:E60) -> 8350.779
B63: Revolver | D63: 645.883 | E63: 1289.3
B64: Term Loan A | D64: 18943.222 | E64: 12001.451
B65: Subordinated Debt - Note 1 | D65: 545.333 | E65: 85.338
B66: Subordinated Debt - Note 2 | D66: 92.448 | E66: 12.667
B67: Other Long-Term Liabilities | D67: 417.874 | E67: 429.888
B69: Total Liabilities | D69: =+SUM(D61:D68) -> 27892.418 | E69: =+SUM(E61:E68) -> 22169.423
B71: Common Stock | D71: 7783.6338 | E71: 8916.1157
B72: Retained Earnings | D72: 48248.887 | E72: 55852.505
B73: Total Equity | D73: =+SUM(D71:D72) -> 56032.521 | E73: =+SUM(E71:E72) -> 64768.62
B76: Total Liabilities and Equity | D76: =+D73+D69 -> 83924.939 | E76: =+E73+E69 -> 86938.043
B78: Net Working Capital | D78: =D51-D61 -> 17714.098 | E78: =E51-E61 -> 18397.911
B79: Net Working Capital, less Cash | D79: =(D51-D46)-D61 -> 10608.446 | E79: =(E51-E46)-E61 -> 15439.919
B81: Check | D81: =+D76-D56 -> 0.00082790072 | E81: =+E76-E56 -> -0.0005041918

Sheet Step 1
C2: Athena Modeling Exercise
C3: Step 1 - Historicals
J5: Black font = Calculation
C6: YELLOWS ARE FILLS | F6: SKIP FOR NOW | J6: Blue font = Hardcoded Input/Assumption
J7: Green font = Pulled from another Sheet
B8: x | C8: Income Statement | M8: Use the historical financial statements (Income Statement and Balance Sheet) to get started. Copy the financial statements as they appear from your research
F10: MRY | G10: MRY | H10: Fiscal Years Ending December 31,
C11: ($ in millions) | F11: =EOMONTH(G11,-12) -> 45291 | G11: 45657 | H11: =EOMONTH(G11,12) -> 46022 | I11: =EOMONTH(H11,12) -> 46387 | J11: =EOMONTH(I11,12) -> 46752 | K11: =EOMONTH(J11,12) -> 47118 | L11: =EOMONTH(K11,12) -> 47483
C13: Total Revenue
C14: COGS
C15: Gross Profit | F15: =F13-F14 -> 0 | G15: =G13-G14 -> 0
C16: Gross Margin (%) | F16: =IFERROR(F15/F$13,"N/M") -> N/M | G16: =IFERROR(G15/G$13,"N/M") -> N/M
C17: SG&A
C18: EBITDA | F18: =F15-F17 -> 0 | G18: =G15-G17 -> 0
C19: EBITDA Margin (%) | F19: =IFERROR(F18/F$13,"N/M") -> N/M | G19: =IFERROR(G18/G$13,"N/M") -> N/M
C20: Depreciation
C21: Amortization
C22: EBIT | F22: =F18-SUM(F20:F21) -> 0 | G22: =G18-SUM(G20:G21) -> 0
C23: Interest (Income) / Expense
C24: Revolver – Interest
C25: Revolver – Undrawn Commitment Fee
C26: =+C66 -> Term Loan A
C27: =+C67 -> Subordinated - Note 1
C28: =+C68 -> Subordinated - Note 2
C29: Interest (Income) / Expense
C30: Other (Income) / Expense
C31: Income Before Taxes | F31: =F22-F29-F30 -> 0 | G31: =G22-G29-G30 -> 0
C32: Provision for Tax
C33: Net Income | F33: =F31-F32 -> 0 | G33: =G31-G32 -> 0
C34: Profit Margin (%) | F34: =IFERROR(F33/F$13,"N/M") -> N/M | G34: =IFERROR(G33/G$13,"N/M") -> N/M
C36: Capital Expenditures
B40: x | C40: Balance Sheet
F42: MRY | G42: MRY | H42: Fiscal Years Ending December 31,
C43: ($ in millions) | F43: =EOMONTH(G43,-12) -> 45291 | G43: =G$11 -> 45657 | H43: =H$11 -> 46022 | I43: =I$11 -> 46387 | J43: =J$11 -> 46752 | K43: =K$11 -> 47118 | L43: =L$11 -> 47483
C45: Assets
C47: Cash and Equivalents
C48: Accounts Receivable, net
C49: Inventory
C50: Prepaids and Other Current Assets
C51: Total Current Assets | F51: =SUM(F47:F50) -> 0 | G51: =SUM(G47:G50) -> 0
C52: PP&E, Gross
C53: ( – ) Accumulated Depreciation
C54: PP&E, Net
C55: Goodwill | F55: 0 | G55: 0
C56: Intangible and Long-Term Other Assets
C57: Total Assets | F57: =SUM(F51,F54:F56) -> 0 | G57: =SUM(G51,G54:G56) -> 0
C59: Liabilities & Shareholders' Equity
C61: Accounts Payable
C62: Wages Payable
C63: Accrued Expenses & Other
C64: Total Current Liabilities | F64: =SUM(F61:F63) -> 0 | G64: =SUM(G61:G63) -> 0
C65: Revolver
C66: Term Loan A
C67: Subordinated - Note 1
C68: Subordinated - Note 2
C69: Total Debt | F69: =SUM(F65:F68) -> 0 | G69: =SUM(G65:G68) -> 0
C70: Other Long-term Liabilities
C71: Total liabilities | F71: =SUM(F64,F69:F70) -> 0 | G71: =SUM(G64,G69:G70) -> 0
C72: Common Stock
C73: Retained Earnings
C74: Total Liabilities & Shareholders' Equity | F74: =SUM(F71:F73) -> 0 | G74: =SUM(G71:G73) -> 0
B79: x | C79: Checks to Source
C80: Income Statement
C81: Revenue
C82: Gross Profit
C83: EBITDA
C84: Net Income
C86: Balance Sheet
C87: Cash
C88: Current Assets
C89: Total Assets
C90: Current Liabilities
C91: Total Liabilities
C92: Total Equity
... C95: A= L + E

Sheet Step 1 Answer Key
C2: Athena Modeling Exercise
C3: Step 1 - Historicals
J5: Black font = Calculation
C6: YELLOWS ARE FILLS | F6: SKIP FOR NOW | J6: Blue font = Hardcoded Input/Assumption
J7: Green font = Pulled from another Sheet
B8: x | C8: Income Statement | M8: Use the historical financial statements (Income Statement and Balance Sheet) to get started. Copy the financial statements as they appear from your research
F10: MRY | G10: MRY | H10: Fiscal Years Ending December 31,
C11: ($ in millions) | F11: =EOMONTH(G11,-12) -> 45291 | G11: 45657 | H11: =EOMONTH(G11,12) -> 46022 | I11: =EOMONTH(H11,12) -> 46387 | J11: =EOMONTH(I11,12) -> 46752 | K11: =EOMONTH(J11,12) -> 47118 | L11: =EOMONTH(K11,12) -> 47483
C13: Total Revenue | F13: ='Financials from CIP'!D13/1000 -> 78.565676 | G13: ='Financials from CIP'!E13/1000 -> 90.614008
C14: COGS | F14: =SUM('Financials from CIP'!D15:D17)/1000 -> 51.562189 | G14: =SUM('Financials from CIP'!E15:E17)/1000 -> 61.618676
C15: Gross Profit | F15: =F13-F14 -> 27.003487 | G15: =G13-G14 -> 28.995332
C16: Gross Margin (%) | F16: =IFERROR(F15/F$13,"N/M") -> 0.34370591 | G16: =IFERROR(G15/G$13,"N/M") -> 0.3199873
C17: SG&A | F17: =SUM('Financials from CIP'!D23:D24,'Financials from CIP'!D28)/1000 -> 14.179915 | G17: =SUM('Financials from CIP'!E23:E24,'Financials from CIP'!E28)/1000 -> 15.436689
C18: EBITDA | F18: =F15-F17 -> 12.823572 | G18: =G15-G17 -> 13.558643
C19: EBITDA Margin (%) | F19: =IFERROR(F18/F$13,"N/M") -> 0.16322105 | G19: =IFERROR(G18/G$13,"N/M") -> 0.14963076
C20: Depreciation | F20: ='Financials from CIP'!D25/1000 -> 1.1801621 | G20: ='Financials from CIP'!E25/1000 -> 1.1617643
C21: Amortization | F21: ='Financials from CIP'!D26/1000 -> 0.208264 | G21: ='Financials from CIP'!E26/1000 -> 0.237952
C22: EBIT | F22: =F18-SUM(F20:F21) -> 11.435146 | G22: =G18-SUM(G20:G21) -> 12.158927
C23: Interest (Income) / Expense
C24: Revolver – Interest
C25: Revolver – Undrawn Commitment Fee
C26: =+C66 -> Term Loan A
C27: =+C67 -> Subordinated - Note 1
C28: =+C68 -> Subordinated - Note 2
C29: Interest (Income) / Expense | F29: ='Financials from CIP'!D27/1000 -> 2.224955 | G29: ='Financials from CIP'!E27/1000 -> 1.472763
C30: Other (Income) / Expense | F30: ='Financials from CIP'!D32/1000 -> 0.147371 | G30: ='Financials from CIP'!E32/1000 -> 0.273439
C31: Income Before Taxes | F31: =F22-F29-F30 -> 9.0628199 | G31: =G22-G29-G30 -> 10.412725
C32: Provision for Tax | F32: ='Financials from CIP'!D29/1000 -> 3.201039 | G32: ='Financials from CIP'!E29/1000 -> 2.809107
C33: Net Income | F33: =F31-F32 -> 5.8617809 | G33: =G31-G32 -> 7.6036178
C34: Profit Margin (%) | F34: =IFERROR(F33/F$13,"N/M") -> 0.074609947 | G34: =IFERROR(G33/G$13,"N/M") -> 0.083912167
C36: Capital Expenditures
B40: x | C40: Balance Sheet
F42: MRY | G42: MRY | H42: Fiscal Years Ending December 31,
C43: ($ in millions) | F43: =EOMONTH(G43,-12) -> 45291 | G43: =G$11 -> 45657 | H43: =H$11 -> 46022 | I43: =I$11 -> 46387 | J43: =J$11 -> 46752 | K43: =K$11 -> 47118 | L43: =L$11 -> 47483
C45: Assets
C47: Cash and Equivalents | F47: ='Financials from CIP'!D46/1000 -> 7.105652 | G47: ='Financials from CIP'!E46/1000 -> 2.957992
C48: Accounts Receivable, net | F48: =SUM('Financials from CIP'!D47:D48)/1000 -> 16.781419 | G48: =SUM('Financials from CIP'!E47:E48)/1000 -> 22.284722
C49: Inventory | F49: ='Financials from CIP'!D49/1000 -> 0.804901 | G49: ='Financials from CIP'!E49/1000 -> 1.161057
C50: Prepaids and Other Current Assets | F50: ='Financials from CIP'!D50/1000 -> 0.269784 | G50: ='Financials from CIP'!E50/1000 -> 0.344919
C51: Total Current Assets | F51: =SUM(F47:F50) -> 24.961756 | G51: =SUM(G47:G50) -> 26.74869
C52: PP&E, Gross
C53: ( – ) Accumulated Depreciation
C54: PP&E, Net | F54: ='Financials from CIP'!D53/1000 -> 54.5847 | G54: ='Financials from CIP'!E53/1000 -> 55.684984
C55: Goodwill | F55: 0 | G55: 0
C56: Intangible and Long-Term Other Assets | F56: ='Financials from CIP'!D54/1000 -> 4.378482 | G56: ='Financials from CIP'!E54/1000 -> 4.50437
C57: Total Assets | F57: =SUM(F51,F54:F56) -> 83.924938 | G57: =SUM(G51,G54:G56) -> 86.938044
C59: Liabilities & Shareholders' Equity
C61: Accounts Payable | F61: ='Financials from CIP'!D58/1000 -> 2.805817 | G61: ='Financials from CIP'!E58/1000 -> 2.36071
C62: Wages Payable | F62: ='Financials from CIP'!D59/1000 -> 2.383933 | G62: ='Financials from CIP'!E59/1000 -> 2.788038
C63: Accrued Expenses & Other | F63: ='Financials from CIP'!D60/1000 -> 2.057908 | G63: ='Financials from CIP'!E60/1000 -> 3.202031
C64: Total Current Liabilities | F64: =SUM(F61:F63) -> 7.247658 | G64: =SUM(G61:G63) -> 8.350779
C65: Revolver | F65: ='Financials from CIP'!D63/1000 -> 0.645883 | G65: ='Financials from CIP'!E63/1000 -> 1.2893
C66: Term Loan A | F66: ='Financials from CIP'!D64/1000 -> 18.943222 | G66: ='Financials from CIP'!E64/1000 -> 12.001451
C67: Subordinated - Note 1 | F67: ='Financials from CIP'!D65/1000 -> 0.545333 | G67: ='Financials from CIP'!E65/1000 -> 0.085338
C68: Subordinated - Note 2 | F68: ='Financials from CIP'!D66/1000 -> 0.092448 | G68: ='Financials from CIP'!E66/1000 -> 0.012667
C69: Total Debt | F69: =SUM(F65:F68) -> 20.226886 | G69: =SUM(G65:G68) -> 13.388756
C70: Other Long-term Liabilities | F70: ='Financials from CIP'!D67/1000 -> 0.417874 | G70: ='Financials from CIP'!E67/1000 -> 0.429888
C71: Total liabilities | F71: =SUM(F64,F69:F70) -> 27.892418 | G71: =SUM(G64,G69:G70) -> 22.169423
C72: Common Stock | F72: ='Financials from CIP'!D71/1000 -> 7.7836338 | G72: ='Financials from CIP'!E71/1000 -> 8.9161157
C73: Retained Earnings | F73: ='Financials from CIP'!D72/1000 -> 48.248887 | G73: ='Financials from CIP'!E72/1000 -> 55.852505
C74: Total Liabilities & Shareholders' Equity | F74: =SUM(F71:F73) -> 83.924939 | G74: =SUM(G71:G73) -> 86.938043
B79: x | C79: Checks to Source
C80: Income Statement
C81: Revenue | F81: ='Financials from CIP'!D13/1000-'Step 1 Answer Key'!F13 -> 0 | G81: ='Financials from CIP'!E13/1000-'Step 1 Answer Key'!G13 -> 0
C82: Gross Profit | F82: ='Financials from CIP'!D19/1000-'Step 1 Answer Key'!F15 -> 0 | G82: ='Financials from CIP'!E19/1000-'Step 1 Answer Key'!G15 -> 0
C83: EBITDA | F83: ='Financials from CIP'!D36/1000-'Step 1 Answer Key'!F18 -> 0 | G83: ='Financials from CIP'!E36/1000-'Step 1 Answer Key'!G18 -> 0
C84: Net Income | F84: ='Financials from CIP'!D34/1000-'Step 1 Answer Key'!F33 -> 0 | G84: ='Financials from CIP'!E34/1000-'Step 1 Answer Key'!G33 -> 0
C86: Balance Sheet
C87: Cash | F87: ='Financials from CIP'!D46/1000-'Step 1 Answer Key'!F47 -> 0 | G87: ='Financials from CIP'!E46/1000-'Step 1 Answer Key'!G47 -> 0
C88: Current Assets | F88: ='Financials from CIP'!D51/1000-'Step 1 Answer Key'!F51 -> 0 | G88: ='Financials from CIP'!E51/1000-'Step 1 Answer Key'!G51 -> 0
C89: Total Assets | F89: ='Financials from CIP'!D56/1000-'Step 1 Answer Key'!F57 -> 0 | G89: ='Financials from CIP'!E56/1000-'Step 1 Answer Key'!G57 -> 0
C90: Current Liabilities | F90: ='Financials from CIP'!D61/1000-'Step 1 Answer Key'!F64 -> 0 | G90: ='Financials from CIP'!E61/1000-'Step 1 Answer Key'!G64 -> 0
C91: Total Liabilities | F91: ='Financials from CIP'!D69/1000-'Step 1 Answer Key'!F71 -> 0 | G91: ='Financials from CIP'!E69/1000-'Step 1 Answer Key'!G71 -> 0
C92: Total Equity | F92: ='Financials from CIP'!D73/1000-SUM('Step 1 Answer Key'!F72:F73) -> 0 | G92: ='Financials from CIP'!E73/1000-SUM('Step 1 Answer Key'!G72:G73) -> 0
C94: Internal Checks
C95: A= L + E | F95: =F57-F74 -> -8.2790072e-07 | G95: =G57-G74 -> 5.041918e-07

Sheet Step 2
C2: Athena Modeling Exercise
C3: Step 2 - Begin Projecting the Income Statement
J5: Black font = Calculation
C6: YELLOWS ARE FILLS | F6: SKIP FOR NOW | J6: Blue font = Hardcoded Input/Assumption
J7: Green font = Pulled from another Sheet
B8: x | C8: Income Statement
F10: MRY | G10: MRY | H10: Fiscal Years Ending December 31,
C11: ($ in millions) | F11: =EOMONTH(G11,-12) -> 45291 | G11: 45657 | H11: =EOMONTH(G11,12) -> 46022 | I11: =EOMONTH(H11,12) -> 46387 | J11: =EOMONTH(I11,12) -> 46752 | K11: =EOMONTH(J11,12) -> 47118 | L11: =EOMONTH(K11,12) -> 47483
C13: Total Revenue | F13: ='Financials from CIP'!D13/1000 -> 78.565676 | G13: ='Financials from CIP'!E13/1000 -> 90.614008 | M13: Revenue is grown year-over-year. Project total revenue based on the growth rate assumption below and the prior period revenue (line 41)
C14: COGS | F14: =SUM('Financials from CIP'!D15:D17)/1000 -> 51.562189 | G14: =SUM('Financials from CIP'!E15:E17)/1000 -> 61.618676 | M14: CoGS typically fluctuates with Revenue - it is the cost of the goods and services we sell. We call this a "Variable Cost." As such, project as a % of Sales based on the performance driver below - that way CoGS moves with Revenue
C15: Gross Profit | F15: =F13-F14 -> 27.003487 | G15: =G13-G14 -> 28.995332 | H15: =H13-H14 -> 0 | I15: =I13-I14 -> 0 | J15: =J13-J14 -> 0 | K15: =K13-K14 -> 0 | L15: =L13-L14 -> 0
C16: Gross Margin (%) | F16: =IFERROR(F15/F$13,"N/M") -> 0.34370591 | G16: =IFERROR(G15/G$13,"N/M") -> 0.3199873 | H16: =IFERROR(H15/H$13,"N/M") -> N/M | I16: =IFERROR(I15/I$13,"N/M") -> N/M | J16: =IFERROR(J15/J$13,"N/M") -> N/M | K16: =IFERROR(K15/K$13,"N/M") -> N/M | L16: =IFERROR(L15/L$13,"N/M") -> N/M | M16: Calculate Gross Profit Margin (Gross Profit / Total Revenue)
C17: SG&A | F17: =SUM('Financials from CIP'!D23:D24,'Financials from CIP'!D28)/1000 -> 14.179915 | G17: =SUM('Financials from CIP'!E23:E24,'Financials from CIP'!E28)/1000 -> 15.436689 | M17: SG&A typically has a part that is fixed (cost that does not fluctuate with revenue - like Rent) and a part that is Variable Cost. When I look at what the components of SG&A are using information from the 'Financials from CIP' tab, I see the majority of it is in Payroll & Related Expense - something that is most likely Variable. For simplicity sake, let's project SG&A in the business to be Variable. As such, project as a % of Sales based on the performance driver below
C18: EBITDA | F18: =F15-F17 -> 12.823572 | G18: =G15-G17 -> 13.558643 | H18: =H15-H17 -> 0 | I18: =I15-I17 -> 0 | J18: =J15-J17 -> 0 | K18: =K15-K17 -> 0 | L18: =L15-L17 -> 0
C19: EBITDA Margin (%) | F19: =IFERROR(F18/F$13,"N/M") -> 0.16322105 | G19: =IFERROR(G18/G$13,"N/M") -> 0.14963076 | H19: =IFERROR(H18/H$13,"N/M") -> N/M | I19: =IFERROR(I18/I$13,"N/M") -> N/M | J19: =IFERROR(J18/J$13,"N/M") -> N/M | K19: =IFERROR(K18/K$13,"N/M") -> N/M | L19: =IFERROR(L18/L$13,"N/M") -> N/M | M19: Calculate EBITDA Margin (EBITDA / Total Revenue)
C20: Depreciation | F20: ='Financials from CIP'!D25/1000 -> 1.1801621 | G20: ='Financials from CIP'!E25/1000 -> 1.1617643 | M20: See the schedule, below. Link total Depreciation per year from the schedule to here. Follow the Depreciation schedule instructions carefully
C21: Amortization | F21: ='Financials from CIP'!D26/1000 -> 0.208264 | G21: ='Financials from CIP'!E26/1000 -> 0.237952 | M21: Amortization Expense reduces Other Intangibles Assets on the Balance sheet. It is similar to Depreciation but for Assets that are not physical (like a copyright). For simplicity sake, let's hold the 2024 amount consistent per year going forward but be careful to not to amortize more than the Balance of the Other Intangible Assets in any given year. We will revisit this calculation to ensure its working properly in a later step
C22: EBIT | F22: =F18-SUM(F20:F21) -> 11.435146 | G22: =G18-SUM(G20:G21) -> 12.158927 | H22: =H18-SUM(H20:H21) -> 0 | I22: =I18-SUM(I20:I21) -> 0 | J22: =J18-SUM(J20:J21) -> 0 | K22: =K18-SUM(K20:K21) -> 0 | L22: =L18-SUM(L20:L21) -> 0
C23: Interest (Income) / Expense
C24: Revolver – Interest
C25: Revolver – Undrawn Commitment Fee
C26: =+C79 -> Term Loan A
C27: =+C80 -> Subordinated - Note 1
C28: =+C81 -> Subordinated - Note 2
C29: Interest (Income) / Expense | F29: ='Financials from CIP'!D27/1000 -> 2.224955 | G29: ='Financials from CIP'!E27/1000 -> 1.472763 | H29: =SUM(H24:H28) -> 0 | I29: =SUM(I24:I28) -> 0 | J29: =SUM(J24:J28) -> 0 | K29: =SUM(K24:K28) -> 0 | L29: =SUM(L24:L28) -> 0
C30: Other (Income) / Expense | F30: ='Financials from CIP'!D32/1000 -> 0.147371 | G30: ='Financials from CIP'!E32/1000 -> 0.273439 | M30: This is very low in 2023 and 2024. Let's assume it stays zero going forward
C31: Income Before Taxes | F31: =F22-F29-F30 -> 9.0628199 | G31: =G22-G29-G30 -> 10.412725 | H31: =H22-H29-H30 -> 0 | I31: =I22-I29-I30 -> 0 | J31: =J22-J29-J30 -> 0 | K31: =K22-K29-K30 -> 0 | L31: =L22-L29-L30 -> 0
C32: Provision for Tax | F32: ='Financials from CIP'!D29/1000 -> 3.201039 | G32: ='Financials from CIP'!E29/1000 -> 2.809107 | M32: Calculate tax expense based on the tax rate below
C33: Net Income | F33: =F31-F32 -> 5.8617809 | G33: =G31-G32 -> 7.6036178 | H33: =H31-H32 -> 0 | I33: =I31-I32 -> 0 | J33: =J31-J32 -> 0 | K33: =K31-K32 -> 0 | L33: =L31-L32 -> 0
C34: Profit Margin (%) | F34: =IFERROR(F33/F$13,"N/M") -> 0.074609947 | G34: =IFERROR(G33/G$13,"N/M") -> 0.083912167 | H34: =IFERROR(H33/H$13,"N/M") -> N/M | I34: =IFERROR(I33/I$13,"N/M") -> N/M | J34: =IFERROR(J33/J$13,"N/M") -> N/M | K34: =IFERROR(K33/K$13,"N/M") -> N/M | L34: =IFERROR(L33/L$13,"N/M") -> N/M
C36: Capital Expenditures
C39: Key Performance Metrics & Drivers
C41: Sales Growth (%) | M41: Round your 2024 growth rate to the nearest percent and use that for 2025 and 2026, reducing it by 3% per year thereafter
C43: COGS / Sales (%) | M43: Divide by sales to get the % in 2023 and 2024. Use an average as your assumption and hold constant going forward
C44: SG&A / Sales (%) | M44: Same as above
C46: Tax Rate (%) | M46: Round the 2024 tax rate to the nearest % and use that going forward
C48: Capex / Sales (%)
B53: x | C53: Balance Sheet
F55: MRY | G55: MRY | H55: Fiscal Years Ending December 31,
C56: ($ in millions) | F56: =EOMONTH(G56,-12) -> 45291 | G56: =G$11 -> 45657 | H56: =H$11 -> 46022 | I56: =I$11 -> 46387 | J56: =J$11 -> 46752 | K56: =K$11 -> 47118 | L56: =L$11 -> 47483
C58: Assets
C60: Cash and Equivalents | F60: ='Financials from CIP'!D46/1000 -> 7.105652 | G60: ='Financials from CIP'!E46/1000 -> 2.957992
C61: Accounts Receivable, net | F61: =SUM('Financials from CIP'!D47:D48)/1000 -> 16.781419 | G61: =SUM('Financials from CIP'!E47:E48)/1000 -> 22.284722
C62: Inventory | F62: ='Financials from CIP'!D49/1000 -> 0.804901 | G62: ='Financials from CIP'!E49/1000 -> 1.161057
C63: Prepaids and Other Current Assets | F63: ='Financials from CIP'!D50/1000 -> 0.269784 | G63: ='Financials from CIP'!E50/1000 -> 0.344919
C64: Total Current Assets | F64: =SUM(F60:F63) -> 24.961756 | G64: =SUM(G60:G63) -> 26.74869
C65: PP&E, Gross
C66: ( – ) Accumulated Depreciation
C67: PP&E, Net | F67: ='Financials from CIP'!D53/1000 -> 54.5847 | G67: ='Financials from CIP'!E53/1000 -> 55.684984
C68: Goodwill | F68: 0 | G68: 0
C69: Intangible and Long-Term Other Assets | F69: ='Financials from CIP'!D54/1000 -> 4.378482 | G69: ='Financials from CIP'!E54/1000 -> 4.50437
C70: Total Assets | F70: =SUM(F64,F67:F69) -> 83.924938 | G70: =SUM(G64,G67:G69) -> 86.938044
C72: Liabilities & Shareholders' Equity
C74: Accounts Payable | F74: ='Financials from CIP'!D58/1000 -> 2.805817 | G74: ='Financials from CIP'!E58/1000 -> 2.36071
C75: Wages Payable | F75: ='Financials from CIP'!D59/1000 -> 2.383933 | G75: ='Financials from CIP'!E59/1000 -> 2.788038
C76: Accrued Expenses & Other | F76: ='Financials from CIP'!D60/1000 -> 2.057908 | G76: ='Financials from CIP'!E60/1000 -> 3.202031
C77: Total Current Liabilities | F77: =SUM(F74:F76) -> 7.247658 | G77: =SUM(G74:G76) -> 8.350779
C78: Revolver | F78: ='Financials from CIP'!D63/1000 -> 0.645883 | G78: ='Financials from CIP'!E63/1000 -> 1.2893
C79: Term Loan A | F79: ='Financials from CIP'!D64/1000 -> 18.943222 | G79: ='Financials from CIP'!E64/1000 -> 12.001451
C80: Subordinated - Note 1 | F80: ='Financials from CIP'!D65/1000 -> 0.545333 | G80: ='Financials from CIP'!E65/1000 -> 0.085338
C81: Subordinated - Note 2 | F81: ='Financials from CIP'!D66/1000 -> 0.092448 | G81: ='Financials from CIP'!E66/1000 -> 0.012667
C82: Total Debt | F82: =SUM(F78:F81) -> 20.226886 | G82: =SUM(G78:G81) -> 13.388756
C83: Other Long-term Liabilities | F83: ='Financials from CIP'!D67/1000 -> 0.417874 | G83: ='Financials from CIP'!E67/1000 -> 0.429888
C84: Total liabilities | F84: =SUM(F77,F82:F83) -> 27.892418 | G84: =SUM(G77,G82:G83) -> 22.169423
C85: Common Stock | F85: ='Financials from CIP'!D71/1000 -> 7.7836338 | G85: ='Financials from CIP'!E71/1000 -> 8.9161157
C86: Retained Earnings | F86: ='Financials from CIP'!D72/1000 -> 48.248887 | G86: ='Financials from CIP'!E72/1000 -> 55.852505
C87: Total Liabilities & Shareholders' Equity | F87: =SUM(F84:F86) -> 83.924939 | G87: =SUM(G84:G86) -> 86.938043
B92: x | C92: Checks to Source
C93: Income Statement
C94: Revenue | F94: ='Financials from CIP'!D13/1000-'Step 2'!F13 -> 0 | G94: ='Financials from CIP'!E13/1000-'Step 2'!G13 -> 0
C95: Gross Profit | F95: ='Financials from CIP'!D19/1000-'Step 2'!F15 -> 0 | G95: ='Financials from CIP'!E19/1000-'Step 2'!G15 -> 0
C96: EBITDA | F96: ='Financials from CIP'!D36/1000-'Step 2'!F18 -> 0 | G96: ='Financials from CIP'!E36/1000-'Step 2'!G18 -> 0
C97: Net Income | F97: ='Financials from CIP'!D34/1000-'Step 2'!F33 -> 0 | G97: ='Financials from CIP'!E34/1000-'Step 2'!G33 -> 0
C99: Balance Sheet
C100: Cash | F100: ='Financials from CIP'!D46/1000-'Step 2'!F60 -> 0 | G100: ='Financials from CIP'!E46/1000-'Step 2'!G60 -> 0
C101: Current Assets | F101: ='Financials from CIP'!D51/1000-'Step 2'!F64 -> 0 | G101: ='Financials from CIP'!E51/1000-'Step 2'!G64 -> 0
C102: Total Assets | F102: ='Financials from CIP'!D56/1000-'Step 2'!F70 -> 0 | G102: ='Financials from CIP'!E56/1000-'Step 2'!G70 -> 0
C103: Current Liabilities | F103: ='Financials from CIP'!D61/1000-'Step 2'!F77 -> 0 | G103: ='Financials from CIP'!E61/1000-'Step 2'!G77 -> 0
C104: Total Liabilities | F104: ='Financials from CIP'!D69/1000-'Step 2'!F84 -> 0 | G104: ='Financials from CIP'!E69/1000-'Step 2'!G84 -> 0
C105: Total Equity | F105: ='Financials from CIP'!D73/1000-SUM('Step 2'!F85:F86) -> 0 | G105: ='Financials from CIP'!E73/1000-SUM('Step 2'!G85:G86) -> 0
C107: Internal Checks
C108: A= L + E | F108: =F70-F87 -> -8.2790072e-07 | G108: =G70-G87 -> 5.041918e-07
B114: x | C114: Depreciation Schedule | M114: Depreciation is how much your long-term, physical assets (such as equipment) decrease in value each year. We have to know the cost of our the long-term, physical assets (CapEx) and then choose an "estimated life" to find the depreciation each year
H116: Fiscal Years Ending December 31,
C117: ($ in millions) | D117: PP&E to Depr | E117: SL Years (Est Life) | F117: Last Year | G117: Depr/Year | H117: =H$11 -> 46022 | I117: =I$11 -> 46387 | J117: =J$11 -> 46752 | K117: =K$11 -> 47118 | L117: =L$11 -> 47483
C119: =G11 -> 45657 | D119: =G67 -> 55.684984 | F119: =-G20 -> -1.1617643 | G119: =IFERROR(-D119/E119,"N/M") -> N/M | M119: Link Amt to Depr to this year's capex. Straight line Depr for 10 more years. Use a rolling formula to determine what the amount should be each year - how much is left over vs annual depreciation per year. The first year formula can be written as: =-MIN(-$G119,$D119). Following that, we can write it as: =-MIN(-$H119,SUM($H119:H119,$D119))
C120: =H117 -> 46022
C121: =I117 -> 46387
C122: =J117 -> 46752
C123: =K117 -> 47118
C124: =L117 -> 47483
C126: Total Depr. | H126: =-SUM(H119:H125) -> 0 | I126: =-SUM(I119:I125) -> 0 | J126: =-SUM(J119:J125) -> 0 | K126: =-SUM(K119:K125) -> 0 | L126: =-SUM(L119:L125) -> 0

Sheet Step 2 Answer Key
C2: Athena Modeling Exercise
C3: Step 2 - Begin Projecting the Income Statement
J5: Black font = Calculation
C6: YELLOWS ARE FILLS | F6: SKIP FOR NOW | J6: Blue font = Hardcoded Input/Assumption
J7: Green font = Pulled from another Sheet
B8: x | C8: Income Statement
F10: MRY | G10: MRY | H10: Fiscal Years Ending December 31,
C11: ($ in millions) | F11: =EOMONTH(G11,-12) -> 45291 | G11: 45657 | H11: =EOMONTH(G11,12) -> 46022 | I11: =EOMONTH(H11,12) -> 46387 | J11: =EOMONTH(I11,12) -> 46752 | K11: =EOMONTH(J11,12) -> 47118 | L11: =EOMONTH(K11,12) -> 47483
C13: Total Revenue | F13: ='Financials from CIP'!D13/1000 -> 78.565676 | G13: ='Financials from CIP'!E13/1000 -> 90.614008 | H13: =(1+H41)*G13 -> 104.51 | I13: =(1+I41)*H13 -> 120.53698 | J13: =(1+J41)*I13 -> 135.40566 | K13: =(1+K41)*J13 -> 148.04627 | L13: =(1+L41)*K13 -> 157.42554 | M13: Revenue is grown year-over-year. Project total revenue based on the growth rate assumption below and the prior period revenue (line 41)
C14: COGS | F14: =SUM('Financials from CIP'!D15:D17)/1000 -> 51.562189 | G14: =SUM('Financials from CIP'!E15:E17)/1000 -> 61.618676 | H14: =H43*H13 -> 69.828708 | I14: =I43*I13 -> 80.537195 | J14: =J43*J13 -> 90.47175 | K14: =K43*K13 -> 98.917617 | L14: =L43*L13 -> 105.18441 | M14: CoGS typically fluctuates with Revenue - it is the cost of the goods and services we sell. We call this a "Variable Cost." As such, project as a % of Sales based on the performance driver below - that way CoGS moves with Revenue
C15: Gross Profit | F15: =F13-F14 -> 27.003487 | G15: =G13-G14 -> 28.995332 | H15: =H13-H14 -> 34.681287 | I15: =I13-I14 -> 39.999789 | J15: =J13-J14 -> 44.933908 | K15: =K13-K14 -> 49.128652 | L15: =L13-L14 -> 52.24113
C16: Gross Margin (%) | F16: =IFERROR(F15/F$13,"N/M") -> 0.34370591 | G16: =IFERROR(G15/G$13,"N/M") -> 0.3199873 | H16: =IFERROR(H15/H$13,"N/M") -> 0.33184661 | I16: =IFERROR(I15/I$13,"N/M") -> 0.33184661 | J16: =IFERROR(J15/J$13,"N/M") -> 0.33184661 | K16: =IFERROR(K15/K$13,"N/M") -> 0.33184661 | L16: =IFERROR(L15/L$13,"N/M") -> 0.33184661 | M16: Calculate Gross Profit Margin (Gross Profit / Total Revenue)
C17: SG&A | F17: =SUM('Financials from CIP'!D23:D24,'Financials from CIP'!D28)/1000 -> 14.179915 | G17: =SUM('Financials from CIP'!E23:E24,'Financials from CIP'!E28)/1000 -> 15.436689 | H17: =H44*H13 -> 18.333217 | I17: =I44*I13 -> 21.144682 | J17: =J44*J13 -> 23.752955 | K17: =K44*K13 -> 25.97038 | L17: =L44*L13 -> 27.615698 | M17: SG&A typically has a part that is fixed (cost that does not fluctuate with revenue - like Rent) and a part that is Variable Cost. When I look at what the components of SG&A are using information from the 'Financials from CIP' tab, I see the majority of it is in Payroll & Related Expense - something that is most likely Variable. For simplicity sake, let's project SG&A in the business to be Variable. As such, project as a % of Sales based on the performance driver below
C18: EBITDA | F18: =F15-F17 -> 12.823572 | G18: =G15-G17 -> 13.558643 | H18: =H15-H17 -> 16.348071 | I18: =I15-I17 -> 18.855107 | J18: =J15-J17 -> 21.180953 | K18: =K15-K17 -> 23.158272 | L18: =L15-L17 -> 24.625432
C19: EBITDA Margin (%) | F19: =IFERROR(F18/F$13,"N/M") -> 0.16322105 | G19: =IFERROR(G18/G$13,"N/M") -> 0.14963076 | H19: =IFERROR(H18/H$13,"N/M") -> 0.15642591 | I19: =IFERROR(I18/I$13,"N/M") -> 0.15642591 | J19: =IFERROR(J18/J$13,"N/M") -> 0.15642591 | K19: =IFERROR(K18/K$13,"N/M") -> 0.15642591 | L19: =IFERROR(L18/L$13,"N/M") -> 0.15642591 | M19: Calculate EBITDA Margin (EBITDA / Total Revenue)
C20: Depreciation | F20: ='Financials from CIP'!D25/1000 -> 1.1801621 | G20: ='Financials from CIP'!E25/1000 -> 1.1617643 | H20: =H126 -> 5.5684984 | I20: =I126 -> 5.5684984 | J20: =J126 -> 5.5684984 | K20: =K126 -> 5.5684984 | L20: =L126 -> 5.5684984 | M20: See the schedule, below. Link total Depreciation per year from the schedule to here. Follow the Depreciation schedule instructions carefully
C21: Amortization | F21: ='Financials from CIP'!D26/1000 -> 0.208264 | G21: ='Financials from CIP'!E26/1000 -> 0.237952 | H21: =G21 -> 0.237952 | I21: =H21 -> 0.237952 | J21: =I21 -> 0.237952 | K21: =J21 -> 0.237952 | L21: =K21 -> 0.237952 | M21: Amortization Expense reduces Other Intangibles Assets on the Balance sheet. It is similar to Depreciation but for Assets that are not physical (like a copyright). For simplicity sake, let's hold the 2024 amount consistent per year going forward but be careful to not to amortize more than the Balance of the Other Intangible Assets in any given year. We will revisit this calculation to ensure its working properly in a later step
C22: EBIT | F22: =F18-SUM(F20:F21) -> 11.435146 | G22: =G18-SUM(G20:G21) -> 12.158927 | H22: =H18-SUM(H20:H21) -> 10.54162 | I22: =I18-SUM(I20:I21) -> 13.048656 | J22: =J18-SUM(J20:J21) -> 15.374502 | K22: =K18-SUM(K20:K21) -> 17.351821 | L22: =L18-SUM(L20:L21) -> 18.818982
C23: Interest (Income) / Expense
C24: Revolver – Interest
C25: Revolver – Undrawn Commitment Fee
C26: =+C79 -> Term Loan A
C27: =+C80 -> Subordinated - Note 1
C28: =+C81 -> Subordinated - Note 2
C29: Interest (Income) / Expense | F29: ='Financials from CIP'!D27/1000 -> 2.224955 | G29: ='Financials from CIP'!E27/1000 -> 1.472763 | H29: =SUM(H24:H28) -> 0 | I29: =SUM(I24:I28) -> 0 | J29: =SUM(J24:J28) -> 0 | K29: =SUM(K24:K28) -> 0 | L29: =SUM(L24:L28) -> 0
C30: Other (Income) / Expense | F30: ='Financials from CIP'!D32/1000 -> 0.147371 | G30: ='Financials from CIP'!E32/1000 -> 0.273439 | H30: 0 | I30: 0 | J30: 0 | K30: 0 | L30: 0 | M30: This is very low in 2023 and 2024. Let's assume it stays zero going forward
C31: Income Before Taxes | F31: =F22-F29-F30 -> 9.0628199 | G31: =G22-G29-G30 -> 10.412725 | H31: =H22-H29-H30 -> 10.54162 | I31: =I22-I29-I30 -> 13.048656 | J31: =J22-J29-J30 -> 15.374502 | K31: =K22-K29-K30 -> 17.351821 | L31: =L22-L29-L30 -> 18.818982
C32: Provision for Tax | F32: ='Financials from CIP'!D29/1000 -> 3.201039 | G32: ='Financials from CIP'!E29/1000 -> 2.809107 | H32: =H46*H31 -> 3.2836198 | I32: =I46*I31 -> 4.0645389 | J32: =J46*J31 -> 4.789019 | K32: =K46*K31 -> 5.404936 | L32: =L46*L31 -> 5.8619434 | M32: Calculate tax expense based on the tax rate below
C33: Net Income | F33: =F31-F32 -> 5.8617809 | G33: =G31-G32 -> 7.6036178 | H33: =H31-H32 -> 7.2580005 | I33: =I31-I32 -> 8.9841174 | J33: =J31-J32 -> 10.585483 | K33: =K31-K32 -> 11.946885 | L33: =L31-L32 -> 12.957038
C34: Profit Margin (%) | F34: =IFERROR(F33/F$13,"N/M") -> 0.074609947 | G34: =IFERROR(G33/G$13,"N/M") -> 0.083912167 | H34: =IFERROR(H33/H$13,"N/M") -> 0.069447907 | I34: =IFERROR(I33/I$13,"N/M") -> 0.074534115 | J34: =IFERROR(J33/J$13,"N/M") -> 0.078176078 | K34: =IFERROR(K33/K$13,"N/M") -> 0.080696969 | L34: =IFERROR(L33/L$13,"N/M") -> 0.082305823
C36: Capital Expenditures
C39: Key Performance Metrics & Drivers
C41: Sales Growth (%) | G41: =G13/F13-1 -> 0.15335363 | H41: =G41 -> 0.15335363 | I41: =H41 -> 0.15335363 | J41: =I41-3% -> 0.12335363 | K41: =J41-3% -> 0.093353635 | L41: =K41-3% -> 0.063353635 | M41: Round your 2024 growth rate to the nearest percent and use that for 2025 and 2026, reducing it by 3% per year thereafter
C43: COGS / Sales (%) | F43: =F14/F13 -> 0.65629409 | G43: =G14/G13 -> 0.6800127 | H43: =AVERAGE(F43:G43) -> 0.66815339 | I43: =H43 -> 0.66815339 | J43: =I43 -> 0.66815339 | K43: =J43 -> 0.66815339 | L43: =K43 -> 0.66815339 | M43: Divide by sales to get the % in 2023 and 2024. Use an average as your assumption and hold constant going forward
C44: SG&A / Sales (%) | F44: =F17/F13 -> 0.18048486 | G44: =G17/G13 -> 0.17035654 | H44: =AVERAGE(F44:G44) -> 0.1754207 | I44: =H44 -> 0.1754207 | J44: =I44 -> 0.1754207 | K44: =J44 -> 0.1754207 | L44: =K44 -> 0.1754207 | M44: Same as above
C46: Tax Rate (%) | F46: =F32/F31 -> 0.35320563 | G46: =G32/G31 -> 0.26977636 | H46: =AVERAGE(F46:G46) -> 0.31149099 | I46: =H46 -> 0.31149099 | J46: =I46 -> 0.31149099 | K46: =J46 -> 0.31149099 | L46: =K46 -> 0.31149099 | M46: Round the 2024 tax rate to the nearest % and use that going forward
C48: Capex / Sales (%)
B53: x | C53: Balance Sheet
F55: MRY | G55: MRY | H55: Fiscal Years Ending December 31,
C56: ($ in millions) | F56: =EOMONTH(G56,-12) -> 45291 | G56: =G$11 -> 45657 | H56: =H$11 -> 46022 | I56: =I$11 -> 46387 | J56: =J$11 -> 46752 | K56: =K$11 -> 47118 | L56: =L$11 -> 47483
C58: Assets
C60: Cash and Equivalents | F60: ='Financials from CIP'!D46/1000 -> 7.105652 | G60: ='Financials from CIP'!E46/1000 -> 2.957992
C61: Accounts Receivable, net | F61: =SUM('Financials from CIP'!D47:D48)/1000 -> 16.781419 | G61: =SUM('Financials from CIP'!E47:E48)/1000 -> 22.284722
C62: Inventory | F62: ='Financials from CIP'!D49/1000 -> 0.804901 | G62: ='Financials from CIP'!E49/1000 -> 1.161057
C63: Prepaids and Other Current Assets | F63: ='Financials from CIP'!D50/1000 -> 0.269784 | G63: ='Financials from CIP'!E50/1000 -> 0.344919
C64: Total Current Assets | F64: =SUM(F60:F63) -> 24.961756 | G64: =SUM(G60:G63) -> 26.74869
C65: PP&E, Gross
C66: ( – ) Accumulated Depreciation
C67: PP&E, Net | F67: ='Financials from CIP'!D53/1000 -> 54.5847 | G67: ='Financials from CIP'!E53/1000 -> 55.684984
C68: Goodwill | F68: 0 | G68: 0
C69: Intangible and Long-Term Other Assets | F69: ='Financials from CIP'!D54/1000 -> 4.378482 | G69: ='Financials from CIP'!E54/1000 -> 4.50437
C70: Total Assets | F70: =SUM(F64,F67:F69) -> 83.924938 | G70: =SUM(G64,G67:G69) -> 86.938044
C72: Liabilities & Shareholders' Equity
C74: Accounts Payable | F74: ='Financials from CIP'!D58/1000 -> 2.805817 | G74: ='Financials from CIP'!E58/1000 -> 2.36071
C75: Wages Payable | F75: ='Financials from CIP'!D59/1000 -> 2.383933 | G75: ='Financials from CIP'!E59/1000 -> 2.788038
C76: Accrued Expenses & Other | F76: ='Financials from CIP'!D60/1000 -> 2.057908 | G76: ='Financials from CIP'!E60/1000 -> 3.202031
C77: Total Current Liabilities | F77: =SUM(F74:F76) -> 7.247658 | G77: =SUM(G74:G76) -> 8.350779
C78: Revolver | F78: ='Financials from CIP'!D63/1000 -> 0.645883 | G78: ='Financials from CIP'!E63/1000 -> 1.2893
C79: Term Loan A | F79: ='Financials from CIP'!D64/1000 -> 18.943222 | G79: ='Financials from CIP'!E64/1000 -> 12.001451
C80: Subordinated - Note 1 | F80: ='Financials from CIP'!D65/1000 -> 0.545333 | G80: ='Financials from CIP'!E65/1000 -> 0.085338
C81: Subordinated - Note 2 | F81: ='Financials from CIP'!D66/1000 -> 0.092448 | G81: ='Financials from CIP'!E66/1000 -> 0.012667
C82: Total Debt | F82: =SUM(F78:F81) -> 20.226886 | G82: =SUM(G78:G81) -> 13.388756
C83: Other Long-term Liabilities | F83: ='Financials from CIP'!D67/1000 -> 0.417874 | G83: ='Financials from CIP'!E67/1000 -> 0.429888
C84: Total liabilities | F84: =SUM(F77,F82:F83) -> 27.892418 | G84: =SUM(G77,G82:G83) -> 22.169423
C85: Common Stock | F85: ='Financials from CIP'!D71/1000 -> 7.7836338 | G85: ='Financials from CIP'!E71/1000 -> 8.9161157
C86: Retained Earnings | F86: ='Financials from CIP'!D72/1000 -> 48.248887 | G86: ='Financials from CIP'!E72/1000 -> 55.852505
C87: Total Liabilities & Shareholders' Equity | F87: =SUM(F84:F86) -> 83.924939 | G87: =SUM(G84:G86) -> 86.938043
B92: x | C92: Checks to Source
C93: Income Statement
C94: Revenue | F94: ='Financials from CIP'!D13/1000-'Step 2 Answer Key'!F13 -> 0 | G94: ='Financials from CIP'!E13/1000-'Step 2 Answer Key'!G13 -> 0
C95: Gross Profit | F95: ='Financials from CIP'!D19/1000-'Step 2 Answer Key'!F15 -> 0 | G95: ='Financials from CIP'!E19/1000-'Step 2 Answer Key'!G15 -> 0
C96: EBITDA | F96: ='Financials from CIP'!D36/1000-'Step 2 Answer Key'!F18 -> 0 | G96: ='Financials from CIP'!E36/1000-'Step 2 Answer Key'!G18 -> 0
C97: Net Income | F97: ='Financials from CIP'!D34/1000-'Step 2 Answer Key'!F33 -> 0 | G97: ='Financials from CIP'!E34/1000-'Step 2 Answer Key'!G33 -> 0
C99: Balance Sheet
C100: Cash | F100: ='Financials from CIP'!D46/1000-'Step 2 Answer Key'!F60 -> 0 | G100: ='Financials from CIP'!E46/1000-'Step 2 Answer Key'!G60 -> 0
C101: Current Assets | F101: ='Financials from CIP'!D51/1000-'Step 2 Answer Key'!F64 -> 0 | G101: ='Financials from CIP'!E51/1000-'Step 2 Answer Key'!G64 -> 0
C102: Total Assets | F102: ='Financials from CIP'!D56/1000-'Step 2 Answer Key'!F70 -> 0 | G102: ='Financials from CIP'!E56/1000-'Step 2 Answer Key'!G70 -> 0
C103: Current Liabilities | F103: ='Financials from CIP'!D61/1000-'Step 2 Answer Key'!F77 -> 0 | G103: ='Financials from CIP'!E61/1000-'Step 2 Answer Key'!G77 -> 0
C104: Total Liabilities | F104: ='Financials from CIP'!D69/1000-'Step 2 Answer Key'!F84 -> 0 | G104: ='Financials from CIP'!E69/1000-'Step 2 Answer Key'!G84 -> 0
C105: Total Equity | F105: ='Financials from CIP'!D73/1000-SUM('Step 2 Answer Key'!F85:F86) -> 0 | G105: ='Financials from CIP'!E73/1000-SUM('Step 2 Answer Key'!G85:G86) -> 0
C107: Internal Checks
C108: A= L + E | F108: =F70-F87 -> -8.2790072e-07 | G108: =G70-G87 -> 5.041918e-07
B114: x | C114: Depreciation Schedule | M114: Depreciation is how much your long-term, physical assets (such as equipment) decrease in value each year. We have to know the cost of our the long-term, physical assets (CapEx) and then choose an "estimated life" to find the depreciation each year
H116: Fiscal Years Ending December 31,
C117: ($ in millions) | D117: PP&E to Depr | E117: SL Years (Est Life) | F117: Last Year | G117: Depr/Year | H117: =H$11 -> 46022 | I117: =I$11 -> 46387 | J117: =J$11 -> 46752 | K117: =K$11 -> 47118 | L117: =L$11 -> 47483
C119: =G11 -> 45657 | D119: =G67 -> 55.684984 | E119: 10 | F119: =-G20 -> -1.1617643 | G119: =IFERROR(-D119/E119,"N/M") -> -5.5684984 | H119: =-MIN(-$G119,$D119) -> -5.5684984 | I119: =-MIN(-$H119,SUM($H119:H119,$D119)) -> -5.5684984 | J119: =-MIN(-$H119,SUM($H119:I119,$D119)) -> -5.5684984 | K119: =-MIN(-$H119,SUM($H119:J119,$D119)) -> -5.5684984 | L119: =-MIN(-$H119,SUM($H119:K119,$D119)) -> -5.5684984 | M119: Link Amt to Depr to this year's capex. Straight line Depr for 10 more years. Use a rolling formula to determine what the amount should be each year - how much is left over vs annual depreciation per year. The first year formula can be written as: =-MIN(-$G119,$D119). Following that, we can write it as: =-MIN(-$H119,SUM($H119:H119,$D119))
C120: =H117 -> 46022
C121: =I117 -> 46387
C122: =J117 -> 46752
C123: =K117 -> 47118
C124: =L117 -> 47483
C126: Total Depr. | H126: =-SUM(H119:H125) -> 5.5684984 | I126: =-SUM(I119:I125) -> 5.5684984 | J126: =-SUM(J119:J125) -> 5.5684984 | K126: =-SUM(K119:K125) -> 5.5684984 | L126: =-SUM(L119:L125) -> 5.5684984

Sheet Step 3
C2: Athena Modeling Exercise
C3: Step 3 - Start the Balance Sheet
J5: Black font = Calculation
C6: YELLOWS ARE FILLS | F6: SKIP FOR NOW | J6: Blue font = Hardcoded Input/Assumption
J7: Green font = Pulled from another Sheet
B8: x | C8: Income Statement
F10: MRY | G10: MRY | H10: Fiscal Years Ending December 31,
C11: ($ in millions) | F11: =EOMONTH(G11,-12) -> 45291 | G11: 45657 | H11: =EOMONTH(G11,12) -> 46022 | I11: =EOMONTH(H11,12) -> 46387 | J11: =EOMONTH(I11,12) -> 46752 | K11: =EOMONTH(J11,12) -> 47118 | L11: =EOMONTH(K11,12) -> 47483
C13: Total Revenue | F13: ='Financials from CIP'!D13/1000 -> 78.565676 | G13: ='Financials from CIP'!E13/1000 -> 90.614008 | H13: =(1+H41)*G13 -> 104.51 | I13: =(1+I41)*H13 -> 120.53698 | J13: =(1+J41)*I13 -> 135.40566 | K13: =(1+K41)*J13 -> 148.04627 | L13: =(1+L41)*K13 -> 157.42554
C14: COGS | F14: =SUM('Financials from CIP'!D15:D17)/1000 -> 51.562189 | G14: =SUM('Financials from CIP'!E15:E17)/1000 -> 61.618676 | H14: =H43*H13 -> 69.828708 | I14: =I43*I13 -> 80.537195 | J14: =J43*J13 -> 90.47175 | K14: =K43*K13 -> 98.917617 | L14: =L43*L13 -> 105.18441
C15: Gross Profit | F15: =F13-F14 -> 27.003487 | G15: =G13-G14 -> 28.995332 | H15: =H13-H14 -> 34.681287 | I15: =I13-I14 -> 39.999789 | J15: =J13-J14 -> 44.933908 | K15: =K13-K14 -> 49.128652 | L15: =L13-L14 -> 52.24113
C16: Gross Margin (%) | F16: =IFERROR(F15/F$13,"N/M") -> 0.34370591 | G16: =IFERROR(G15/G$13,"N/M") -> 0.3199873 | H16: =IFERROR(H15/H$13,"N/M") -> 0.33184661 | I16: =IFERROR(I15/I$13,"N/M") -> 0.33184661 | J16: =IFERROR(J15/J$13,"N/M") -> 0.33184661 | K16: =IFERROR(K15/K$13,"N/M") -> 0.33184661 | L16: =IFERROR(L15/L$13,"N/M") -> 0.33184661
C17: SG&A | F17: =SUM('Financials from CIP'!D23:D24,'Financials from CIP'!D28)/1000 -> 14.179915 | G17: =SUM('Financials from CIP'!E23:E24,'Financials from CIP'!E28)/1000 -> 15.436689 | H17: =H44*H13 -> 18.333217 | I17: =I44*I13 -> 21.144682 | J17: =J44*J13 -> 23.752955 | K17: =K44*K13 -> 25.97038 | L17: =L44*L13 -> 27.615698
C18: EBITDA | F18: =F15-F17 -> 12.823572 | G18: =G15-G17 -> 13.558643 | H18: =H15-H17 -> 16.348071 | I18: =I15-I17 -> 18.855107 | J18: =J15-J17 -> 21.180953 | K18: =K15-K17 -> 23.158272 | L18: =L15-L17 -> 24.625432
C19: EBITDA Margin (%) | F19: =IFERROR(F18/F$13,"N/M") -> 0.16322105 | G19: =IFERROR(G18/G$13,"N/M") -> 0.14963076 | H19: =IFERROR(H18/H$13,"N/M") -> 0.15642591 | I19: =IFERROR(I18/I$13,"N/M") -> 0.15642591 | J19: =IFERROR(J18/J$13,"N/M") -> 0.15642591 | K19: =IFERROR(K18/K$13,"N/M") -> 0.15642591 | L19: =IFERROR(L18/L$13,"N/M") -> 0.15642591
C20: Depreciation | F20: ='Financials from CIP'!D25/1000 -> 1.1801621 | G20: ='Financials from CIP'!E25/1000 -> 1.1617643 | H20: =H126 -> 5.5684984 | I20: =I126 -> 5.5684984 | J20: =J126 -> 5.5684984 | K20: =K126 -> 5.5684984 | L20: =L126 -> 5.5684984
C21: Amortization | F21: ='Financials from CIP'!D26/1000 -> 0.208264 | G21: ='Financials from CIP'!E26/1000 -> 0.237952 | H21: =MIN(G21,G69) -> 0.237952 | I21: =MIN(H21,H69) -> 0.237952 | J21: =MIN(I21,I69) -> 0.237952 | K21: =MIN(J21,J69) -> 0.237952 | L21: =MIN(K21,K69) -> 0.237952
C22: EBIT | F22: =F18-SUM(F20:F21) -> 11.435146 | G22: =G18-SUM(G20:G21) -> 12.158927 | H22: =H18-SUM(H20:H21) -> 10.54162 | I22: =I18-SUM(I20:I21) -> 13.048656 | J22: =J18-SUM(J20:J21) -> 15.374502 | K22: =K18-SUM(K20:K21) -> 17.351821 | L22: =L18-SUM(L20:L21) -> 18.818982
C23: Interest (Income) / Expense
C24: Revolver – Interest
C25: Revolver – Undrawn Commitment Fee
C26: =+C79 -> Term Loan A
C27: =+C80 -> Subordinated - Note 1
C28: =+C81 -> Subordinated - Note 2
C29: Interest (Income) / Expense | F29: ='Financials from CIP'!D27/1000 -> 2.224955 | G29: ='Financials from CIP'!E27/1000 -> 1.472763 | H29: =SUM(H24:H28) -> 0 | I29: =SUM(I24:I28) -> 0 | J29: =SUM(J24:J28) -> 0 | K29: =SUM(K24:K28) -> 0 | L29: =SUM(L24:L28) -> 0
C30: Other (Income) / Expense | F30: ='Financials from CIP'!D32/1000 -> 0.147371 | G30: ='Financials from CIP'!E32/1000 -> 0.273439 | H30: 0 | I30: 0 | J30: 0 | K30: 0 | L30: 0
C31: Income Before Taxes | F31: =F22-F29-F30 -> 9.0628199 | G31: =G22-G29-G30 -> 10.412725 | H31: =H22-H29-H30 -> 10.54162 | I31: =I22-I29-I30 -> 13.048656 | J31: =J22-J29-J30 -> 15.374502 | K31: =K22-K29-K30 -> 17.351821 | L31: =L22-L29-L30 -> 18.818982
C32: Provision for Tax | F32: ='Financials from CIP'!D29/1000 -> 3.201039 | G32: ='Financials from CIP'!E29/1000 -> 2.809107 | H32: =H46*H31 -> 3.2836198 | I32: =I46*I31 -> 4.0645389 | J32: =J46*J31 -> 4.789019 | K32: =K46*K31 -> 5.404936 | L32: =L46*L31 -> 5.8619434
C33: Net Income | F33: =F31-F32 -> 5.8617809 | G33: =G31-G32 -> 7.6036178 | H33: =H31-H32 -> 7.2580005 | I33: =I31-I32 -> 8.9841174 | J33: =J31-J32 -> 10.585483 | K33: =K31-K32 -> 11.946885 | L33: =L31-L32 -> 12.957038
C34: Profit Margin (%) | F34: =IFERROR(F33/F$13,"N/M") -> 0.074609947 | G34: =IFERROR(G33/G$13,"N/M") -> 0.083912167 | H34: =IFERROR(H33/H$13,"N/M") -> 0.069447907 | I34: =IFERROR(I33/I$13,"N/M") -> 0.074534115 | J34: =IFERROR(J33/J$13,"N/M") -> 0.078176078 | K34: =IFERROR(K33/K$13,"N/M") -> 0.080696969 | L34: =IFERROR(L33/L$13,"N/M") -> 0.082305823
C36: Capital Expenditures | M36: CapEx is the cost of equipment that is "capitalized" on your Balance Sheet because it lasts more than one year. Let's assume we buy more equipment as we grow and make it a Variable cost. As such, project as a % of Sales based on the performance driver below
C39: Key Performance Metrics & Drivers
C41: Sales Growth (%) | G41: =G13/F13-1 -> 0.15335363 | H41: =G41 -> 0.15335363 | I41: =H41 -> 0.15335363 | J41: =I41-3% -> 0.12335363 | K41: =J41-3% -> 0.093353635 | L41: =K41-3% -> 0.063353635
C43: COGS / Sales (%) | F43: =F14/F13 -> 0.65629409 | G43: =G14/G13 -> 0.6800127 | H43: =AVERAGE(F43:G43) -> 0.66815339 | I43: =H43 -> 0.66815339 | J43: =I43 -> 0.66815339 | K43: =J43 -> 0.66815339 | L43: =K43 -> 0.66815339
C44: SG&A / Sales (%) | F44: =F17/F13 -> 0.18048486 | G44: =G17/G13 -> 0.17035654 | H44: =AVERAGE(F44:G44) -> 0.1754207 | I44: =H44 -> 0.1754207 | J44: =I44 -> 0.1754207 | K44: =J44 -> 0.1754207 | L44: =K44 -> 0.1754207
C46: Tax Rate (%) | F46: =F32/F31 -> 0.35320563 | G46: =G32/G31 -> 0.26977636 | H46: =AVERAGE(F46:G46) -> 0.31149099 | I46: =H46 -> 0.31149099 | J46: =I46 -> 0.31149099 | K46: =J46 -> 0.31149099 | L46: =K46 -> 0.31149099
C48: Capex / Sales (%) | M48: Let's start by finding CapEx in 2024. We can do that by looking at the change in PP&E, net - using the information given to us in the 'Financials from CIP' tab, and removing the effect of Depreciation. Then, I can divide the CapEx I calculate by Sales to get the % in 2024. Use this as your assumption and hold constant going forward
B53: x | C53: Balance Sheet
F55: MRY | G55: MRY | H55: Fiscal Years Ending December 31,
C56: ($ in millions) | F56: =EOMONTH(G56,-12) -> 45291 | G56: =G$11 -> 45657 | H56: =H$11 -> 46022 | I56: =I$11 -> 46387 | J56: =J$11 -> 46752 | K56: =K$11 -> 47118 | L56: =L$11 -> 47483
C58: Assets
C60: Cash and Equivalents | F60: ='Financials from CIP'!D46/1000 -> 7.105652 | G60: ='Financials from CIP'!E46/1000 -> 2.957992
C61: Accounts Receivable, net | F61: =SUM('Financials from CIP'!D47:D48)/1000 -> 16.781419 | G61: =SUM('Financials from CIP'!E47:E48)/1000 -> 22.284722
C62: Inventory | F62: ='Financials from CIP'!D49/1000 -> 0.804901 | G62: ='Financials from CIP'!E49/1000 -> 1.161057
C63: Prepaids and Other Current Assets | F63: ='Financials from CIP'!D50/1000 -> 0.269784 | G63: ='Financials from CIP'!E50/1000 -> 0.344919
C64: Total Current Assets | F64: =SUM(F60:F63) -> 24.961756 | G64: =SUM(G60:G63) -> 26.74869 | H64: =SUM(H60:H63) -> 0 | I64: =SUM(I60:I63) -> 0 | J64: =SUM(J60:J63) -> 0 | K64: =SUM(K60:K63) -> 0 | L64: =SUM(L60:L63) -> 0
C65: PP&E, Gross | M65: PP&E stands for Property, Plant and Equipment (aka, long-term, physical assets). CapEx is the amount spent on long-term, physical assets that will last longer than 1 year. This is the GROSS amount, aka the TOTAL amount. As such, we add Capital Expenditures for the current year to Gross PP&E from the prior year to get our new aggregate PP&E. The result is an aggregation of all the CapEx we have spent (unless we sell an long-term, physical asset... but let's skip that for now)
C66: ( – ) Accumulated Depreciation | M66: When we buy physical assets, there is "wear and tear" making the value of the physical assets go down. This is decrease in value is called and it goes against PP&E, Gross to get to the "Net Amount." Add Depreciation (from the P&L) for the current year to Accumulated Depreciation (from the Balance Sheet) from the prior year. We want to show this as a negative balance because we will be reducing Gross PP&E by this amount - a Contra Asset
C67: PP&E, Net | F67: ='Financials from CIP'!D53/1000 -> 54.5847 | G67: ='Financials from CIP'!E53/1000 -> 55.684984 | H67: =SUM(H65:H66) -> 0 | I67: =SUM(I65:I66) -> 0 | J67: =SUM(J65:J66) -> 0 | K67: =SUM(K65:K66) -> 0 | L67: =SUM(L65:L66) -> 0
C68: Goodwill | F68: 0 | G68: 0 | M68: Goodwill is the amount of excess that someone pays for your company, above the fair value of assumed Assets less the fair value of assumed Liabilities when they purchase it. We will revisit this later. For now, let's assume it stays consistent each period and stays constant at zero
C69: Intangible and Long-Term Other Assets | F69: ='Financials from CIP'!D54/1000 -> 4.378482 | G69: ='Financials from CIP'!E54/1000 -> 4.50437 | M69: For future periods, Other Intangible Assets will be amortized by the current year amortization (from the Income Statement). Revisit your formula for Amortization on the P&L and make sure its not causing this balance to go negative. Once this balance reaches zero there is nothing left to amortize
C70: Total Assets | F70: =SUM(F64,F67:F69) -> 83.924938 | G70: =SUM(G64,G67:G69) -> 86.938044 | H70: =SUM(H64,H67:H69) -> 0 | I70: =SUM(I64,I67:I69) -> 0 | J70: =SUM(J64,J67:J69) -> 0 | K70: =SUM(K64,K67:K69) -> 0 | L70: =SUM(L64,L67:L69) -> 0
C72: Liabilities & Shareholders' Equity
C74: Accounts Payable | F74: ='Financials from CIP'!D58/1000 -> 2.805817 | G74: ='Financials from CIP'!E58/1000 -> 2.36071
C75: Wages Payable | F75: ='Financials from CIP'!D59/1000 -> 2.383933 | G75: ='Financials from CIP'!E59/1000 -> 2.788038
C76: Accrued Expenses & Other | F76: ='Financials from CIP'!D60/1000 -> 2.057908 | G76: ='Financials from CIP'!E60/1000 -> 3.202031
C77: Total Current Liabilities | F77: =SUM(F74:F76) -> 7.247658 | G77: =SUM(G74:G76) -> 8.350779 | H77: =SUM(H74:H76) -> 0 | I77: =SUM(I74:I76) -> 0 | J77: =SUM(J74:J76) -> 0 | K77: =SUM(K74:K76) -> 0 | L77: =SUM(L74:L76) -> 0
C78: Revolver | F78: ='Financials from CIP'!D63/1000 -> 0.645883 | G78: ='Financials from CIP'!E63/1000 -> 1.2893
C79: Term Loan A | F79: ='Financials from CIP'!D64/1000 -> 18.943222 | G79: ='Financials from CIP'!E64/1000 -> 12.001451
C80: Subordinated - Note 1 | F80: ='Financials from CIP'!D65/1000 -> 0.545333 | G80: ='Financials from CIP'!E65/1000 -> 0.085338
C81: Subordinated - Note 2 | F81: ='Financials from CIP'!D66/1000 -> 0.092448 | G81: ='Financials from CIP'!E66/1000 -> 0.012667
C82: Total Debt | F82: =SUM(F78:F81) -> 20.226886 | G82: =SUM(G78:G81) -> 13.388756 | H82: =SUM(H78:H81) -> 0 | I82: =SUM(I78:I81) -> 0 | J82: =SUM(J78:J81) -> 0 | K82: =SUM(K78:K81) -> 0 | L82: =SUM(L78:L81) -> 0
C83: Other Long-term Liabilities | F83: ='Financials from CIP'!D67/1000 -> 0.417874 | G83: ='Financials from CIP'!E67/1000 -> 0.429888 | M83: For simplicity, let's hold Other Long-Term Liabilities constant for the future periods. It looks like it won't change much given the history that I have and I am not sure what it is unless I ask for more details
C84: Total liabilities | F84: =SUM(F77,F82:F83) -> 27.892418 | G84: =SUM(G77,G82:G83) -> 22.169423 | H84: =SUM(H77,H82:H83) -> 0 | I84: =SUM(I77,I82:I83) -> 0 | J84: =SUM(J77,J82:J83) -> 0 | K84: =SUM(K77,K82:K83) -> 0 | L84: =SUM(L77,L82:L83) -> 0
C85: Common Stock | F85: ='Financials from CIP'!D71/1000 -> 7.7836338 | G85: ='Financials from CIP'!E71/1000 -> 8.9161157 | M85: Common Stock is the value of what you OWN in the business - Equity, another word for ownership. Equity goes up when we have Net Income or Issue stock and goes down if we have a Net Loss or give out a Dividend (paying Cash to owners). Let's assume that this will stay constant - no new stock issuances, no dividends, no stock buybacks
C86: Retained Earnings | F86: ='Financials from CIP'!D72/1000 -> 48.248887 | G86: ='Financials from CIP'!E72/1000 -> 55.852505 | M86: When we connect WHAT happened (Income Statement) to our Balance Sheet (HOW it affects our ownership), we connect the Income Statement (above) to the Balance Sheet, through Net Income and Retained Earnings. This is a key connection to all financial statements. As we have Net Income or a Net Loss each year, we take the previous year's Retained Earnings and add Net Income for the current year
C87: Total Liabilities & Shareholders' Equity | F87: =SUM(F84:F86) -> 83.924939 | G87: =SUM(G84:G86) -> 86.938043 | H87: =SUM(H84:H86) -> 0 | I87: =SUM(I84:I86) -> 0 | J87: =SUM(J84:J86) -> 0 | K87: =SUM(K84:K86) -> 0 | L87: =SUM(L84:L86) -> 0
C89: Check (should be zero) | M89: Subtract total Assets and Total Liabilities and Shareholder's Equity from each other as a check that will come in handy later. Italicize and show out 3 decimal places. Don't worry it will not balance yet.
B92: x | C92: Checks to Source
C93: Income Statement
C94: Revenue | F94: ='Financials from CIP'!D13/1000-'Step 3'!F13 -> 0 | G94: ='Financials from CIP'!E13/1000-'Step 3'!G13 -> 0
C95: Gross Profit | F95: ='Financials from CIP'!D19/1000-'Step 3'!F15 -> 0 | G95: ='Financials from CIP'!E19/1000-'Step 3'!G15 -> 0
C96: EBITDA | F96: ='Financials from CIP'!D36/1000-'Step 3'!F18 -> 0 | G96: ='Financials from CIP'!E36/1000-'Step 3'!G18 -> 0
C97: Net Income | F97: ='Financials from CIP'!D34/1000-'Step 3'!F33 -> 0 | G97: ='Financials from CIP'!E34/1000-'Step 3'!G33 -> 0
C99: Balance Sheet
C100: Cash | F100: ='Financials from CIP'!D46/1000-'Step 3'!F60 -> 0 | G100: ='Financials from CIP'!E46/1000-'Step 3'!G60 -> 0
C101: Current Assets | F101: ='Financials from CIP'!D51/1000-'Step 3'!F64 -> 0 | G101: ='Financials from CIP'!E51/1000-'Step 3'!G64 -> 0
C102: Total Assets | F102: ='Financials from CIP'!D56/1000-'Step 3'!F70 -> 0 | G102: ='Financials from CIP'!E56/1000-'Step 3'!G70 -> 0
C103: Current Liabilities | F103: ='Financials from CIP'!D61/1000-'Step 3'!F77 -> 0 | G103: ='Financials from CIP'!E61/1000-'Step 3'!G77 -> 0
C104: Total Liabilities | F104: ='Financials from CIP'!D69/1000-'Step 3'!F84 -> 0 | G104: ='Financials from CIP'!E69/1000-'Step 3'!G84 -> 0
C105: Total Equity | F105: ='Financials from CIP'!D73/1000-SUM('Step 3'!F85:F86) -> 0 | G105: ='Financials from CIP'!E73/1000-SUM('Step 3'!G85:G86) -> 0
C107: Internal Checks
C108: A= L + E | F108: =F70-F87 -> -8.2790072e-07 | G108: =G70-G87 -> 5.041918e-07
B114: x | C114: Depreciation Schedule | M114: Depreciation is how much your long-term, physical assets (such as equipment) decrease in value each year. We have to know the cost of our the long-term, physical assets (CapEx) and then choose an "estimated life" to find the depreciation each year
H116: Fiscal Years Ending December 31,
C117: ($ in millions) | D117: PP&E to Depr | E117: SL Years (Est Life) | F117: Last Year | G117: Depr/Year | H117: =H$11 -> 46022 | I117: =I$11 -> 46387 | J117: =J$11 -> 46752 | K117: =K$11 -> 47118 | L117: =L$11 -> 47483
C119: =G11 -> 45657 | D119: =G67 -> 55.684984 | E119: 10 | F119: =-G20 -> -1.1617643 | G119: =IFERROR(-D119/E119,"N/M") -> -5.5684984 | H119: =-MIN(-$G119,$D119) -> -5.5684984 | I119: =-MIN(-$H119,SUM($H119:H119,$D119)) -> -5.5684984 | J119: =-MIN(-$H119,SUM($H119:I119,$D119)) -> -5.5684984 | K119: =-MIN(-$H119,SUM($H119:J119,$D119)) -> -5.5684984 | L119: =-MIN(-$H119,SUM($H119:K119,$D119)) -> -5.5684984
C120: =H117 -> 46022 | M120: Link Amt to Depr to this year's CapEx. Straight line Depr for 10 years - remember to watch the year it starts based on when the CapEx was incurred. Use the same formulas as we did on line 119, using the first year formula in the first year, and the next years' formulas after that
C121: =I117 -> 46387 | M121: Link Amt to Depr to this year's CapEx. Straight line Depr for 10 years - remember to watch the year it starts based on when the CapEx was incurred. Use the same formulas as we did on line 119, using the first year formula in the first year, and the next years' formulas after that
C122: =J117 -> 46752 | M122: Link Amt to Depr to this year's CapEx. Straight line Depr for 10 years - remember to watch the year it starts based on when the CapEx was incurred. Use the same formulas as we did on line 119, using the first year formula in the first year, and the next years' formulas after that
C123: =K117 -> 47118 | M123: Link Amt to Depr to this year's CapEx. Straight line Depr for 10 years - remember to watch the year it starts based on when the CapEx was incurred. Use the same formulas as we did on line 119, using the first year formula in the first year, and the next years' formulas after that
C124: =L117 -> 47483 | M124: Link Amt to Depr to this year's CapEx. Straight line Depr for 10 years - remember to watch the year it starts based on when the CapEx was incurred. Use the same formulas as we did on line 119, using the first year formula in the first year, and the next years' formulas after that
C126: Total Depr. | H126: =-SUM(H119:H125) -> 5.5684984 | I126: =-SUM(I119:I125) -> 5.5684984 | J126: =-SUM(J119:J125) -> 5.5684984 | K126: =-SUM(K119:K125) -> 5.5684984 | L126: =-SUM(L119:L125) -> 5.5684984
