Workbook

Sheet PART I - MODEL BUILD >>>

Sheet Financials from CIP
B3: Project Athena
B4: Quarterly and Annual Financial Statements
B5: ($s in 000s)
B7: Income Statement
D9: FY | E9: FY
D10: 2023 | E10: 2024
B11: Service Revenues | D11: 67988.162 | E11: 74320.332
B12: Parts & Other | D12: 10577.514 | E12: 16293.676
B13: Total Revenue | D13: =+SUM(D11:D12) -> 78565.676 | E13: =+SUM(E11:E12) -> 90614.008
B15: Labor | D15: 41584.93 | E15: 49665.089
B16: Materials | D16: 8321.468 | E16: 9548.864
B17: Other CoGS | D17: 1655.791 | E17: 2404.723
B19: Total Gross Profit | D19: =+D13-SUM(D15:D18) -> 27003.487 | E19: =+E13-SUM(E15:E18) -> 28995.332
B21: Total Gross Margin % | D21: =+D19/D$13 -> 0.34370591 | E21: =+E19/E$13 -> 0.3199873
B23: Payroll & Related Expenses | D23: 10567.613 | E23: 11023.057
B24: Rent & Occupancy | D24: 3246.147 | E24: 4150.1989
B25: Depreciation | D25: 1180.1621 | E25: 1161.7643
B26: Amortization | D26: 208.264 | E26: 237.952
B27: Interest | D27: 2224.955 | E27: 1472.763
B28: Other SG&A | D28: 366.155 | E28: 263.433
B29: Income Taxes | D29: 3201.039 | E29: 2809.107
B30: Total SG&A | D30: =+SUM(D23:D29) -> 20994.335 | E30: =+SUM(E23:E29) -> 21118.275
B32: Other Expense (Income) | D32: 147.371 | E32: 273.439
B34: Net Income | D34: =+D19-D30-D32 -> 5861.7809 | E34: =+E19-E30-E32 -> 7603.6178
B36: EBITDA, Unadjusted | D36: =+D34+D25+D27+D29+D26+D32 -> 12823.572 | E36: =+E34+E25+E27+E29+E26+E32 -> 13558.643
B39: Total Profit Margin % | D39: =D34/D$13 -> 0.074609947 | E39: =E34/E$13 -> 0.083912167
B40: Total EBITDA Margin % | D40: =D36/D$13 -> 0.16322105 | E40: =E36/E$13 -> 0.14963076
B42: Balance Sheet
D44: YE | E44: YE
D45: =+D10 -> 2023 | E45: =+D45+1 -> 2024
B46: Cash & Cash Equivalents | D46: 7105.652 | E46: 2957.992
B47: Accounts Receivable, Gross | D47: 17300.432 | E47: 22973.94
B48: Allowance for Doubtful Accounts | D48: -519.013 | E48: -689.218
B49: Inventory | D49: 804.901 | E49: 1161.057
B50: Prepaids & Other | D50: 269.784 | E50: 344.919
B51: Total Current Assets | D51: =+SUM(D46:D50) -> 24961.756 | E51: =+SUM(E46:E50) -> 26748.69
B53: PP&E, Net | D53: 54584.7 | E53: 55684.984
B54: Long-Term Intangible Assets | D54: 4378.482 | E54: 4504.37
B56: Total Assets | D56: =+SUM(D51:D55) -> 83924.938 | E56: =+SUM(E51:E55) -> 86938.044
B58: Accounts Payable | D58: 2805.817 | E58: 2360.71
B59: Wages Payable | D59: 2383.933 | E59: 2788.038
B60: Accrued Expenses & Other | D60: 2057.908 | E60: 3202.031
B61: Total Current Liabilities | D61: =+SUM(D58:D60) -> 7247.658 | E61: =+SUM(E58:E60) -> 8350.779
B63: Revolver | D63: 645.883 | E63: 1289.3
B64: Term Loan A | D64: 18943.222 | E64: 12001.451
B65: Subordinated Debt - Note 1 | D65: 545.333 | E65: 85.338
B66: Subordinated Debt - Note 2 | D66: 92.448 | E66: 12.667
B67: Other Long-Term Liabilities | D67: 417.874 | E67: 429.888
B69: Total Liabilities | D69: =+SUM(D61:D68) -> 27892.418 | E69: =+SUM(E61:E68) -> 22169.423
B71: Common Stock | D71: 7783.6338 | E71: 8916.1157
B72: Retained Earnings | D72: 48248.887 | E72: 55852.505
B73: Total Equity | D73: =+SUM(D71:D72) -> 56032.521 | E73: =+SUM(E71:E72) -> 64768.62
B76: Total Liabilities and Equity | D76: =+D73+D69 -> 83924.939 | E76: =+E73+E69 -> 86938.043
B78: Net Working Capital | D78: =D51-D61 -> 17714.098 | E78: =E51-E61 -> 18397.911
B79: Net Working Capital, less Cash | D79: =(D51-D46)-D61 -> 10608.446 | E79: =(E51-E46)-E61 -> 15439.919
B81: Check | D81: =+D76-D56 -> 0.00082790072 | E81: =+E76-E56 -> -0.0005041918

Sheet Step 1
C2: Athena Modeling Exercise
C3: Step 1 - Historicals
J5: Black font = Calculation
C6: YELLOWS ARE FILLS | F6: SKIP FOR NOW | J6: Blue font = Hardcoded Input/Assumption
J7: Green font = Pulled from another Sheet
B8: x | C8: Income Statement | M8: Use the historical financial statements (Income Statement and Balance Sheet) to get started. Copy the financial statements as they appear from your research
F10: MRY | G10: MRY | H10: Fiscal Years Ending December 31,
C11: ($ in millions) | F11: =EOMONTH(G11,-12) -> 45291 | G11: 45657 | H11: =EOMONTH(G11,12) -> 46022 | I11: =EOMONTH(H11,12) -> 46387 | J11: =EOMONTH(I11,12) -> 46752 | K11: =EOMONTH(J11,12) -> 47118 | L11: =EOMONTH(K11,12) -> 47483
C13: Total Revenue
C14: COGS
C15: Gross Profit | F15: =F13-F14 -> 0 | G15: =G13-G14 -> 0
C16: Gross Margin (%) | F16: =IFERROR(F15/F$13,"N/M") -> N/M | G16: =IFERROR(G15/G$13,"N/M") -> N/M
C17: SG&A
C18: EBITDA | F18: =F15-F17 -> 0 | G18: =G15-G17 -> 0
C19: EBITDA Margin (%) | F19: =IFERROR(F18/F$13,"N/M") -> N/M | G19: =IFERROR(G18/G$13,"N/M") -> N/M
C20: Depreciation
C21: Amortization
C22: EBIT | F22: =F18-SUM(F20:F21) -> 0 | G22: =G18-SUM(G20:G21) -> 0
C23: Interest (Income) / Expense
C24: Revolver – Interest
C25: Revolver – Undrawn Commitment Fee
C26: =+C66 -> Term Loan A
C27: =+C67 -> Subordinated - Note 1
C28: =+C68 -> Subordinated - Note 2
C29: Interest (Income) / Expense
C30: Other (Income) / Expense
C31: Income Before Taxes | F31: =F22-F29-F30 -> 0 | G31: =G22-G29-G30 -> 0
C32: Provision for Tax
C33: Net Income | F33: =F31-F32 -> 0 | G33: =G31-G32 -> 0
C34: Profit Margin (%) | F34: =IFERROR(F33/F$13,"N/M") -> N/M | G34: =IFERROR(G33/G$13,"N/M") -> N/M
C36: Capital Expenditures
B40: x | C40: Balance Sheet
F42: MRY | G42: MRY | H42: Fiscal Years Ending December 31,
C43: ($ in millions) | F43: =EOMONTH(G43,-12) -> 45291 | G43: =G$11 -> 45657 | H43: =H$11 -> 46022 | I43: =I$11 -> 46387 | J43: =J$11 -> 46752 | K43: =K$11 -> 47118 | L43: =L$11 -> 47483
C45: Assets
C47: Cash and Equivalents
C48: Accounts Receivable, net
C49: Inventory
C50: Prepaids and Other Current Assets
C51: Total Current Assets | F51: =SUM(F47:F50) -> 0 | G51: =SUM(G47:G50) -> 0
C52: PP&E, Gross
C53: ( – ) Accumulated Depreciation
C54: PP&E, Net
C55: Goodwill | F55: 0 | G55: 0
C56: Intangible and Long-Term Other Assets
C57: Total Assets | F57: =SUM(F51,F54:F56) -> 0 | G57: =SUM(G51,G54:G56) -> 0
C59: Liabilities & Shareholders' Equity
C61: Accounts Payable
C62: Wages Payable
C63: Accrued Expenses & Other
C64: Total Current Liabilities | F64: =SUM(F61:F63) -> 0 | G64: =SUM(G61:G63) -> 0
C65: Revolver
C66: Term Loan A
C67: Subordinated - Note 1
C68: Subordinated - Note 2
C69: Total Debt | F69: =SUM(F65:F68) -> 0 | G69: =SUM(G65:G68) -> 0
C70: Other Long-term Liabilities
C71: Total liabilities | F71: =SUM(F64,F69:F70) -> 0 | G71: =SUM(G64,G69:G70) -> 0
C72: Common Stock
C73: Retained Earnings
C74: Total Liabilities & Shareholders' Equity | F74: =SUM(F71:F73) -> 0 | G74: =SUM(G71:G73) -> 0
B79: x | C79: Checks to Source
C80: Income Statement
C81: Revenue
C82: Gross Profit
C83: EBITDA
C84: Net Income
C86: Balance Sheet
C87: Cash
C88: Current Assets
C89: Total Assets
C90: Current Liabilities
C91: Total Liabilities
C92: Total Equity
... C95: A= L + E

Sheet Step 1 Answer Key
C2: Athena Modeling Exercise
C3: Step 1 - Historicals
J5: Black font = Calculation
C6: YELLOWS ARE FILLS | F6: SKIP FOR NOW | J6: Blue font = Hardcoded Input/Assumption
J7: Green font = Pulled from another Sheet
B8: x | C8: Income Statement | M8: Use the historical financial statements (Income Statement and Balance Sheet) to get started. Copy the financial statements as they appear from your research
F10: MRY | G10: MRY | H10: Fiscal Years Ending December 31,
C11: ($ in millions) | F11: =EOMONTH(G11,-12) -> 45291 | G11: 45657 | H11: =EOMONTH(G11,12) -> 46022 | I11: =EOMONTH(H11,12) -> 46387 | J11: =EOMONTH(I11,12) -> 46752 | K11: =EOMONTH(J11,12) -> 47118 | L11: =EOMONTH(K11,12) -> 47483
C13: Total Revenue | F13: ='Financials from CIP'!D13/1000 -> 78.565676 | G13: ='Financials from CIP'!E13/1000 -> 90.614008
C14: COGS | F14: =SUM('Financials from CIP'!D15:D17)/1000 -> 51.562189 | G14: =SUM('Financials from CIP'!E15:E17)/1000 -> 61.618676
C15: Gross Profit | F15: =F13-F14 -> 27.003487 | G15: =G13-G14 -> 28.995332
C16: Gross Margin (%) | F16: =IFERROR(F15/F$13,"N/M") -> 0.34370591 | G16: =IFERROR(G15/G$13,"N/M") -> 0.3199873
C17: SG&A | F17: =SUM('Financials from CIP'!D23:D24,'Financials from CIP'!D28)/1000 -> 14.179915 | G17: =SUM('Financials from CIP'!E23:E24,'Financials from CIP'!E28)/1000 -> 15.436689
C18: EBITDA | F18: =F15-F17 -> 12.823572 | G18: =G15-G17 -> 13.558643
C19: EBITDA Margin (%) | F19: =IFERROR(F18/F$13,"N/M") -> 0.16322105 | G19: =IFERROR(G18/G$13,"N/M") -> 0.14963076
C20: Depreciation | F20: ='Financials from CIP'!D25/1000 -> 1.1801621 | G20: ='Financials from CIP'!E25/1000 -> 1.1617643
C21: Amortization | F21: ='Financials from CIP'!D26/1000 -> 0.208264 | G21: ='Financials from CIP'!E26/1000 -> 0.237952
C22: EBIT | F22: =F18-SUM(F20:F21) -> 11.435146 | G22: =G18-SUM(G20:G21) -> 12.158927
C23: Interest (Income) / Expense
C24: Revolver – Interest
C25: Revolver – Undrawn Commitment Fee
C26: =+C66 -> Term Loan A
C27: =+C67 -> Subordinated - Note 1
C28: =+C68 -> Subordinated - Note 2
C29: Interest (Income) / Expense | F29: ='Financials from CIP'!D27/1000 -> 2.224955 | G29: ='Financials from CIP'!E27/1000 -> 1.472763
C30: Other (Income) / Expense | F30: ='Financials from CIP'!D32/1000 -> 0.147371 | G30: ='Financials from CIP'!E32/1000 -> 0.273439
C31: Income Before Taxes | F31: =F22-F29-F30 -> 9.0628199 | G31: =G22-G29-G30 -> 10.412725
C32: Provision for Tax | F32: ='Financials from CIP'!D29/1000 -> 3.201039 | G32: ='Financials from CIP'!E29/1000 -> 2.809107
C33: Net Income | F33: =F31-F32 -> 5.8617809 | G33: =G31-G32 -> 7.6036178
C34: Profit Margin (%) | F34: =IFERROR(F33/F$13,"N/M") -> 0.074609947 | G34: =IFERROR(G33/G$13,"N/M") -> 0.083912167
C36: Capital Expenditures
B40: x | C40: Balance Sheet
F42: MRY | G42: MRY | H42: Fiscal Years Ending December 31,
C43: ($ in millions) | F43: =EOMONTH(G43,-12) -> 45291 | G43: =G$11 -> 45657 | H43: =H$11 -> 46022 | I43: =I$11 -> 46387 | J43: =J$11 -> 46752 | K43: =K$11 -> 47118 | L43: =L$11 -> 47483
C45: Assets
C47: Cash and Equivalents | F47: ='Financials from CIP'!D46/1000 -> 7.105652 | G47: ='Financials from CIP'!E46/1000 -> 2.957992
C48: Accounts Receivable, net | F48: =SUM('Financials from CIP'!D47:D48)/1000 -> 16.781419 | G48: =SUM('Financials from CIP'!E47:E48)/1000 -> 22.284722
C49: Inventory | F49: ='Financials from CIP'!D49/1000 -> 0.804901 | G49: ='Financials from CIP'!E49/1000 -> 1.161057
C50: Prepaids and Other Current Assets | F50: ='Financials from CIP'!D50/1000 -> 0.269784 | G50: ='Financials from CIP'!E50/1000 -> 0.344919
C51: Total Current Assets | F51: =SUM(F47:F50) -> 24.961756 | G51: =SUM(G47:G50) -> 26.74869
C52: PP&E, Gross
C53: ( – ) Accumulated Depreciation
C54: PP&E, Net | F54: ='Financials from CIP'!D53/1000 -> 54.5847 | G54: ='Financials from CIP'!E53/1000 -> 55.684984
C55: Goodwill | F55: 0 | G55: 0
C56: Intangible and Long-Term Other Assets | F56: ='Financials from CIP'!D54/1000 -> 4.378482 | G56: ='Financials from CIP'!E54/1000 -> 4.50437
C57: Total Assets | F57: =SUM(F51,F54:F56) -> 83.924938 | G57: =SUM(G51,G54:G56) -> 86.938044
C59: Liabilities & Shareholders' Equity
C61: Accounts Payable | F61: ='Financials from CIP'!D58/1000 -> 2.805817 | G61: ='Financials from CIP'!E58/1000 -> 2.36071
C62: Wages Payable | F62: ='Financials from CIP'!D59/1000 -> 2.383933 | G62: ='Financials from CIP'!E59/1000 -> 2.788038
C63: Accrued Expenses & Other | F63: ='Financials from CIP'!D60/1000 -> 2.057908 | G63: ='Financials from CIP'!E60/1000 -> 3.202031
C64: Total Current Liabilities | F64: =SUM(F61:F63) -> 7.247658 | G64: =SUM(G61:G63) -> 8.350779
C65: Revolver | F65: ='Financials from CIP'!D63/1000 -> 0.645883 | G65: ='Financials from CIP'!E63/1000 -> 1.2893
C66: Term Loan A | F66: ='Financials from CIP'!D64/1000 -> 18.943222 | G66: ='Financials from CIP'!E64/1000 -> 12.001451
C67: Subordinated - Note 1 | F67: ='Financials from CIP'!D65/1000 -> 0.545333 | G67: ='Financials from CIP'!E65/1000 -> 0.085338
C68: Subordinated - Note 2 | F68: ='Financials from CIP'!D66/1000 -> 0.092448 | G68: ='Financials from CIP'!E66/1000 -> 0.012667
C69: Total Debt | F69: =SUM(F65:F68) -> 20.226886 | G69: =SUM(G65:G68) -> 13.388756
C70: Other Long-term Liabilities | F70: ='Financials from CIP'!D67/1000 -> 0.417874 | G70: ='Financials from CIP'!E67/1000 -> 0.429888
C71: Total liabilities | F71: =SUM(F64,F69:F70) -> 27.892418 | G71: =SUM(G64,G69:G70) -> 22.169423
C72: Common Stock | F72: ='Financials from CIP'!D71/1000 -> 7.7836338 | G72: ='Financials from CIP'!E71/1000 -> 8.9161157
C73: Retained Earnings | F73: ='Financials from CIP'!D72/1000 -> 48.248887 | G73: ='Financials from CIP'!E72/1000 -> 55.852505
C74: Total Liabilities & Shareholders' Equity | F74: =SUM(F71:F73) -> 83.924939 | G74: =SUM(G71:G73) -> 86.938043
B79: x | C79: Checks to Source
C80: Income Statement
C81: Revenue | F81: ='Financials from CIP'!D13/1000-'Step 1 Answer Key'!F13 -> 0 | G81: ='Financials from CIP'!E13/1000-'Step 1 Answer Key'!G13 -> 0
C82: Gross Profit | F82: ='Financials from CIP'!D19/1000-'Step 1 Answer Key'!F15 -> 0 | G82: ='Financials from CIP'!E19/1000-'Step 1 Answer Key'!G15 -> 0
C83: EBITDA | F83: ='Financials from CIP'!D36/1000-'Step 1 Answer Key'!F18 -> 0 | G83: ='Financials from CIP'!E36/1000-'Step 1 Answer Key'!G18 -> 0
C84: Net Income | F84: ='Financials from CIP'!D34/1000-'Step 1 Answer Key'!F33 -> 0 | G84: ='Financials from CIP'!E34/1000-'Step 1 Answer Key'!G33 -> 0
C86: Balance Sheet
C87: Cash | F87: ='Financials from CIP'!D46/1000-'Step 1 Answer Key'!F47 -> 0 | G87: ='Financials from CIP'!E46/1000-'Step 1 Answer Key'!G47 -> 0
C88: Current Assets | F88: ='Financials from CIP'!D51/1000-'Step 1 Answer Key'!F51 -> 0 | G88: ='Financials from CIP'!E51/1000-'Step 1 Answer Key'!G51 -> 0
C89: Total Assets | F89: ='Financials from CIP'!D56/1000-'Step 1 Answer Key'!F57 -> 0 | G89: ='Financials from CIP'!E56/1000-'Step 1 Answer Key'!G57 -> 0
C90: Current Liabilities | F90: ='Financials from CIP'!D61/1000-'Step 1 Answer Key'!F64 -> 0 | G90: ='Financials from CIP'!E61/1000-'Step 1 Answer Key'!G64 -> 0
C91: Total Liabilities | F91: ='Financials from CIP'!D69/1000-'Step 1 Answer Key'!F71 -> 0 | G91: ='Financials from CIP'!E69/1000-'Step 1 Answer Key'!G71 -> 0
C92: Total Equity | F92: ='Financials from CIP'!D73/1000-SUM('Step 1 Answer Key'!F72:F73) -> 0 | G92: ='Financials from CIP'!E73/1000-SUM('Step 1 Answer Key'!G72:G73) -> 0
C94: Internal Checks
C95: A= L + E | F95: =F57-F74 -> -8.2790072e-07 | G95: =G57-G74 -> 5.041918e-07

Sheet Step 2
C2: Athena Modeling Exercise
C3: Step 2 - Begin Projecting the Income Statement
J5: Black font = Calculation
C6: YELLOWS ARE FILLS | F6: SKIP FOR NOW | J6: Blue font = Hardcoded Input/Assumption
J7: Green font = Pulled from another Sheet
B8: x | C8: Income Statement
F10: MRY | G10: MRY | H10: Fiscal Years Ending December 31,
C11: ($ in millions) | F11: =EOMONTH(G11,-12) -> 45291 | G11: 45657 | H11: =EOMONTH(G11,12) -> 46022 | I11: =EOMONTH(H11,12) -> 46387 | J11: =EOMONTH(I11,12) -> 46752 | K11: =EOMONTH(J11,12) -> 47118 | L11: =EOMONTH(K11,12) -> 47483
C13: Total Revenue | F13: ='Financials from CIP'!D13/1000 -> 78.565676 | G13: ='Financials from CIP'!E13/1000 -> 90.614008 | M13: Revenue is grown year-over-year. Project total revenue based on the growth rate assumption below and the prior period revenue (line 41)
C14: COGS | F14: =SUM('Financials from CIP'!D15:D17)/1000 -> 51.562189 | G14: =SUM('Financials from CIP'!E15:E17)/1000 -> 61.618676 | M14: CoGS typically fluctuates with Revenue - it is the cost of the goods and services we sell. We call this a "Variable Cost." As such, project as a % of Sales based on the performance driver below - that way CoGS moves with Revenue
C15: Gross Profit | F15: =F13-F14 -> 27.003487 | G15: =G13-G14 -> 28.995332 | H15: =H13-H14 -> 0 | I15: =I13-I14 -> 0 | J15: =J13-J14 -> 0 | K15: =K13-K14 -> 0 | L15: =L13-L14 -> 0
C16: Gross Margin (%) | F16: =IFERROR(F15/F$13,"N/M") -> 0.34370591 | G16: =IFERROR(G15/G$13,"N/M") -> 0.3199873 | H16: =IFERROR(H15/H$13,"N/M") -> N/M | I16: =IFERROR(I15/I$13,"N/M") -> N/M | J16: =IFERROR(J15/J$13,"N/M") -> N/M | K16: =IFERROR(K15/K$13,"N/M") -> N/M | L16: =IFERROR(L15/L$13,"N/M") -> N/M | M16: Calculate Gross Profit Margin (Gross Profit / Total Revenue)
C17: SG&A | F17: =SUM('Financials from CIP'!D23:D24,'Financials from CIP'!D28)/1000 -> 14.179915 | G17: =SUM('Financials from CIP'!E23:E24,'Financials from CIP'!E28)/1000 -> 15.436689 | M17: SG&A typically has a part that is fixed (cost that does not fluctuate with revenue - like Rent) and a part that is Variable Cost. When I look at what the components of SG&A are using information from the 'Financials from CIP' tab, I see the majority of it is in Payroll & Related Expense - something that is most likely Variable. For simplicity sake, let's project SG&A in the business to be Variable. As such, project as a % of Sales based on the performance driver below
C18: EBITDA | F18: =F15-F17 -> 12.823572 | G18: =G15-G17 -> 13.558643 | H18: =H15-H17 -> 0 | I18: =I15-I17 -> 0 | J18: =J15-J17 -> 0 | K18: =K15-K17 -> 0 | L18: =L15-L17 -> 0
C19: EBITDA Margin (%) | F19: =IFERROR(F18/F$13,"N/M") -> 0.16322105 | G19: =IFERROR(G18/G$13,"N/M") -> 0.14963076 | H19: =IFERROR(H18/H$13,"N/M") -> N/M | I19: =IFERROR(I18/I$13,"N/M") -> N/M | J19: =IFERROR(J18/J$13,"N/M") -> N/M | K19: =IFERROR(K18/K$13,"N/M") -> N/M | L19: =IFERROR(L18/L$13,"N/M") -> N/M | M19: Calculate EBITDA Margin (EBITDA / Total Revenue)
C20: Depreciation | F20: ='Financials from CIP'!D25/1000 -> 1.1801621 | G20: ='Financials from CIP'!E25/1000 -> 1.1617643 | M20: See the schedule, below. Link total Depreciation per year from the schedule to here. Follow the Depreciation schedule instructions carefully
C21: Amortization | F21: ='Financials from CIP'!D26/1000 -> 0.208264 | G21: ='Financials from CIP'!E26/1000 -> 0.237952 | M21: Amortization Expense reduces Other Intangibles Assets on the Balance sheet. It is similar to Depreciation but for Assets that are not physical (like a copyright). For simplicity sake, let's hold the 2024 amount consistent per year going forward but be careful to not to amortize more than the Balance of the Other Intangible Assets in any given year. We will revisit this calculation to ensure its working properly in a later step
C22: EBIT | F22: =F18-SUM(F20:F21) -> 11.435146 | G22: =G18-SUM(G20:G21) -> 12.158927 | H22: =H18-SUM(H20:H21) -> 0 | I22: =I18-SUM(I20:I21) -> 0 | J22: =J18-SUM(J20:J21) -> 0 | K22: =K18-SUM(K20:K21) -> 0 | L22: =L18-SUM(L20:L21) -> 0
C23: Interest (Income) / Expense
C24: Revolver – Interest
C25: Revolver – Undrawn Commitment Fee
C26: =+C79 -> Term Loan A
C27: =+C80 -> Subordinated - Note 1
C28: =+C81 -> Subordinated - Note 2
C29: Interest (Income) / Expense | F29: ='Financials from CIP'!D27/1000 -> 2.224955 | G29: ='Financials from CIP'!E27/1000 -> 1.472763 | H29: =SUM(H24:H28) -> 0 | I29: =SUM(I24:I28) -> 0 | J29: =SUM(J24:J28) -> 0 | K29: =SUM(K24:K28) -> 0 | L29: =SUM(L24:L28) -> 0
C30: Other (Income) / Expense | F30: ='Financials from CIP'!D32/1000 -> 0.147371 | G30: ='Financials from CIP'!E32/1000 -> 0.273439 | M30: This is very low in 2023 and 2024. Let's assume it stays zero going forward
C31: Income Before Taxes | F31: =F22-F29-F30 -> 9.0628199 | G31: =G22-G29-G30 -> 10.412725 | H31: =H22-H29-H30 -> 0 | I31: =I22-I29-I30 -> 0 | J31: =J22-J29-J30 -> 0 | K31: =K22-K29-K30 -> 0 | L31: =L22-L29-L30 -> 0
C32: Provision for Tax | F32: ='Financials from CIP'!D29/1000 -> 3.201039 | G32: ='Financials from CIP'!E29/1000 -> 2.809107 | M32: Calculate tax expense based on the tax rate below
C33: Net Income | F33: =F31-F32 -> 5.8617809 | G33: =G31-G32 -> 7.6036178 | H33: =H31-H32 -> 0 | I33: =I31-I32 -> 0 | J33: =J31-J32 -> 0 | K33: =K31-K32 -> 0 | L33: =L31-L32 -> 0
C34: Profit Margin (%) | F34: =IFERROR(F33/F$13,"N/M") -> 0.074609947 | G34: =IFERROR(G33/G$13,"N/M") -> 0.083912167 | H34: =IFERROR(H33/H$13,"N/M") -> N/M | I34: =IFERROR(I33/I$13,"N/M") -> N/M | J34: =IFERROR(J33/J$13,"N/M") -> N/M | K34: =IFERROR(K33/K$13,"N/M") -> N/M | L34: =IFERROR(L33/L$13,"N/M") -> N/M
C36: Capital Expenditures
C39: Key Performance Metrics & Drivers
C41: Sales Growth (%) | M41: Round your 2024 growth rate to the nearest percent and use that for 2025 and 2026, reducing it by 3% per year thereafter
C43: COGS / Sales (%) | M43: Divide by sales to get the % in 2023 and 2024. Use an average as your assumption and hold constant going forward
C44: SG&A / Sales (%) | M44: Same as above
C46: Tax Rate (%) | M46: Round the 2024 tax rate to the nearest % and use that going forward
C48: Capex / Sales (%)
B53: x | C53: Balance Sheet
F55: MRY | G55: MRY | H55: Fiscal Years Ending December 31,
C56: ($ in millions) | F56: =EOMONTH(G56,-12) -> 45291 | G56: =G$11 -> 45657 | H56: =H$11 -> 46022 | I56: =I$11 -> 46387 | J56: =J$11 -> 46752 | K56: =K$11 -> 47118 | L56: =L$11 -> 47483
C58: Assets
C60: Cash and Equivalents | F60: ='Financials from CIP'!D46/1000 -> 7.105652 | G60: ='Financials from CIP'!E46/1000 -> 2.957992
C61: Accounts Receivable, net | F61: =SUM('Financials from CIP'!D47:D48)/1000 -> 16.781419 | G61: =SUM('Financials from CIP'!E47:E48)/1000 -> 22.284722
C62: Inventory | F62: ='Financials from CIP'!D49/1000 -> 0.804901 | G62: ='Financials from CIP'!E49/1000 -> 1.161057
C63: Prepaids and Other Current Assets | F63: ='Financials from CIP'!D50/1000 -> 0.269784 | G63: ='Financials from CIP'!E50/1000 -> 0.344919
C64: Total Current Assets | F64: =SUM(F60:F63) -> 24.961756 | G64: =SUM(G60:G63) -> 26.74869
C65: PP&E, Gross
C66: ( – ) Accumulated Depreciation
C67: PP&E, Net | F67: ='Financials from CIP'!D53/1000 -> 54.5847 | G67: ='Financials from CIP'!E53/1000 -> 55.684984
C68: Goodwill | F68: 0 | G68: 0
C69: Intangible and Long-Term Other Assets | F69: ='Financials from CIP'!D54/1000 -> 4.378482 | G69: ='Financials from CIP'!E54/1000 -> 4.50437
C70: Total Assets | F70: =SUM(F64,F67:F69) -> 83.924938 | G70: =SUM(G64,G67:G69) -> 86.938044
C72: Liabilities & Shareholders' Equity
C74: Accounts Payable | F74: ='Financials from CIP'!D58/1000 -> 2.805817 | G74: ='Financials from CIP'!E58/1000 -> 2.36071
C75: Wages Payable | F75: ='Financials from CIP'!D59/1000 -> 2.383933 | G75: ='Financials from CIP'!E59/1000 -> 2.788038
C76: Accrued Expenses & Other | F76: ='Financials from CIP'!D60/1000 -> 2.057908 | G76: ='Financials from CIP'!E60/1000 -> 3.202031
C77: Total Current Liabilities | F77: =SUM(F74:F76) -> 7.247658 | G77: =SUM(G74:G76) -> 8.350779
C78: Revolver | F78: ='Financials from CIP'!D63/1000 -> 0.645883 | G78: ='Financials from CIP'!E63/1000 -> 1.2893
C79: Term Loan A | F79: ='Financials from CIP'!D64/1000 -> 18.943222 | G79: ='Financials from CIP'!E64/1000 -> 12.001451
C80: Subordinated - Note 1 | F80: ='Financials from CIP'!D65/1000 -> 0.545333 | G80: ='Financials from CIP'!E65/1000 -> 0.085338
C81: Subordinated - Note 2 | F81: ='Financials from CIP'!D66/1000 -> 0.092448 | G81: ='Financials from CIP'!E66/1000 -> 0.012667
C82: Total Debt | F82: =SUM(F78:F81) -> 20.226886 | G82: =SUM(G78:G81) -> 13.388756
C83: Other Long-term Liabilities | F83: ='Financials from CIP'!D67/1000 -> 0.417874 | G83: ='Financials from CIP'!E67/1000 -> 0.429888
C84: Total liabilities | F84: =SUM(F77,F82:F83) -> 27.892418 | G84: =SUM(G77,G82:G83) -> 22.169423
C85: Common Stock | F85: ='Financials from CIP'!D71/1000 -> 7.7836338 | G85: ='Financials from CIP'!E71/1000 -> 8.9161157
C86: Retained Earnings | F86: ='Financials from CIP'!D72/1000 -> 48.248887 | G86: ='Financials from CIP'!E72/1000 -> 55.852505
C87: Total Liabilities & Shareholders' Equity | F87: =SUM(F84:F86) -> 83.924939 | G87: =SUM(G84:G86) -> 86.938043
B92: x | C92: Checks to Source
C93: Income Statement
C94: Revenue | F94: ='Financials from CIP'!D13/1000-'Step 2'!F13 -> 0 | G94: ='Financials from CIP'!E13/1000-'Step 2'!G13 -> 0
C95: Gross Profit | F95: ='Financials from CIP'!D19/1000-'Step 2'!F15 -> 0 | G95: ='Financials from CIP'!E19/1000-'Step 2'!G15 -> 0
C96: EBITDA | F96: ='Financials from CIP'!D36/1000-'Step 2'!F18 -> 0 | G96: ='Financials from CIP'!E36/1000-'Step 2'!G18 -> 0
C97: Net Income | F97: ='Financials from CIP'!D34/1000-'Step 2'!F33 -> 0 | G97: ='Financials from CIP'!E34/1000-'Step 2'!G33 -> 0
C99: Balance Sheet
C100: Cash | F100: ='Financials from CIP'!D46/1000-'Step 2'!F60 -> 0 | G100: ='Financials from CIP'!E46/1000-'Step 2'!G60 -> 0
C101: Current Assets | F101: ='Financials from CIP'!D51/1000-'Step 2'!F64 -> 0 | G101: ='Financials from CIP'!E51/1000-'Step 2'!G64 -> 0
C102: Total Assets | F102: ='Financials from CIP'!D56/1000-'Step 2'!F70 -> 0 | G102: ='Financials from CIP'!E56/1000-'Step 2'!G70 -> 0
C103: Current Liabilities | F103: ='Financials from CIP'!D61/1000-'Step 2'!F77 -> 0 | G103: ='Financials from CIP'!E61/1000-'Step 2'!G77 -> 0
C104: Total Liabilities | F104: ='Financials from CIP'!D69/1000-'Step 2'!F84 -> 0 | G104: ='Financials from CIP'!E69/1000-'Step 2'!G84 -> 0
C105: Total Equity | F105: ='Financials from CIP'!D73/1000-SUM('Step 2'!F85:F86) -> 0 | G105: ='Financials from CIP'!E73/1000-SUM('Step 2'!G85:G86) -> 0
C107: Internal Checks
C108: A= L + E | F108: =F70-F87 -> -8.2790072e-07 | G108: =G70-G87 -> 5.041918e-07
B114: x | C114: Depreciation Schedule | M114: Depreciation is how much your long-term, physical assets (such as equipment) decrease in value each year. We have to know the cost of our the long-term, physical assets (CapEx) and then choose an "estimated life" to find the depreciation each year
H116: Fiscal Years Ending December 31,
C117: ($ in millions) | D117: PP&E to Depr | E117: SL Years (Est Life) | F117: Last Year | G117: Depr/Year | H117: =H$11 -> 46022 | I117: =I$11 -> 46387 | J117: =J$11 -> 46752 | K117: =K$11 -> 47118 | L117: =L$11 -> 47483
C119: =G11 -> 45657 | D119: =G67 -> 55.684984 | F119: =-G20 -> -1.1617643 | G119: =IFERROR(-D119/E119,"N/M") -> N/M | M119: Link Amt to Depr to this year's capex. Straight line Depr for 10 more years. Use a rolling formula to determine what the amount should be each year - how much is left over vs annual depreciation per year. The first year formula can be written as: =-MIN(-$G119,$D119). Following that, we can write it as: =-MIN(-$H119,SUM($H119:H119,$D119))
C120: =H117 -> 46022
C121: =I117 -> 46387
C122: =J117 -> 46752
C123: =K117 -> 47118
C124: =L117 -> 47483
C126: Total Depr. | H126: =-SUM(H119:H125) -> 0 | I126: =-SUM(I119:I125) -> 0 | J126: =-SUM(J119:J125) -> 0 | K126: =-SUM(K119:K125) -> 0 | L126: =-SUM(L119:L125) -> 0

Sheet Step 2 Answer Key
C2: Athena Modeling Exercise
C3: Step 2 - Begin Projecting the Income Statement
J5: Black font = Calculation
C6: YELLOWS ARE FILLS | F6: SKIP FOR NOW | J6: Blue font = Hardcoded Input/Assumption
J7: Green font = Pulled from another Sheet
B8: x | C8: Income Statement
F10: MRY | G10: MRY | H10: Fiscal Years Ending December 31,
C11: ($ in millions) | F11: =EOMONTH(G11,-12) -> 45291 | G11: 45657 | H11: =EOMONTH(G11,12) -> 46022 | I11: =EOMONTH(H11,12) -> 46387 | J11: =EOMONTH(I11,12) -> 46752 | K11: =EOMONTH(J11,12) -> 47118 | L11: =EOMONTH(K11,12) -> 47483
C13: Total Revenue | F13: ='Financials from CIP'!D13/1000 -> 78.565676 | G13: ='Financials from CIP'!E13/1000 -> 90.614008 | H13: =(1+H41)*G13 -> 104.51 | I13: =(1+I41)*H13 -> 120.53698 | J13: =(1+J41)*I13 -> 135.40566 | K13: =(1+K41)*J13 -> 148.04627 | L13: =(1+L41)*K13 -> 157.42554 | M13: Revenue is grown year-over-year. Project total revenue based on the growth rate assumption below and the prior period revenue (line 41)
C14: COGS | F14: =SUM('Financials from CIP'!D15:D17)/1000 -> 51.562189 | G14: =SUM('Financials from CIP'!E15:E17)/1000 -> 61.618676 | H14: =H43*H13 -> 69.828708 | I14: =I43*I13 -> 80.537195 | J14: =J43*J13 -> 90.47175 | K14: =K43*K13 -> 98.917617 | L14: =L43*L13 -> 105.18441 | M14: CoGS typically fluctuates with Revenue - it is the cost of the goods and services we sell. We call this a "Variable Cost." As such, project as a % of Sales based on the performance driver below - that way CoGS moves with Revenue
C15: Gross Profit | F15: =F13-F14 -> 27.003487 | G15: =G13-G14 -> 28.995332 | H15: =H13-H14 -> 34.681287 | I15: =I13-I14 -> 39.999789 | J15: =J13-J14 -> 44.933908 | K15: =K13-K14 -> 49.128652 | L15: =L13-L14 -> 52.24113
C16: Gross Margin (%) | F16: =IFERROR(F15/F$13,"N/M") -> 0.34370591 | G16: =IFERROR(G15/G$13,"N/M") -> 0.3199873 | H16: =IFERROR(H15/H$13,"N/M") -> 0.33184661 | I16: =IFERROR(I15/I$13,"N/M") -> 0.33184661 | J16: =IFERROR(J15/J$13,"N/M") -> 0.33184661 | K16: =IFERROR(K15/K$13,"N/M") -> 0.33184661 | L16: =IFERROR(L15/L$13,"N/M") -> 0.33184661 | M16: Calculate Gross Profit Margin (Gross Profit / Total Revenue)
C17: SG&A | F17: =SUM('Financials from CIP'!D23:D24,'Financials from CIP'!D28)/1000 -> 14.179915 | G17: =SUM('Financials from CIP'!E23:E24,'Financials from CIP'!E28)/1000 -> 15.436689 | H17: =H44*H13 -> 18.333217 | I17: =I44*I13 -> 21.144682 | J17: =J44*J13 -> 23.752955 | K17: =K44*K13 -> 25.97038 | L17: =L44*L13 -> 27.615698 | M17: SG&A typically has a part that is fixed (cost that does not fluctuate with revenue - like Rent) and a part that is Variable Cost. When I look at what the components of SG&A are using information from the 'Financials from CIP' tab, I see the majority of it is in Payroll & Related Expense - something that is most likely Variable. For simplicity sake, let's project SG&A in the business to be Variable. As such, project as a % of Sales based on the performance driver below
C18: EBITDA | F18: =F15-F17 -> 12.823572 | G18: =G15-G17 -> 13.558643 | H18: =H15-H17 -> 16.348071 | I18: =I15-I17 -> 18.855107 | J18: =J15-J17 -> 21.180953 | K18: =K15-K17 -> 23.158272 | L18: =L15-L17 -> 24.625432
C19: EBITDA Margin (%) | F19: =IFERROR(F18/F$13,"N/M") -> 0.16322105 | G19: =IFERROR(G18/G$13,"N/M") -> 0.14963076 | H19: =IFERROR(H18/H$13,"N/M") -> 0.15642591 | I19: =IFERROR(I18/I$13,"N/M") -> 0.15642591 | J19: =IFERROR(J18/J$13,"N/M") -> 0.15642591 | K19: =IFERROR(K18/K$13,"N/M") -> 0.15642591 | L19: =IFERROR(L18/L$13,"N/M") -> 0.15642591 | M19: Calculate EBITDA Margin (EBITDA / Total Revenue)
C20: Depreciation | F20: ='Financials from CIP'!D25/1000 -> 1.1801621 | G20: ='Financials from CIP'!E25/1000 -> 1.1617643 | H20: =H126 -> 5.5684984 | I20: =I126 -> 5.5684984 | J20: =J126 -> 5.5684984 | K20: =K126 -> 5.5684984 | L20: =L126 -> 5.5684984 | M20: See the schedule, below. Link total Depreciation per year from the schedule to here. Follow the Depreciation schedule instructions carefully
C21: Amortization | F21: ='Financials from CIP'!D26/1000 -> 0.208264 | G21: ='Financials from CIP'!E26/1000 -> 0.237952 | H21: =G21 -> 0.237952 | I21: =H21 -> 0.237952 | J21: =I21 -> 0.237952 | K21: =J21 -> 0.237952 | L21: =K21 -> 0.237952 | M21: Amortization Expense reduces Other Intangibles Assets on the Balance sheet. It is similar to Depreciation but for Assets that are not physical (like a copyright). For simplicity sake, let's hold the 2024 amount consistent per year going forward but be careful to not to amortize more than the Balance of the Other Intangible Assets in any given year. We will revisit this calculation to ensure its working properly in a later step
C22: EBIT | F22: =F18-SUM(F20:F21) -> 11.435146 | G22: =G18-SUM(G20:G21) -> 12.158927 | H22: =H18-SUM(H20:H21) -> 10.54162 | I22: =I18-SUM(I20:I21) -> 13.048656 | J22: =J18-SUM(J20:J21) -> 15.374502 | K22: =K18-SUM(K20:K21) -> 17.351821 | L22: =L18-SUM(L20:L21) -> 18.818982
C23: Interest (Income) / Expense
C24: Revolver – Interest
C25: Revolver – Undrawn Commitment Fee
C26: =+C79 -> Term Loan A
C27: =+C80 -> Subordinated - Note 1
C28: =+C81 -> Subordinated - Note 2
C29: Interest (Income) / Expense | F29: ='Financials from CIP'!D27/1000 -> 2.224955 | G29: ='Financials from CIP'!E27/1000 -> 1.472763 | H29: =SUM(H24:H28) -> 0 | I29: =SUM(I24:I28) -> 0 | J29: =SUM(J24:J28) -> 0 | K29: =SUM(K24:K28) -> 0 | L29: =SUM(L24:L28) -> 0
C30: Other (Income) / Expense | F30: ='Financials from CIP'!D32/1000 -> 0.147371 | G30: ='Financials from CIP'!E32/1000 -> 0.273439 | H30: 0 | I30: 0 | J30: 0 | K30: 0 | L30: 0 | M30: This is very low in 2023 and 2024. Let's assume it stays zero going forward
C31: Income Before Taxes | F31: =F22-F29-F30 -> 9.0628199 | G31: =G22-G29-G30 -> 10.412725 | H31: =H22-H29-H30 -> 10.54162 | I31: =I22-I29-I30 -> 13.048656 | J31: =J22-J29-J30 -> 15.374502 | K31: =K22-K29-K30 -> 17.351821 | L31: =L22-L29-L30 -> 18.818982
C32: Provision for Tax | F32: ='Financials from CIP'!D29/1000 -> 3.201039 | G32: ='Financials from CIP'!E29/1000 -> 2.809107 | H32: =H46*H31 -> 3.2836198 | I32: =I46*I31 -> 4.0645389 | J32: =J46*J31 -> 4.789019 | K32: =K46*K31 -> 5.404936 | L32: =L46*L31 -> 5.8619434 | M32: Calculate tax expense based on the tax rate below
C33: Net Income | F33: =F31-F32 -> 5.8617809 | G33: =G31-G32 -> 7.6036178 | H33: =H31-H32 -> 7.2580005 | I33: =I31-I32 -> 8.9841174 | J33: =J31-J32 -> 10.585483 | K33: =K31-K32 -> 11.946885 | L33: =L31-L32 -> 12.957038
C34: Profit Margin (%) | F34: =IFERROR(F33/F$13,"N/M") -> 0.074609947 | G34: =IFERROR(G33/G$13,"N/M") -> 0.083912167 | H34: =IFERROR(H33/H$13,"N/M") -> 0.069447907 | I34: =IFERROR(I33/I$13,"N/M") -> 0.074534115 | J34: =IFERROR(J33/J$13,"N/M") -> 0.078176078 | K34: =IFERROR(K33/K$13,"N/M") -> 0.080696969 | L34: =IFERROR(L33/L$13,"N/M") -> 0.082305823
C36: Capital Expenditures
C39: Key Performance Metrics & Drivers
C41: Sales Growth (%) | G41: =G13/F13-1 -> 0.15335363 | H41: =G41 -> 0.15335363 | I41: =H41 -> 0.15335363 | J41: =I41-3% -> 0.12335363 | K41: =J41-3% -> 0.093353635 | L41: =K41-3% -> 0.063353635 | M41: Round your 2024 growth rate to the nearest percent and use that for 2025 and 2026, reducing it by 3% per year thereafter
C43: COGS / Sales (%) | F43: =F14/F13 -> 0.65629409 | G43: =G14/G13 -> 0.6800127 | H43: =AVERAGE(F43:G43) -> 0.66815339 | I43: =H43 -> 0.66815339 | J43: =I43 -> 0.66815339 | K43: =J43 -> 0.66815339 | L43: =K43 -> 0.66815339 | M43: Divide by sales to get the % in 2023 and 2024. Use an average as your assumption and hold constant going forward
C44: SG&A / Sales (%) | F44: =F17/F13 -> 0.18048486 | G44: =G17/G13 -> 0.17035654 | H44: =AVERAGE(F44:G44) -> 0.1754207 | I44: =H44 -> 0.1754207 | J44: =I44 -> 0.1754207 | K44: =J44 -> 0.1754207 | L44: =K44 -> 0.1754207 | M44: Same as above
C46: Tax Rate (%) | F46: =F32/F31 -> 0.35320563 | G46: =G32/G31 -> 0.26977636 | H46: =AVERAGE(F46:G46) -> 0.31149099 | I46: =H46 -> 0.31149099 | J46: =I46 -> 0.31149099 | K46: =J46 -> 0.31149099 | L46: =K46 -> 0.31149099 | M46: Round the 2024 tax rate to the nearest % and use that going forward
C48: Capex / Sales (%)
B53: x | C53: Balance Sheet
F55: MRY | G55: MRY | H55: Fiscal Years Ending December 31,
C56: ($ in millions) | F56: =EOMONTH(G56,-12) -> 45291 | G56: =G$11 -> 45657 | H56: =H$11 -> 46022 | I56: =I$11 -> 46387 | J56: =J$11 -> 46752 | K56: =K$11 -> 47118 | L56: =L$11 -> 47483
C58: Assets
C60: Cash and Equivalents | F60: ='Financials from CIP'!D46/1000 -> 7.105652 | G60: ='Financials from CIP'!E46/1000 -> 2.957992
C61: Accounts Receivable, net | F61: =SUM('Financials from CIP'!D47:D48)/1000 -> 16.781419 | G61: =SUM('Financials from CIP'!E47:E48)/1000 -> 22.284722
C62: Inventory | F62: ='Financials from CIP'!D49/1000 -> 0.804901 | G62: ='Financials from CIP'!E49/1000 -> 1.161057
C63: Prepaids and Other Current Assets | F63: ='Financials from CIP'!D50/1000 -> 0.269784 | G63: ='Financials from CIP'!E50/1000 -> 0.344919
C64: Total Current Assets | F64: =SUM(F60:F63) -> 24.961756 | G64: =SUM(G60:G63) -> 26.74869
C65: PP&E, Gross
C66: ( – ) Accumulated Depreciation
C67: PP&E, Net | F67: ='Financials from CIP'!D53/1000 -> 54.5847 | G67: ='Financials from CIP'!E53/1000 -> 55.684984
C68: Goodwill | F68: 0 | G68: 0
C69: Intangible and Long-Term Other Assets | F69: ='Financials from CIP'!D54/1000 -> 4.378482 | G69: ='Financials from CIP'!E54/1000 -> 4.50437
C70: Total Assets | F70: =SUM(F64,F67:F69) -> 83.924938 | G70: =SUM(G64,G67:G69) -> 86.938044
C72: Liabilities & Shareholders' Equity
C74: Accounts Payable | F74: ='Financials from CIP'!D58/1000 -> 2.805817 | G74: ='Financials from CIP'!E58/1000 -> 2.36071
C75: Wages Payable | F75: ='Financials from CIP'!D59/1000 -> 2.383933 | G75: ='Financials from CIP'!E59/1000 -> 2.788038
C76: Accrued Expenses & Other | F76: ='Financials from CIP'!D60/1000 -> 2.057908 | G76: ='Financials from CIP'!E60/1000 -> 3.202031
C77: Total Current Liabilities | F77: =SUM(F74:F76) -> 7.247658 | G77: =SUM(G74:G76) -> 8.350779
C78: Revolver | F78: ='Financials from CIP'!D63/1000 -> 0.645883 | G78: ='Financials from CIP'!E63/1000 -> 1.2893
C79: Term Loan A | F79: ='Financials from CIP'!D64/1000 -> 18.943222 | G79: ='Financials from CIP'!E64/1000 -> 12.001451
C80: Subordinated - Note 1 | F80: ='Financials from CIP'!D65/1000 -> 0.545333 | G80: ='Financials from CIP'!E65/1000 -> 0.085338
C81: Subordinated - Note 2 | F81: ='Financials from CIP'!D66/1000 -> 0.092448 | G81: ='Financials from CIP'!E66/1000 -> 0.012667
C82: Total Debt | F82: =SUM(F78:F81) -> 20.226886 | G82: =SUM(G78:G81) -> 13.388756
C83: Other Long-term Liabilities | F83: ='Financials from CIP'!D67/1000 -> 0.417874 | G83: ='Financials from CIP'!E67/1000 -> 0.429888
C84: Total liabilities | F84: =SUM(F77,F82:F83) -> 27.892418 | G84: =SUM(G77,G82:G83) -> 22.169423
C85: Common Stock | F85: ='Financials from CIP'!D71/1000 -> 7.7836338 | G85: ='Financials from CIP'!E71/1000 -> 8.9161157
C86: Retained Earnings | F86: ='Financials from CIP'!D72/1000 -> 48.248887 | G86: ='Financials from CIP'!E72/1000 -> 55.852505
C87: Total Liabilities & Shareholders' Equity | F87: =SUM(F84:F86) -> 83.924939 | G87: =SUM(G84:G86) -> 86.938043
B92: x | C92: Checks to Source
C93: Income Statement
C94: Revenue | F94: ='Financials from CIP'!D13/1000-'Step 2 Answer Key'!F13 -> 0 | G94: ='Financials from CIP'!E13/1000-'Step 2 Answer Key'!G13 -> 0
C95: Gross Profit | F95: ='Financials from CIP'!D19/1000-'Step 2 Answer Key'!F15 -> 0 | G95: ='Financials from CIP'!E19/1000-'Step 2 Answer Key'!G15 -> 0
C96: EBITDA | F96: ='Financials from CIP'!D36/1000-'Step 2 Answer Key'!F18 -> 0 | G96: ='Financials from CIP'!E36/1000-'Step 2 Answer Key'!G18 -> 0
C97: Net Income | F97: ='Financials from CIP'!D34/1000-'Step 2 Answer Key'!F33 -> 0 | G97: ='Financials from CIP'!E34/1000-'Step 2 Answer Key'!G33 -> 0
C99: Balance Sheet
C100: Cash | F100: ='Financials from CIP'!D46/1000-'Step 2 Answer Key'!F60 -> 0 | G100: ='Financials from CIP'!E46/1000-'Step 2 Answer Key'!G60 -> 0
C101: Current Assets | F101: ='Financials from CIP'!D51/1000-'Step 2 Answer Key'!F64 -> 0 | G101: ='Financials from CIP'!E51/1000-'Step 2 Answer Key'!G64 -> 0
C102: Total Assets | F102: ='Financials from CIP'!D56/1000-'Step 2 Answer Key'!F70 -> 0 | G102: ='Financials from CIP'!E56/1000-'Step 2 Answer Key'!G70 -> 0
C103: Current Liabilities | F103: ='Financials from CIP'!D61/1000-'Step 2 Answer Key'!F77 -> 0 | G103: ='Financials from CIP'!E61/1000-'Step 2 Answer Key'!G77 -> 0
C104: Total Liabilities | F104: ='Financials from CIP'!D69/1000-'Step 2 Answer Key'!F84 -> 0 | G104: ='Financials from CIP'!E69/1000-'Step 2 Answer Key'!G84 -> 0
C105: Total Equity | F105: ='Financials from CIP'!D73/1000-SUM('Step 2 Answer Key'!F85:F86) -> 0 | G105: ='Financials from CIP'!E73/1000-SUM('Step 2 Answer Key'!G85:G86) -> 0
C107: Internal Checks
C108: A= L + E | F108: =F70-F87 -> -8.2790072e-07 | G108: =G70-G87 -> 5.041918e-07
B114: x | C114: Depreciation Schedule | M114: Depreciation is how much your long-term, physical assets (such as equipment) decrease in value each year. We have to know the cost of our the long-term, physical assets (CapEx) and then choose an "estimated life" to find the depreciation each year
H116: Fiscal Years Ending December 31,
C117: ($ in millions) | D117: PP&E to Depr | E117: SL Years (Est Life) | F117: Last Year | G117: Depr/Year | H117: =H$11 -> 46022 | I117: =I$11 -> 46387 | J117: =J$11 -> 46752 | K117: =K$11 -> 47118 | L117: =L$11 -> 47483
C119: =G11 -> 45657 | D119: =G67 -> 55.684984 | E119: 10 | F119: =-G20 -> -1.1617643 | G119: =IFERROR(-D119/E119,"N/M") -> -5.5684984 | H119: =-MIN(-$G119,$D119) -> -5.5684984 | I119: =-MIN(-$H119,SUM($H119:H119,$D119)) -> -5.5684984 | J119: =-MIN(-$H119,SUM($H119:I119,$D119)) -> -5.5684984 | K119: =-MIN(-$H119,SUM($H119:J119,$D119)) -> -5.5684984 | L119: =-MIN(-$H119,SUM($H119:K119,$D119)) -> -5.5684984 | M119: Link Amt to Depr to this year's capex. Straight line Depr for 10 more years. Use a rolling formula to determine what the amount should be each year - how much is left over vs annual depreciation per year. The first year formula can be written as: =-MIN(-$G119,$D119). Following that, we can write it as: =-MIN(-$H119,SUM($H119:H119,$D119))
C120: =H117 -> 46022
C121: =I117 -> 46387
C122: =J117 -> 46752
C123: =K117 -> 47118
C124: =L117 -> 47483
C126: Total Depr. | H126: =-SUM(H119:H125) -> 5.5684984 | I126: =-SUM(I119:I125) -> 5.5684984 | J126: =-SUM(J119:J125) -> 5.5684984 | K126: =-SUM(K119:K125) -> 5.5684984 | L126: =-SUM(L119:L125) -> 5.5684984

Sheet Step 3
C2: Athena Modeling Exercise
C3: Step 3 - Start the Balance Sheet
J5: Black font = Calculation
C6: YELLOWS ARE FILLS | F6: SKIP FOR NOW | J6: Blue font = Hardcoded Input/Assumption
J7: Green font = Pulled from another Sheet
B8: x | C8: Income Statement
F10: MRY | G10: MRY | H10: Fiscal Years Ending December 31,
C11: ($ in millions) | F11: =EOMONTH(G11,-12) -> 45291 | G11: 45657 | H11: =EOMONTH(G11,12) -> 46022 | I11: =EOMONTH(H11,12) -> 46387 | J11: =EOMONTH(I11,12) -> 46752 | K11: =EOMONTH(J11,12) -> 47118 | L11: =EOMONTH(K11,12) -> 47483
C13: Total Revenue | F13: ='Financials from CIP'!D13/1000 -> 78.565676 | G13: ='Financials from CIP'!E13/1000 -> 90.614008 | H13: =(1+H41)*G13 -> 104.51 | I13: =(1+I41)*H13 -> 120.53698 | J13: =(1+J41)*I13 -> 135.40566 | K13: =(1+K41)*J13 -> 148.04627 | L13: =(1+L41)*K13 -> 157.42554
C14: COGS | F14: =SUM('Financials from CIP'!D15:D17)/1000 -> 51.562189 | G14: =SUM('Financials from CIP'!E15:E17)/1000 -> 61.618676 | H14: =H43*H13 -> 69.828708 | I14: =I43*I13 -> 80.537195 | J14: =J43*J13 -> 90.47175 | K14: =K43*K13 -> 98.917617 | L14: =L43*L13 -> 105.18441
C15: Gross Profit | F15: =F13-F14 -> 27.003487 | G15: =G13-G14 -> 28.995332 | H15: =H13-H14 -> 34.681287 | I15: =I13-I14 -> 39.999789 | J15: =J13-J14 -> 44.933908 | K15: =K13-K14 -> 49.128652 | L15: =L13-L14 -> 52.24113
C16: Gross Margin (%) | F16: =IFERROR(F15/F$13,"N/M") -> 0.34370591 | G16: =IFERROR(G15/G$13,"N/M") -> 0.3199873 | H16: =IFERROR(H15/H$13,"N/M") -> 0.33184661 | I16: =IFERROR(I15/I$13,"N/M") -> 0.33184661 | J16: =IFERROR(J15/J$13,"N/M") -> 0.33184661 | K16: =IFERROR(K15/K$13,"N/M") -> 0.33184661 | L16: =IFERROR(L15/L$13,"N/M") -> 0.33184661
C17: SG&A | F17: =SUM('Financials from CIP'!D23:D24,'Financials from CIP'!D28)/1000 -> 14.179915 | G17: =SUM('Financials from CIP'!E23:E24,'Financials from CIP'!E28)/1000 -> 15.436689 | H17: =H44*H13 -> 18.333217 | I17: =I44*I13 -> 21.144682 | J17: =J44*J13 -> 23.752955 | K17: =K44*K13 -> 25.97038 | L17: =L44*L13 -> 27.615698
C18: EBITDA | F18: =F15-F17 -> 12.823572 | G18: =G15-G17 -> 13.558643 | H18: =H15-H17 -> 16.348071 | I18: =I15-I17 -> 18.855107 | J18: =J15-J17 -> 21.180953 | K18: =K15-K17 -> 23.158272 | L18: =L15-L17 -> 24.625432
C19: EBITDA Margin (%) | F19: =IFERROR(F18/F$13,"N/M") -> 0.16322105 | G19: =IFERROR(G18/G$13,"N/M") -> 0.14963076 | H19: =IFERROR(H18/H$13,"N/M") -> 0.15642591 | I19: =IFERROR(I18/I$13,"N/M") -> 0.15642591 | J19: =IFERROR(J18/J$13,"N/M") -> 0.15642591 | K19: =IFERROR(K18/K$13,"N/M") -> 0.15642591 | L19: =IFERROR(L18/L$13,"N/M") -> 0.15642591
C20: Depreciation | F20: ='Financials from CIP'!D25/1000 -> 1.1801621 | G20: ='Financials from CIP'!E25/1000 -> 1.1617643 | H20: =H126 -> 5.5684984 | I20: =I126 -> 5.5684984 | J20: =J126 -> 5.5684984 | K20: =K126 -> 5.5684984 | L20: =L126 -> 5.5684984
C21: Amortization | F21: ='Financials from CIP'!D26/1000 -> 0.208264 | G21: ='Financials from CIP'!E26/1000 -> 0.237952 | H21: =MIN(G21,G69) -> 0.237952 | I21: =MIN(H21,H69) -> 0.237952 | J21: =MIN(I21,I69) -> 0.237952 | K21: =MIN(J21,J69) -> 0.237952 | L21: =MIN(K21,K69) -> 0.237952
C22: EBIT | F22: =F18-SUM(F20:F21) -> 11.435146 | G22: =G18-SUM(G20:G21) -> 12.158927 | H22: =H18-SUM(H20:H21) -> 10.54162 | I22: =I18-SUM(I20:I21) -> 13.048656 | J22: =J18-SUM(J20:J21) -> 15.374502 | K22: =K18-SUM(K20:K21) -> 17.351821 | L22: =L18-SUM(L20:L21) -> 18.818982
C23: Interest (Income) / Expense
C24: Revolver – Interest
C25: Revolver – Undrawn Commitment Fee
C26: =+C79 -> Term Loan A
C27: =+C80 -> Subordinated - Note 1
C28: =+C81 -> Subordinated - Note 2
C29: Interest (Income) / Expense | F29: ='Financials from CIP'!D27/1000 -> 2.224955 | G29: ='Financials from CIP'!E27/1000 -> 1.472763 | H29: =SUM(H24:H28) -> 0 | I29: =SUM(I24:I28) -> 0 | J29: =SUM(J24:J28) -> 0 | K29: =SUM(K24:K28) -> 0 | L29: =SUM(L24:L28) -> 0
C30: Other (Income) / Expense | F30: ='Financials from CIP'!D32/1000 -> 0.147371 | G30: ='Financials from CIP'!E32/1000 -> 0.273439 | H30: 0 | I30: 0 | J30: 0 | K30: 0 | L30: 0
C31: Income Before Taxes | F31: =F22-F29-F30 -> 9.0628199 | G31: =G22-G29-G30 -> 10.412725 | H31: =H22-H29-H30 -> 10.54162 | I31: =I22-I29-I30 -> 13.048656 | J31: =J22-J29-J30 -> 15.374502 | K31: =K22-K29-K30 -> 17.351821 | L31: =L22-L29-L30 -> 18.818982
C32: Provision for Tax | F32: ='Financials from CIP'!D29/1000 -> 3.201039 | G32: ='Financials from CIP'!E29/1000 -> 2.809107 | H32: =H46*H31 -> 3.2836198 | I32: =I46*I31 -> 4.0645389 | J32: =J46*J31 -> 4.789019 | K32: =K46*K31 -> 5.404936 | L32: =L46*L31 -> 5.8619434
C33: Net Income | F33: =F31-F32 -> 5.8617809 | G33: =G31-G32 -> 7.6036178 | H33: =H31-H32 -> 7.2580005 | I33: =I31-I32 -> 8.9841174 | J33: =J31-J32 -> 10.585483 | K33: =K31-K32 -> 11.946885 | L33: =L31-L32 -> 12.957038
C34: Profit Margin (%) | F34: =IFERROR(F33/F$13,"N/M") -> 0.074609947 | G34: =IFERROR(G33/G$13,"N/M") -> 0.083912167 | H34: =IFERROR(H33/H$13,"N/M") -> 0.069447907 | I34: =IFERROR(I33/I$13,"N/M") -> 0.074534115 | J34: =IFERROR(J33/J$13,"N/M") -> 0.078176078 | K34: =IFERROR(K33/K$13,"N/M") -> 0.080696969 | L34: =IFERROR(L33/L$13,"N/M") -> 0.082305823
C36: Capital Expenditures | M36: CapEx is the cost of equipment that is "capitalized" on your Balance Sheet because it lasts more than one year. Let's assume we buy more equipment as we grow and make it a Variable cost. As such, project as a % of Sales based on the performance driver below
C39: Key Performance Metrics & Drivers
C41: Sales Growth (%) | G41: =G13/F13-1 -> 0.15335363 | H41: =G41 -> 0.15335363 | I41: =H41 -> 0.15335363 | J41: =I41-3% -> 0.12335363 | K41: =J41-3% -> 0.093353635 | L41: =K41-3% -> 0.063353635
C43: COGS / Sales (%) | F43: =F14/F13 -> 0.65629409 | G43: =G14/G13 -> 0.6800127 | H43: =AVERAGE(F43:G43) -> 0.66815339 | I43: =H43 -> 0.66815339 | J43: =I43 -> 0.66815339 | K43: =J43 -> 0.66815339 | L43: =K43 -> 0.66815339
C44: SG&A / Sales (%) | F44: =F17/F13 -> 0.18048486 | G44: =G17/G13 -> 0.17035654 | H44: =AVERAGE(F44:G44) -> 0.1754207 | I44: =H44 -> 0.1754207 | J44: =I44 -> 0.1754207 | K44: =J44 -> 0.1754207 | L44: =K44 -> 0.1754207
C46: Tax Rate (%) | F46: =F32/F31 -> 0.35320563 | G46: =G32/G31 -> 0.26977636 | H46: =AVERAGE(F46:G46) -> 0.31149099 | I46: =H46 -> 0.31149099 | J46: =I46 -> 0.31149099 | K46: =J46 -> 0.31149099 | L46: =K46 -> 0.31149099
C48: Capex / Sales (%) | M48: Let's start by finding CapEx in 2024. We can do that by looking at the change in PP&E, net - using the information given to us in the 'Financials from CIP' tab, and removing the effect of Depreciation. Then, I can divide the CapEx I calculate by Sales to get the % in 2024. Use this as your assumption and hold constant going forward
B53: x | C53: Balance Sheet
F55: MRY | G55: MRY | H55: Fiscal Years Ending December 31,
C56: ($ in millions) | F56: =EOMONTH(G56,-12) -> 45291 | G56: =G$11 -> 45657 | H56: =H$11 -> 46022 | I56: =I$11 -> 46387 | J56: =J$11 -> 46752 | K56: =K$11 -> 47118 | L56: =L$11 -> 47483
C58: Assets
C60: Cash and Equivalents | F60: ='Financials from CIP'!D46/1000 -> 7.105652 | G60: ='Financials from CIP'!E46/1000 -> 2.957992
C61: Accounts Receivable, net | F61: =SUM('Financials from CIP'!D47:D48)/1000 -> 16.781419 | G61: =SUM('Financials from CIP'!E47:E48)/1000 -> 22.284722
C62: Inventory | F62: ='Financials from CIP'!D49/1000 -> 0.804901 | G62: ='Financials from CIP'!E49/1000 -> 1.161057
C63: Prepaids and Other Current Assets | F63: ='Financials from CIP'!D50/1000 -> 0.269784 | G63: ='Financials from CIP'!E50/1000 -> 0.344919
C64: Total Current Assets | F64: =SUM(F60:F63) -> 24.961756 | G64: =SUM(G60:G63) -> 26.74869 | H64: =SUM(H60:H63) -> 0 | I64: =SUM(I60:I63) -> 0 | J64: =SUM(J60:J63) -> 0 | K64: =SUM(K60:K63) -> 0 | L64: =SUM(L60:L63) -> 0
C65: PP&E, Gross | M65: PP&E stands for Property, Plant and Equipment (aka, long-term, physical assets). CapEx is the amount spent on long-term, physical assets that will last longer than 1 year. This is the GROSS amount, aka the TOTAL amount. As such, we add Capital Expenditures for the current year to Gross PP&E from the prior year to get our new aggregate PP&E. The result is an aggregation of all the CapEx we have spent (unless we sell an long-term, physical asset... but let's skip that for now)
C66: ( – ) Accumulated Depreciation | M66: When we buy physical assets, there is "wear and tear" making the value of the physical assets go down. This is decrease in value is called and it goes against PP&E, Gross to get to the "Net Amount." Add Depreciation (from the P&L) for the current year to Accumulated Depreciation (from the Balance Sheet) from the prior year. We want to show this as a negative balance because we will be reducing Gross PP&E by this amount - a Contra Asset
C67: PP&E, Net | F67: ='Financials from CIP'!D53/1000 -> 54.5847 | G67: ='Financials from CIP'!E53/1000 -> 55.684984 | H67: =SUM(H65:H66) -> 0 | I67: =SUM(I65:I66) -> 0 | J67: =SUM(J65:J66) -> 0 | K67: =SUM(K65:K66) -> 0 | L67: =SUM(L65:L66) -> 0
C68: Goodwill | F68: 0 | G68: 0 | M68: Goodwill is the amount of excess that someone pays for your company, above the fair value of assumed Assets less the fair value of assumed Liabilities when they purchase it. We will revisit this later. For now, let's assume it stays consistent each period and stays constant at zero
C69: Intangible and Long-Term Other Assets | F69: ='Financials from CIP'!D54/1000 -> 4.378482 | G69: ='Financials from CIP'!E54/1000 -> 4.50437 | M69: For future periods, Other Intangible Assets will be amortized by the current year amortization (from the Income Statement). Revisit your formula for Amortization on the P&L and make sure its not causing this balance to go negative. Once this balance reaches zero there is nothing left to amortize
C70: Total Assets | F70: =SUM(F64,F67:F69) -> 83.924938 | G70: =SUM(G64,G67:G69) -> 86.938044 | H70: =SUM(H64,H67:H69) -> 0 | I70: =SUM(I64,I67:I69) -> 0 | J70: =SUM(J64,J67:J69) -> 0 | K70: =SUM(K64,K67:K69) -> 0 | L70: =SUM(L64,L67:L69) -> 0
C72: Liabilities & Shareholders' Equity
C74: Accounts Payable | F74: ='Financials from CIP'!D58/1000 -> 2.805817 | G74: ='Financials from CIP'!E58/1000 -> 2.36071
C75: Wages Payable | F75: ='Financials from CIP'!D59/1000 -> 2.383933 | G75: ='Financials from CIP'!E59/1000 -> 2.788038
C76: Accrued Expenses & Other | F76: ='Financials from CIP'!D60/1000 -> 2.057908 | G76: ='Financials from CIP'!E60/1000 -> 3.202031
C77: Total Current Liabilities | F77: =SUM(F74:F76) -> 7.247658 | G77: =SUM(G74:G76) -> 8.350779 | H77: =SUM(H74:H76) -> 0 | I77: =SUM(I74:I76) -> 0 | J77: =SUM(J74:J76) -> 0 | K77: =SUM(K74:K76) -> 0 | L77: =SUM(L74:L76) -> 0
C78: Revolver | F78: ='Financials from CIP'!D63/1000 -> 0.645883 | G78: ='Financials from CIP'!E63/1000 -> 1.2893
C79: Term Loan A | F79: ='Financials from CIP'!D64/1000 -> 18.943222 | G79: ='Financials from CIP'!E64/1000 -> 12.001451
C80: Subordinated - Note 1 | F80: ='Financials from CIP'!D65/1000 -> 0.545333 | G80: ='Financials from CIP'!E65/1000 -> 0.085338
C81: Subordinated - Note 2 | F81: ='Financials from CIP'!D66/1000 -> 0.092448 | G81: ='Financials from CIP'!E66/1000 -> 0.012667
C82: Total Debt | F82: =SUM(F78:F81) -> 20.226886 | G82: =SUM(G78:G81) -> 13.388756 | H82: =SUM(H78:H81) -> 0 | I82: =SUM(I78:I81) -> 0 | J82: =SUM(J78:J81) -> 0 | K82: =SUM(K78:K81) -> 0 | L82: =SUM(L78:L81) -> 0
C83: Other Long-term Liabilities | F83: ='Financials from CIP'!D67/1000 -> 0.417874 | G83: ='Financials from CIP'!E67/1000 -> 0.429888 | M83: For simplicity, let's hold Other Long-Term Liabilities constant for the future periods. It looks like it won't change much given the history that I have and I am not sure what it is unless I ask for more details
C84: Total liabilities | F84: =SUM(F77,F82:F83) -> 27.892418 | G84: =SUM(G77,G82:G83) -> 22.169423 | H84: =SUM(H77,H82:H83) -> 0 | I84: =SUM(I77,I82:I83) -> 0 | J84: =SUM(J77,J82:J83) -> 0 | K84: =SUM(K77,K82:K83) -> 0 | L84: =SUM(L77,L82:L83) -> 0
C85: Common Stock | F85: ='Financials from CIP'!D71/1000 -> 7.7836338 | G85: ='Financials from CIP'!E71/1000 -> 8.9161157 | M85: Common Stock is the value of what you OWN in the business - Equity, another word for ownership. Equity goes up when we have Net Income or Issue stock and goes down if we have a Net Loss or give out a Dividend (paying Cash to owners). Let's assume that this will stay constant - no new stock issuances, no dividends, no stock buybacks
C86: Retained Earnings | F86: ='Financials from CIP'!D72/1000 -> 48.248887 | G86: ='Financials from CIP'!E72/1000 -> 55.852505 | M86: When we connect WHAT happened (Income Statement) to our Balance Sheet (HOW it affects our ownership), we connect the Income Statement (above) to the Balance Sheet, through Net Income and Retained Earnings. This is a key connection to all financial statements. As we have Net Income or a Net Loss each year, we take the previous year's Retained Earnings and add Net Income for the current year
C87: Total Liabilities & Shareholders' Equity | F87: =SUM(F84:F86) -> 83.924939 | G87: =SUM(G84:G86) -> 86.938043 | H87: =SUM(H84:H86) -> 0 | I87: =SUM(I84:I86) -> 0 | J87: =SUM(J84:J86) -> 0 | K87: =SUM(K84:K86) -> 0 | L87: =SUM(L84:L86) -> 0
C89: Check (should be zero) | M89: Subtract total Assets and Total Liabilities and Shareholder's Equity from each other as a check that will come in handy later. Italicize and show out 3 decimal places. Don't worry it will not balance yet.
B92: x | C92: Checks to Source
C93: Income Statement
C94: Revenue | F94: ='Financials from CIP'!D13/1000-'Step 3'!F13 -> 0 | G94: ='Financials from CIP'!E13/1000-'Step 3'!G13 -> 0
C95: Gross Profit | F95: ='Financials from CIP'!D19/1000-'Step 3'!F15 -> 0 | G95: ='Financials from CIP'!E19/1000-'Step 3'!G15 -> 0
C96: EBITDA | F96: ='Financials from CIP'!D36/1000-'Step 3'!F18 -> 0 | G96: ='Financials from CIP'!E36/1000-'Step 3'!G18 -> 0
C97: Net Income | F97: ='Financials from CIP'!D34/1000-'Step 3'!F33 -> 0 | G97: ='Financials from CIP'!E34/1000-'Step 3'!G33 -> 0
C99: Balance Sheet
C100: Cash | F100: ='Financials from CIP'!D46/1000-'Step 3'!F60 -> 0 | G100: ='Financials from CIP'!E46/1000-'Step 3'!G60 -> 0
C101: Current Assets | F101: ='Financials from CIP'!D51/1000-'Step 3'!F64 -> 0 | G101: ='Financials from CIP'!E51/1000-'Step 3'!G64 -> 0
C102: Total Assets | F102: ='Financials from CIP'!D56/1000-'Step 3'!F70 -> 0 | G102: ='Financials from CIP'!E56/1000-'Step 3'!G70 -> 0
C103: Current Liabilities | F103: ='Financials from CIP'!D61/1000-'Step 3'!F77 -> 0 | G103: ='Financials from CIP'!E61/1000-'Step 3'!G77 -> 0
C104: Total Liabilities | F104: ='Financials from CIP'!D69/1000-'Step 3'!F84 -> 0 | G104: ='Financials from CIP'!E69/1000-'Step 3'!G84 -> 0
C105: Total Equity | F105: ='Financials from CIP'!D73/1000-SUM('Step 3'!F85:F86) -> 0 | G105: ='Financials from CIP'!E73/1000-SUM('Step 3'!G85:G86) -> 0
C107: Internal Checks
C108: A= L + E | F108: =F70-F87 -> -8.2790072e-07 | G108: =G70-G87 -> 5.041918e-07
B114: x | C114: Depreciation Schedule | M114: Depreciation is how much your long-term, physical assets (such as equipment) decrease in value each year. We have to know the cost of our the long-term, physical assets (CapEx) and then choose an "estimated life" to find the depreciation each year
H116: Fiscal Years Ending December 31,
C117: ($ in millions) | D117: PP&E to Depr | E117: SL Years (Est Life) | F117: Last Year | G117: Depr/Year | H117: =H$11 -> 46022 | I117: =I$11 -> 46387 | J117: =J$11 -> 46752 | K117: =K$11 -> 47118 | L117: =L$11 -> 47483
C119: =G11 -> 45657 | D119: =G67 -> 55.684984 | E119: 10 | F119: =-G20 -> -1.1617643 | G119: =IFERROR(-D119/E119,"N/M") -> -5.5684984 | H119: =-MIN(-$G119,$D119) -> -5.5684984 | I119: =-MIN(-$H119,SUM($H119:H119,$D119)) -> -5.5684984 | J119: =-MIN(-$H119,SUM($H119:I119,$D119)) -> -5.5684984 | K119: =-MIN(-$H119,SUM($H119:J119,$D119)) -> -5.5684984 | L119: =-MIN(-$H119,SUM($H119:K119,$D119)) -> -5.5684984
C120: =H117 -> 46022 | M120: Link Amt to Depr to this year's CapEx. Straight line Depr for 10 years - remember to watch the year it starts based on when the CapEx was incurred. Use the same formulas as we did on line 119, using the first year formula in the first year, and the next years' formulas after that
C121: =I117 -> 46387 | M121: Link Amt to Depr to this year's CapEx. Straight line Depr for 10 years - remember to watch the year it starts based on when the CapEx was incurred. Use the same formulas as we did on line 119, using the first year formula in the first year, and the next years' formulas after that
C122: =J117 -> 46752 | M122: Link Amt to Depr to this year's CapEx. Straight line Depr for 10 years - remember to watch the year it starts based on when the CapEx was incurred. Use the same formulas as we did on line 119, using the first year formula in the first year, and the next years' formulas after that
C123: =K117 -> 47118 | M123: Link Amt to Depr to this year's CapEx. Straight line Depr for 10 years - remember to watch the year it starts based on when the CapEx was incurred. Use the same formulas as we did on line 119, using the first year formula in the first year, and the next years' formulas after that
C124: =L117 -> 47483 | M124: Link Amt to Depr to this year's CapEx. Straight line Depr for 10 years - remember to watch the year it starts based on when the CapEx was incurred. Use the same formulas as we did on line 119, using the first year formula in the first year, and the next years' formulas after that
C126: Total Depr. | H126: =-SUM(H119:H125) -> 5.5684984 | I126: =-SUM(I119:I125) -> 5.5684984 | J126: =-SUM(J119:J125) -> 5.5684984 | K126: =-SUM(K119:K125) -> 5.5684984 | L126: =-SUM(L119:L125) -> 5.5684984

Sheet Step 3 Answer Key
C2: Athena Modeling Exercise
C3: Step 3 - Start the Balance Sheet
J5: Black font = Calculation
C6: YELLOWS ARE FILLS | F6: SKIP FOR NOW | J6: Blue font = Hardcoded Input/Assumption
J7: Green font = Pulled from another Sheet
B8: x | C8: Income Statement
F10: MRY | G10: MRY | H10: Fiscal Years Ending December 31,
C11: ($ in millions) | F11: =EOMONTH(G11,-12) -> 45291 | G11: 45657 | H11: =EOMONTH(G11,12) -> 46022 | I11: =EOMONTH(H11,12) -> 46387 | J11: =EOMONTH(I11,12) -> 46752 | K11: =EOMONTH(J11,12) -> 47118 | L11: =EOMONTH(K11,12) -> 47483
C13: Total Revenue | F13: ='Financials from CIP'!D13/1000 -> 78.565676 | G13: ='Financials from CIP'!E13/1000 -> 90.614008 | H13: =(1+H41)*G13 -> 104.51 | I13: =(1+I41)*H13 -> 120.53698 | J13: =(1+J41)*I13 -> 135.40566 | K13: =(1+K41)*J13 -> 148.04627 | L13: =(1+L41)*K13 -> 157.42554
C14: COGS | F14: =SUM('Financials from CIP'!D15:D17)/1000 -> 51.562189 | G14: =SUM('Financials from CIP'!E15:E17)/1000 -> 61.618676 | H14: =H43*H13 -> 69.828708 | I14: =I43*I13 -> 80.537195 | J14: =J43*J13 -> 90.47175 | K14: =K43*K13 -> 98.917617 | L14: =L43*L13 -> 105.18441
C15: Gross Profit | F15: =F13-F14 -> 27.003487 | G15: =G13-G14 -> 28.995332 | H15: =H13-H14 -> 34.681287 | I15: =I13-I14 -> 39.999789 | J15: =J13-J14 -> 44.933908 | K15: =K13-K14 -> 49.128652 | L15: =L13-L14 -> 52.24113
C16: Gross Margin (%) | F16: =IFERROR(F15/F$13,"N/M") -> 0.34370591 | G16: =IFERROR(G15/G$13,"N/M") -> 0.3199873 | H16: =IFERROR(H15/H$13,"N/M") -> 0.33184661 | I16: =IFERROR(I15/I$13,"N/M") -> 0.33184661 | J16: =IFERROR(J15/J$13,"N/M") -> 0.33184661 | K16: =IFERROR(K15/K$13,"N/M") -> 0.33184661 | L16: =IFERROR(L15/L$13,"N/M") -> 0.33184661
C17: SG&A | F17: =SUM('Financials from CIP'!D23:D24,'Financials from CIP'!D28)/1000 -> 14.179915 | G17: =SUM('Financials from CIP'!E23:E24,'Financials from CIP'!E28)/1000 -> 15.436689 | H17: =H44*H13 -> 18.333217 | I17: =I44*I13 -> 21.144682 | J17: =J44*J13 -> 23.752955 | K17: =K44*K13 -> 25.97038 | L17: =L44*L13 -> 27.615698
C18: EBITDA | F18: =F15-F17 -> 12.823572 | G18: =G15-G17 -> 13.558643 | H18: =H15-H17 -> 16.348071 | I18: =I15-I17 -> 18.855107 | J18: =J15-J17 -> 21.180953 | K18: =K15-K17 -> 23.158272 | L18: =L15-L17 -> 24.625432
C19: EBITDA Margin (%) | F19: =IFERROR(F18/F$13,"N/M") -> 0.16322105 | G19: =IFERROR(G18/G$13,"N/M") -> 0.14963076 | H19: =IFERROR(H18/H$13,"N/M") -> 0.15642591 | I19: =IFERROR(I18/I$13,"N/M") -> 0.15642591 | J19: =IFERROR(J18/J$13,"N/M") -> 0.15642591 | K19: =IFERROR(K18/K$13,"N/M") -> 0.15642591 | L19: =IFERROR(L18/L$13,"N/M") -> 0.15642591
C20: Depreciation | F20: ='Financials from CIP'!D25/1000 -> 1.1801621 | G20: ='Financials from CIP'!E25/1000 -> 1.1617643 | H20: =H126 -> 5.8293926 | I20: =I126 -> 6.1302958 | J20: =J126 -> 6.4683165 | K20: =K126 -> 6.8378927 | L20: =L126 -> 7.2308829
C21: Amortization | F21: ='Financials from CIP'!D26/1000 -> 0.208264 | G21: ='Financials from CIP'!E26/1000 -> 0.237952 | H21: =MIN(G21,G69) -> 0.237952 | I21: =MIN(H21,H69) -> 0.237952 | J21: =MIN(I21,I69) -> 0.237952 | K21: =MIN(J21,J69) -> 0.237952 | L21: =MIN(K21,K69) -> 0.237952
C22: EBIT | F22: =F18-SUM(F20:F21) -> 11.435146 | G22: =G18-SUM(G20:G21) -> 12.158927 | H22: =H18-SUM(H20:H21) -> 10.280726 | I22: =I18-SUM(I20:I21) -> 12.486859 | J22: =J18-SUM(J20:J21) -> 14.474684 | K22: =K18-SUM(K20:K21) -> 16.082427 | L22: =L18-SUM(L20:L21) -> 17.156597
C23: Interest (Income) / Expense
C24: Revolver – Interest
C25: Revolver – Undrawn Commitment Fee
C26: =+C79 -> Term Loan A
C27: =+C80 -> Subordinated - Note 1
C28: =+C81 -> Subordinated - Note 2
C29: Interest (Income) / Expense | F29: ='Financials from CIP'!D27/1000 -> 2.224955 | G29: ='Financials from CIP'!E27/1000 -> 1.472763 | H29: =SUM(H24:H28) -> 0 | I29: =SUM(I24:I28) -> 0 | J29: =SUM(J24:J28) -> 0 | K29: =SUM(K24:K28) -> 0 | L29: =SUM(L24:L28) -> 0
C30: Other (Income) / Expense | F30: ='Financials from CIP'!D32/1000 -> 0.147371 | G30: ='Financials from CIP'!E32/1000 -> 0.273439 | H30: 0 | I30: 0 | J30: 0 | K30: 0 | L30: 0
C31: Income Before Taxes | F31: =F22-F29-F30 -> 9.0628199 | G31: =G22-G29-G30 -> 10.412725 | H31: =H22-H29-H30 -> 10.280726 | I31: =I22-I29-I30 -> 12.486859 | J31: =J22-J29-J30 -> 14.474684 | K31: =K22-K29-K30 -> 16.082427 | L31: =L22-L29-L30 -> 17.156597
C32: Provision for Tax | F32: ='Financials from CIP'!D29/1000 -> 3.201039 | G32: ='Financials from CIP'!E29/1000 -> 2.809107 | H32: =H46*H31 -> 3.2023536 | I32: =I46*I31 -> 3.8895441 | J32: =J46*J31 -> 4.5087338 | K32: =K46*K31 -> 5.0095311 | L32: =L46*L31 -> 5.3441256
C33: Net Income | F33: =F31-F32 -> 5.8617809 | G33: =G31-G32 -> 7.6036178 | H33: =H31-H32 -> 7.0783725 | I33: =I31-I32 -> 8.5973148 | J33: =J31-J32 -> 9.9659504 | K33: =K31-K32 -> 11.072896 | L33: =L31-L32 -> 11.812472
C34: Profit Margin (%) | F34: =IFERROR(F33/F$13,"N/M") -> 0.074609947 | G34: =IFERROR(G33/G$13,"N/M") -> 0.083912167 | H34: =IFERROR(H33/H$13,"N/M") -> 0.067729144 | I34: =IFERROR(I33/I$13,"N/M") -> 0.07132512 | J34: =IFERROR(J33/J$13,"N/M") -> 0.073600694 | K34: =IFERROR(K33/K$13,"N/M") -> 0.074793481 | L34: =IFERROR(L33/L$13,"N/M") -> 0.075035296
C36: Capital Expenditures | G36: =('Financials from CIP'!E53-'Financials from CIP'!D53+'Financials from CIP'!E25)/1000 -> 2.2620483 | H36: =H48*H13 -> 2.6089416 | I36: =I48*I13 -> 3.0090323 | J36: =J48*J13 -> 3.3802074 | K36: =K48*K13 -> 3.695762 | L36: =L48*L13 -> 3.929902 | M36: CapEx is the cost of equipment that is "capitalized" on your Balance Sheet because it lasts more than one year. Let's assume we buy more equipment as we grow and make it a Variable cost. As such, project as a % of Sales based on the performance driver below
C39: Key Performance Metrics & Drivers
C41: Sales Growth (%) | G41: =G13/F13-1 -> 0.15335363 | H41: =G41 -> 0.15335363 | I41: =H41 -> 0.15335363 | J41: =I41-3% -> 0.12335363 | K41: =J41-3% -> 0.093353635 | L41: =K41-3% -> 0.063353635
C43: COGS / Sales (%) | F43: =F14/F13 -> 0.65629409 | G43: =G14/G13 -> 0.6800127 | H43: =AVERAGE(F43:G43) -> 0.66815339 | I43: =H43 -> 0.66815339 | J43: =I43 -> 0.66815339 | K43: =J43 -> 0.66815339 | L43: =K43 -> 0.66815339
C44: SG&A / Sales (%) | F44: =F17/F13 -> 0.18048486 | G44: =G17/G13 -> 0.17035654 | H44: =AVERAGE(F44:G44) -> 0.1754207 | I44: =H44 -> 0.1754207 | J44: =I44 -> 0.1754207 | K44: =J44 -> 0.1754207 | L44: =K44 -> 0.1754207
C46: Tax Rate (%) | F46: =F32/F31 -> 0.35320563 | G46: =G32/G31 -> 0.26977636 | H46: =AVERAGE(F46:G46) -> 0.31149099 | I46: =H46 -> 0.31149099 | J46: =I46 -> 0.31149099 | K46: =J46 -> 0.31149099 | L46: =K46 -> 0.31149099
C48: Capex / Sales (%) | G48: =G36/G13 -> 0.024963561 | H48: =G48 -> 0.024963561 | I48: =H48 -> 0.024963561 | J48: =I48 -> 0.024963561 | K48: =J48 -> 0.024963561 | L48: =K48 -> 0.024963561 | M48: Let's start by finding CapEx in 2024. We can do that by looking at the change in PP&E, net - using the information given to us in the 'Financials from CIP' tab, and removing the effect of Depreciation. Then, I can divide the CapEx I calculate by Sales to get the % in 2024. Use this as your assumption and hold constant going forward
B53: x | C53: Balance Sheet
F55: MRY | G55: MRY | H55: Fiscal Years Ending December 31,
C56: ($ in millions) | F56: =EOMONTH(G56,-12) -> 45291 | G56: =G$11 -> 45657 | H56: =H$11 -> 46022 | I56: =I$11 -> 46387 | J56: =J$11 -> 46752 | K56: =K$11 -> 47118 | L56: =L$11 -> 47483
C58: Assets
C60: Cash and Equivalents | F60: ='Financials from CIP'!D46/1000 -> 7.105652 | G60: ='Financials from CIP'!E46/1000 -> 2.957992
C61: Accounts Receivable, net | F61: =SUM('Financials from CIP'!D47:D48)/1000 -> 16.781419 | G61: =SUM('Financials from CIP'!E47:E48)/1000 -> 22.284722
C62: Inventory | F62: ='Financials from CIP'!D49/1000 -> 0.804901 | G62: ='Financials from CIP'!E49/1000 -> 1.161057
C63: Prepaids and Other Current Assets | F63: ='Financials from CIP'!D50/1000 -> 0.269784 | G63: ='Financials from CIP'!E50/1000 -> 0.344919
C64: Total Current Assets | F64: =SUM(F60:F63) -> 24.961756 | G64: =SUM(G60:G63) -> 26.74869 | H64: =SUM(H60:H63) -> 0 | I64: =SUM(I60:I63) -> 0 | J64: =SUM(J60:J63) -> 0 | K64: =SUM(K60:K63) -> 0 | L64: =SUM(L60:L63) -> 0
C65: PP&E, Gross | H65: =G67+H36 -> 58.293926 | I65: =H65+I36 -> 61.302958 | J65: =I65+J36 -> 64.683165 | K65: =J65+K36 -> 68.378927 | L65: =K65+L36 -> 72.308829 | M65: PP&E stands for Property, Plant and Equipment (aka, long-term, physical assets). CapEx is the amount spent on long-term, physical assets that will last longer than 1 year. This is the GROSS amount, aka the TOTAL amount. As such, we add Capital Expenditures for the current year to Gross PP&E from the prior year to get our new aggregate PP&E. The result is an aggregation of all the CapEx we have spent (unless we sell an long-term, physical asset... but let's skip that for now)
C66: ( – ) Accumulated Depreciation | H66: =G66-H20 -> -5.8293926 | I66: =H66-I20 -> -11.959688 | J66: =I66-J20 -> -18.428005 | K66: =J66-K20 -> -25.265898 | L66: =K66-L20 -> -32.496781 | M66: When we buy physical assets, there is "wear and tear" making the value of the physical assets go down. This is decrease in value is called and it goes against PP&E, Gross to get to the "Net Amount." Add Depreciation (from the P&L) for the current year to Accumulated Depreciation (from the Balance Sheet) from the prior year. We want to show this as a negative balance because we will be reducing Gross PP&E by this amount - a Contra Asset
C67: PP&E, Net | F67: ='Financials from CIP'!D53/1000 -> 54.5847 | G67: ='Financials from CIP'!E53/1000 -> 55.684984 | H67: =SUM(H65:H66) -> 52.464533 | I67: =SUM(I65:I66) -> 49.34327 | J67: =SUM(J65:J66) -> 46.25516 | K67: =SUM(K65:K66) -> 43.11303 | L67: =SUM(L65:L66) -> 39.812049
C68: Goodwill | F68: 0 | G68: 0 | H68: 0 | I68: 0 | J68: 0 | K68: 0 | L68: 0 | M68: Goodwill is the amount of excess that someone pays for your company, above the fair value of assumed Assets less the fair value of assumed Liabilities when they purchase it. We will revisit this later. For now, let's assume it stays consistent each period and stays constant at zero
C69: Intangible and Long-Term Other Assets | F69: ='Financials from CIP'!D54/1000 -> 4.378482 | G69: ='Financials from CIP'!E54/1000 -> 4.50437 | H69: =G69-H21 -> 4.266418 | I69: =H69-I21 -> 4.028466 | J69: =I69-J21 -> 3.790514 | K69: =J69-K21 -> 3.552562 | L69: =K69-L21 -> 3.31461 | M69: For future periods, Other Intangible Assets will be amortized by the current year amortization (from the Income Statement). Revisit your formula for Amortization on the P&L and make sure its not causing this balance to go negative. Once this balance reaches zero there is nothing left to amortize
C70: Total Assets | F70: =SUM(F64,F67:F69) -> 83.924938 | G70: =SUM(G64,G67:G69) -> 86.938044 | H70: =SUM(H64,H67:H69) -> 56.730951 | I70: =SUM(I64,I67:I69) -> 53.371736 | J70: =SUM(J64,J67:J69) -> 50.045674 | K70: =SUM(K64,K67:K69) -> 46.665592 | L70: =SUM(L64,L67:L69) -> 43.126659
C72: Liabilities & Shareholders' Equity
C74: Accounts Payable | F74: ='Financials from CIP'!D58/1000 -> 2.805817 | G74: ='Financials from CIP'!E58/1000 -> 2.36071
C75: Wages Payable | F75: ='Financials from CIP'!D59/1000 -> 2.383933 | G75: ='Financials from CIP'!E59/1000 -> 2.788038
C76: Accrued Expenses & Other | F76: ='Financials from CIP'!D60/1000 -> 2.057908 | G76: ='Financials from CIP'!E60/1000 -> 3.202031
C77: Total Current Liabilities | F77: =SUM(F74:F76) -> 7.247658 | G77: =SUM(G74:G76) -> 8.350779 | H77: =SUM(H74:H76) -> 0 | I77: =SUM(I74:I76) -> 0 | J77: =SUM(J74:J76) -> 0 | K77: =SUM(K74:K76) -> 0 | L77: =SUM(L74:L76) -> 0
C78: Revolver | F78: ='Financials from CIP'!D63/1000 -> 0.645883 | G78: ='Financials from CIP'!E63/1000 -> 1.2893
C79: Term Loan A | F79: ='Financials from CIP'!D64/1000 -> 18.943222 | G79: ='Financials from CIP'!E64/1000 -> 12.001451
C80: Subordinated - Note 1 | F80: ='Financials from CIP'!D65/1000 -> 0.545333 | G80: ='Financials from CIP'!E65/1000 -> 0.085338
C81: Subordinated - Note 2 | F81: ='Financials from CIP'!D66/1000 -> 0.092448 | G81: ='Financials from CIP'!E66/1000 -> 0.012667
C82: Total Debt | F82: =SUM(F78:F81) -> 20.226886 | G82: =SUM(G78:G81) -> 13.388756 | H82: =SUM(H78:H81) -> 0 | I82: =SUM(I78:I81) -> 0 | J82: =SUM(J78:J81) -> 0 | K82: =SUM(K78:K81) -> 0 | L82: =SUM(L78:L81) -> 0
C83: Other Long-term Liabilities | F83: ='Financials from CIP'!D67/1000 -> 0.417874 | G83: ='Financials from CIP'!E67/1000 -> 0.429888 | H83: =G83 -> 0.429888 | I83: =H83 -> 0.429888 | J83: =I83 -> 0.429888 | K83: =J83 -> 0.429888 | L83: =K83 -> 0.429888 | M83: For simplicity, let's hold Other Long-Term Liabilities constant for the future periods. It looks like it won't change much given the history that I have and I am not sure what it is unless I ask for more details
C84: Total liabilities | F84: =SUM(F77,F82:F83) -> 27.892418 | G84: =SUM(G77,G82:G83) -> 22.169423 | H84: =SUM(H77,H82:H83) -> 0.429888 | I84: =SUM(I77,I82:I83) -> 0.429888 | J84: =SUM(J77,J82:J83) -> 0.429888 | K84: =SUM(K77,K82:K83) -> 0.429888 | L84: =SUM(L77,L82:L83) -> 0.429888
C85: Common Stock | F85: ='Financials from CIP'!D71/1000 -> 7.7836338 | G85: ='Financials from CIP'!E71/1000 -> 8.9161157 | H85: =G85 -> 8.9161157 | I85: =H85 -> 8.9161157 | J85: =I85 -> 8.9161157 | K85: =J85 -> 8.9161157 | L85: =K85 -> 8.9161157 | M85: Common Stock is the value of what you OWN in the business - Equity, another word for ownership. Equity goes up when we have Net Income or Issue stock and goes down if we have a Net Loss or give out a Dividend (paying Cash to owners). Let's assume that this will stay constant - no new stock issuances, no dividends, no stock buybacks
C86: Retained Earnings | F86: ='Financials from CIP'!D72/1000 -> 48.248887 | G86: ='Financials from CIP'!E72/1000 -> 55.852505 | H86: =G86+H33 -> 62.930877 | I86: =H86+I33 -> 71.528192 | J86: =I86+J33 -> 81.494142 | K86: =J86+K33 -> 92.567038 | L86: =K86+L33 -> 104.37951 | M86: When we connect WHAT happened (Income Statement) to our Balance Sheet (HOW it affects our ownership), we connect the Income Statement (above) to the Balance Sheet, through Net Income and Retained Earnings. This is a key connection to all financial statements. As we have Net Income or a Net Loss each year, we take the previous year's Retained Earnings and add Net Income for the current year
C87: Total Liabilities & Shareholders' Equity | F87: =SUM(F84:F86) -> 83.924939 | G87: =SUM(G84:G86) -> 86.938043 | H87: =SUM(H84:H86) -> 72.276881 | I87: =SUM(I84:I86) -> 80.874196 | J87: =SUM(J84:J86) -> 90.840146 | K87: =SUM(K84:K86) -> 101.91304 | L87: =SUM(L84:L86) -> 113.72551
C89: Check (should be zero) | F89: =F87-F70 -> 8.2790072e-07 | G89: =G87-G70 -> -5.041918e-07 | H89: =H87-H70 -> 15.54593 | I89: =I87-I70 -> 27.50246 | J89: =J87-J70 -> 40.794472 | K89: =K87-K70 -> 55.24745 | L89: =L87-L70 -> 70.598855 | M89: Subtract total Assets and Total Liabilities and Shareholder's Equity from each other as a check that will come in handy later. Italicize and show out 3 decimal places. Don't worry it will not balance yet.
B92: x | C92: Checks to Source
C93: Income Statement
C94: Revenue | F94: ='Financials from CIP'!D13/1000-'Step 3 Answer Key'!F13 -> 0 | G94: ='Financials from CIP'!E13/1000-'Step 3 Answer Key'!G13 -> 0
C95: Gross Profit | F95: ='Financials from CIP'!D19/1000-'Step 3 Answer Key'!F15 -> 0 | G95: ='Financials from CIP'!E19/1000-'Step 3 Answer Key'!G15 -> 0
C96: EBITDA | F96: ='Financials from CIP'!D36/1000-'Step 3 Answer Key'!F18 -> 0 | G96: ='Financials from CIP'!E36/1000-'Step 3 Answer Key'!G18 -> 0
C97: Net Income | F97: ='Financials from CIP'!D34/1000-'Step 3 Answer Key'!F33 -> 0 | G97: ='Financials from CIP'!E34/1000-'Step 3 Answer Key'!G33 -> 0
C99: Balance Sheet
C100: Cash | F100: ='Financials from CIP'!D46/1000-'Step 3 Answer Key'!F60 -> 0 | G100: ='Financials from CIP'!E46/1000-'Step 3 Answer Key'!G60 -> 0
C101: Current Assets | F101: ='Financials from CIP'!D51/1000-'Step 3 Answer Key'!F64 -> 0 | G101: ='Financials from CIP'!E51/1000-'Step 3 Answer Key'!G64 -> 0
C102: Total Assets | F102: ='Financials from CIP'!D56/1000-'Step 3 Answer Key'!F70 -> 0 | G102: ='Financials from CIP'!E56/1000-'Step 3 Answer Key'!G70 -> 0
C103: Current Liabilities | F103: ='Financials from CIP'!D61/1000-'Step 3 Answer Key'!F77 -> 0 | G103: ='Financials from CIP'!E61/1000-'Step 3 Answer Key'!G77 -> 0
C104: Total Liabilities | F104: ='Financials from CIP'!D69/1000-'Step 3 Answer Key'!F84 -> 0 | G104: ='Financials from CIP'!E69/1000-'Step 3 Answer Key'!G84 -> 0
C105: Total Equity | F105: ='Financials from CIP'!D73/1000-SUM('Step 3 Answer Key'!F85:F86) -> 0 | G105: ='Financials from CIP'!E73/1000-SUM('Step 3 Answer Key'!G85:G86) -> 0
C107: Internal Checks
C108: A= L + E | F108: =F70-F87 -> -8.2790072e-07 | G108: =G70-G87 -> 5.041918e-07
B114: x | C114: Depreciation Schedule | M114: Depreciation is how much your long-term, physical assets (such as equipment) decrease in value each year. We have to know the cost of our the long-term, physical assets (CapEx) and then choose an "estimated life" to find the depreciation each year
H116: Fiscal Years Ending December 31,
C117: ($ in millions) | D117: PP&E to Depr | E117: SL Years (Est Life) | F117: Last Year | G117: Depr/Year | H117: =H$11 -> 46022 | I117: =I$11 -> 46387 | J117: =J$11 -> 46752 | K117: =K$11 -> 47118 | L117: =L$11 -> 47483
C119: =G11 -> 45657 | D119: =G67 -> 55.684984 | E119: 10 | F119: =-G20 -> -1.1617643 | G119: =IFERROR(-D119/E119,"N/M") -> -5.5684984 | H119: =-MIN(-$G119,$D119) -> -5.5684984 | I119: =-MIN(-$H119,SUM($H119:H119,$D119)) -> -5.5684984 | J119: =-MIN(-$H119,SUM($H119:I119,$D119)) -> -5.5684984 | K119: =-MIN(-$H119,SUM($H119:J119,$D119)) -> -5.5684984 | L119: =-MIN(-$H119,SUM($H119:K119,$D119)) -> -5.5684984
C120: =H117 -> 46022 | D120: =H36 -> 2.6089416 | E120: 10 | G120: =IFERROR(-D120/E120,"N/M") -> -0.26089416 | H120: =-MIN(-$G120,$D120) -> -0.26089416 | I120: =-MIN(-$H120,SUM($H120:H120,$D120)) -> -0.26089416 | J120: =-MIN(-$H120,SUM($H120:I120,$D120)) -> -0.26089416 | K120: =-MIN(-$H120,SUM($H120:J120,$D120)) -> -0.26089416 | L120: =-MIN(-$H120,SUM($H120:K120,$D120)) -> -0.26089416 | M120: Link Amt to Depr to this year's CapEx. Straight line Depr for 10 years - remember to watch the year it starts based on when the CapEx was incurred. Use the same formulas as we did on line 119, using the first year formula in the first year, and the next years' formulas after that
C121: =I117 -> 46387 | D121: =I36 -> 3.0090323 | E121: 10 | G121: =IFERROR(-D121/E121,"N/M") -> -0.30090323 | I121: =-MIN(-$G121,$D121) -> -0.30090323 | J121: =-MIN(-$I121,SUM($I121:J121,$D121)) -> -0.30090323 | K121: =-MIN(-$I121,SUM($I121:K121,$D121)) -> -0.30090323 | L121: =-MIN(-$I121,SUM($I121:L121,$D121)) -> -0.30090323 | M121: Link Amt to Depr to this year's CapEx. Straight line Depr for 10 years - remember to watch the year it starts based on when the CapEx was incurred. Use the same formulas as we did on line 119, using the first year formula in the first year, and the next years' formulas after that
C122: =J117 -> 46752 | D122: =J36 -> 3.3802074 | E122: 10 | G122: =IFERROR(-D122/E122,"N/M") -> -0.33802074 | J122: =-MIN(-$G122,$D122) -> -0.33802074 | K122: =-MIN(-$J122,SUM($J122:L122,$D122)) -> -0.33802074 | L122: =-MIN(-$J122,SUM($J122:M122,$D122)) -> -0.33802074 | M122: Link Amt to Depr to this year's CapEx. Straight line Depr for 10 years - remember to watch the year it starts based on when the CapEx was incurred. Use the same formulas as we did on line 119, using the first year formula in the first year, and the next years' formulas after that
C123: =K117 -> 47118 | D123: =K36 -> 3.695762 | E123: 10 | G123: =IFERROR(-D123/E123,"N/M") -> -0.3695762 | K123: =-MIN(-$G123,$D123) -> -0.3695762 | L123: =-MIN(-$K123,SUM($K123:N123,$D123)) -> -0.3695762 | M123: Link Amt to Depr to this year's CapEx. Straight line Depr for 10 years - remember to watch the year it starts based on when the CapEx was incurred. Use the same formulas as we did on line 119, using the first year formula in the first year, and the next years' formulas after that
C124: =L117 -> 47483 | D124: =L36 -> 3.929902 | E124: 10 | G124: =IFERROR(-D124/E124,"N/M") -> -0.3929902 | L124: =-MIN(-$G124,$D124) -> -0.3929902 | M124: Link Amt to Depr to this year's CapEx. Straight line Depr for 10 years - remember to watch the year it starts based on when the CapEx was incurred. Use the same formulas as we did on line 119, using the first year formula in the first year, and the next years' formulas after that
C126: Total Depr. | H126: =-SUM(H119:H125) -> 5.8293926 | I126: =-SUM(I119:I125) -> 6.1302958 | J126: =-SUM(J119:J125) -> 6.4683165 | K126: =-SUM(K119:K125) -> 6.8378927 | L126: =-SUM(L119:L125) -> 7.2308829

Sheet Step 4
C2: Athena Modeling Exercise
C3: Step 4 - More Balance Sheet - Net Working Capital
J5: Black font = Calculation
C6: YELLOWS ARE FILLS | F6: SKIP FOR NOW | J6: Blue font = Hardcoded Input/Assumption
J7: Green font = Pulled from another Sheet
B8: x | C8: Income Statement
F10: MRY | G10: MRY | H10: Fiscal Years Ending December 31,
C11: ($ in millions) | F11: =EOMONTH(G11,-12) -> 45291 | G11: 45657 | H11: =EOMONTH(G11,12) -> 46022 | I11: =EOMONTH(H11,12) -> 46387 | J11: =EOMONTH(I11,12) -> 46752 | K11: =EOMONTH(J11,12) -> 47118 | L11: =EOMONTH(K11,12) -> 47483
C13: Total Revenue | F13: ='Financials from CIP'!D13/1000 -> 78.565676 | G13: ='Financials from CIP'!E13/1000 -> 90.614008 | H13: =(1+H41)*G13 -> 104.51 | I13: =(1+I41)*H13 -> 120.53698 | J13: =(1+J41)*I13 -> 135.40566 | K13: =(1+K41)*J13 -> 148.04627 | L13: =(1+L41)*K13 -> 157.42554
C14: COGS | F14: =SUM('Financials from CIP'!D15:D17)/1000 -> 51.562189 | G14: =SUM('Financials from CIP'!E15:E17)/1000 -> 61.618676 | H14: =H43*H13 -> 69.828708 | I14: =I43*I13 -> 80.537195 | J14: =J43*J13 -> 90.47175 | K14: =K43*K13 -> 98.917617 | L14: =L43*L13 -> 105.18441
C15: Gross Profit | F15: =F13-F14 -> 27.003487 | G15: =G13-G14 -> 28.995332 | H15: =H13-H14 -> 34.681287 | I15: =I13-I14 -> 39.999789 | J15: =J13-J14 -> 44.933908 | K15: =K13-K14 -> 49.128652 | L15: =L13-L14 -> 52.24113
C16: Gross Margin (%) | F16: =IFERROR(F15/F$13,"N/M") -> 0.34370591 | G16: =IFERROR(G15/G$13,"N/M") -> 0.3199873 | H16: =IFERROR(H15/H$13,"N/M") -> 0.33184661 | I16: =IFERROR(I15/I$13,"N/M") -> 0.33184661 | J16: =IFERROR(J15/J$13,"N/M") -> 0.33184661 | K16: =IFERROR(K15/K$13,"N/M") -> 0.33184661 | L16: =IFERROR(L15/L$13,"N/M") -> 0.33184661
C17: SG&A | F17: =SUM('Financials from CIP'!D23:D24,'Financials from CIP'!D28)/1000 -> 14.179915 | G17: =SUM('Financials from CIP'!E23:E24,'Financials from CIP'!E28)/1000 -> 15.436689 | H17: =H44*H13 -> 18.333217 | I17: =I44*I13 -> 21.144682 | J17: =J44*J13 -> 23.752955 | K17: =K44*K13 -> 25.97038 | L17: =L44*L13 -> 27.615698
C18: EBITDA | F18: =F15-F17 -> 12.823572 | G18: =G15-G17 -> 13.558643 | H18: =H15-H17 -> 16.348071 | I18: =I15-I17 -> 18.855107 | J18: =J15-J17 -> 21.180953 | K18: =K15-K17 -> 23.158272 | L18: =L15-L17 -> 24.625432
C19: EBITDA Margin (%) | F19: =IFERROR(F18/F$13,"N/M") -> 0.16322105 | G19: =IFERROR(G18/G$13,"N/M") -> 0.14963076 | H19: =IFERROR(H18/H$13,"N/M") -> 0.15642591 | I19: =IFERROR(I18/I$13,"N/M") -> 0.15642591 | J19: =IFERROR(J18/J$13,"N/M") -> 0.15642591 | K19: =IFERROR(K18/K$13,"N/M") -> 0.15642591 | L19: =IFERROR(L18/L$13,"N/M") -> 0.15642591
C20: Depreciation | F20: ='Financials from CIP'!D25/1000 -> 1.1801621 | G20: ='Financials from CIP'!E25/1000 -> 1.1617643 | H20: =H164 -> 5.8293926 | I20: =I164 -> 6.1302958 | J20: =J164 -> 6.4683165 | K20: =K164 -> 6.8378927 | L20: =L164 -> 7.2308829
C21: Amortization | F21: ='Financials from CIP'!D26/1000 -> 0.208264 | G21: ='Financials from CIP'!E26/1000 -> 0.237952 | H21: =MIN(G21,G69) -> 0.237952 | I21: =MIN(H21,H69) -> 0.237952 | J21: =MIN(I21,I69) -> 0.237952 | K21: =MIN(J21,J69) -> 0.237952 | L21: =MIN(K21,K69) -> 0.237952
C22: EBIT | F22: =F18-SUM(F20:F21) -> 11.435146 | G22: =G18-SUM(G20:G21) -> 12.158927 | H22: =H18-SUM(H20:H21) -> 10.280726 | I22: =I18-SUM(I20:I21) -> 12.486859 | J22: =J18-SUM(J20:J21) -> 14.474684 | K22: =K18-SUM(K20:K21) -> 16.082427 | L22: =L18-SUM(L20:L21) -> 17.156597
C23: Interest (Income) / Expense
C24: Revolver – Interest
C25: Revolver – Undrawn Commitment Fee
C26: =+C79 -> Term Loan A
C27: =+C80 -> Subordinated - Note 1
C28: =+C81 -> Subordinated - Note 2
C29: Interest (Income) / Expense | F29: ='Financials from CIP'!D27/1000 -> 2.224955 | G29: ='Financials from CIP'!E27/1000 -> 1.472763 | H29: =SUM(H24:H28) -> 0 | I29: =SUM(I24:I28) -> 0 | J29: =SUM(J24:J28) -> 0 | K29: =SUM(K24:K28) -> 0 | L29: =SUM(L24:L28) -> 0
C30: Other (Income) / Expense | F30: ='Financials from CIP'!D32/1000 -> 0.147371 | G30: ='Financials from CIP'!E32/1000 -> 0.273439 | H30: 0 | I30: 0 | J30: 0 | K30: 0 | L30: 0
C31: Income Before Taxes | F31: =F22-F29-F30 -> 9.0628199 | G31: =G22-G29-G30 -> 10.412725 | H31: =H22-H29-H30 -> 10.280726 | I31: =I22-I29-I30 -> 12.486859 | J31: =J22-J29-J30 -> 14.474684 | K31: =K22-K29-K30 -> 16.082427 | L31: =L22-L29-L30 -> 17.156597
C32: Provision for Tax | F32: ='Financials from CIP'!D29/1000 -> 3.201039 | G32: ='Financials from CIP'!E29/1000 -> 2.809107 | H32: =H46*H31 -> 3.2023536 | I32: =I46*I31 -> 3.8895441 | J32: =J46*J31 -> 4.5087338 | K32: =K46*K31 -> 5.0095311 | L32: =L46*L31 -> 5.3441256
C33: Net Income | F33: =F31-F32 -> 5.8617809 | G33: =G31-G32 -> 7.6036178 | H33: =H31-H32 -> 7.0783725 | I33: =I31-I32 -> 8.5973148 | J33: =J31-J32 -> 9.9659504 | K33: =K31-K32 -> 11.072896 | L33: =L31-L32 -> 11.812472
C34: Profit Margin (%) | F34: =IFERROR(F33/F$13,"N/M") -> 0.074609947 | G34: =IFERROR(G33/G$13,"N/M") -> 0.083912167 | H34: =IFERROR(H33/H$13,"N/M") -> 0.067729144 | I34: =IFERROR(I33/I$13,"N/M") -> 0.07132512 | J34: =IFERROR(J33/J$13,"N/M") -> 0.073600694 | K34: =IFERROR(K33/K$13,"N/M") -> 0.074793481 | L34: =IFERROR(L33/L$13,"N/M") -> 0.075035296
C36: Capital Expenditures | G36: =('Financials from CIP'!E53-'Financials from CIP'!D53+'Financials from CIP'!E25)/1000 -> 2.2620483 | H36: =H48*H13 -> 2.6089416 | I36: =I48*I13 -> 3.0090323 | J36: =J48*J13 -> 3.3802074 | K36: =K48*K13 -> 3.695762 | L36: =L48*L13 -> 3.929902
C39: Key Performance Metrics & Drivers
C41: Sales Growth (%) | G41: =G13/F13-1 -> 0.15335363 | H41: =G41 -> 0.15335363 | I41: =H41 -> 0.15335363 | J41: =I41-3% -> 0.12335363 | K41: =J41-3% -> 0.093353635 | L41: =K41-3% -> 0.063353635
C43: COGS / Sales (%) | F43: =F14/F13 -> 0.65629409 | G43: =G14/G13 -> 0.6800127 | H43: =AVERAGE(F43:G43) -> 0.66815339 | I43: =H43 -> 0.66815339 | J43: =I43 -> 0.66815339 | K43: =J43 -> 0.66815339 | L43: =K43 -> 0.66815339
C44: SG&A / Sales (%) | F44: =F17/F13 -> 0.18048486 | G44: =G17/G13 -> 0.17035654 | H44: =AVERAGE(F44:G44) -> 0.1754207 | I44: =H44 -> 0.1754207 | J44: =I44 -> 0.1754207 | K44: =J44 -> 0.1754207 | L44: =K44 -> 0.1754207
C46: Tax Rate (%) | F46: =F32/F31 -> 0.35320563 | G46: =G32/G31 -> 0.26977636 | H46: =AVERAGE(F46:G46) -> 0.31149099 | I46: =H46 -> 0.31149099 | J46: =I46 -> 0.31149099 | K46: =J46 -> 0.31149099 | L46: =K46 -> 0.31149099
C48: Capex / Sales (%) | G48: =G36/G13 -> 0.024963561 | H48: =G48 -> 0.024963561 | I48: =H48 -> 0.024963561 | J48: =I48 -> 0.024963561 | K48: =J48 -> 0.024963561 | L48: =K48 -> 0.024963561
B53: x | C53: Balance Sheet
F55: MRY | G55: MRY | H55: Fiscal Years Ending December 31,
C56: ($ in millions) | F56: =EOMONTH(G56,-12) -> 45291 | G56: =G$11 -> 45657 | H56: =H$11 -> 46022 | I56: =I$11 -> 46387 | J56: =J$11 -> 46752 | K56: =K$11 -> 47118 | L56: =L$11 -> 47483
C58: Assets
C60: Cash and Equivalents | F60: ='Financials from CIP'!D46/1000 -> 7.105652 | G60: ='Financials from CIP'!E46/1000 -> 2.957992
C61: Accounts Receivable, Net | F61: =SUM('Financials from CIP'!D47:D48)/1000 -> 16.781419 | G61: =SUM('Financials from CIP'!E47:E48)/1000 -> 22.284722 | M61: Link to Working Capital section, below
C62: Inventory | F62: ='Financials from CIP'!D49/1000 -> 0.804901 | G62: ='Financials from CIP'!E49/1000 -> 1.161057 | M62: Link to Working Capital section, below
C63: Prepaids and Other Current Assets | F63: ='Financials from CIP'!D50/1000 -> 0.269784 | G63: ='Financials from CIP'!E50/1000 -> 0.344919 | M63: Link to Working Capital section, below
C64: Total Current Assets | F64: =SUM(F60:F63) -> 24.961756 | G64: =SUM(G60:G63) -> 26.74869 | H64: =SUM(H60:H63) -> 0 | I64: =SUM(I60:I63) -> 0 | J64: =SUM(J60:J63) -> 0 | K64: =SUM(K60:K63) -> 0 | L64: =SUM(L60:L63) -> 0
C65: PP&E, Gross | H65: =G67+H36 -> 58.293926 | I65: =H65+I36 -> 61.302958 | J65: =I65+J36 -> 64.683165 | K65: =J65+K36 -> 68.378927 | L65: =K65+L36 -> 72.308829
C66: ( – ) Accumulated Depreciation | H66: =G66-H20 -> -5.8293926 | I66: =H66-I20 -> -11.959688 | J66: =I66-J20 -> -18.428005 | K66: =J66-K20 -> -25.265898 | L66: =K66-L20 -> -32.496781
C67: PP&E, Net | F67: ='Financials from CIP'!D53/1000 -> 54.5847 | G67: ='Financials from CIP'!E53/1000 -> 55.684984 | H67: =SUM(H65:H66) -> 52.464533 | I67: =SUM(I65:I66) -> 49.34327 | J67: =SUM(J65:J66) -> 46.25516 | K67: =SUM(K65:K66) -> 43.11303 | L67: =SUM(L65:L66) -> 39.812049
C68: Goodwill | F68: 0 | G68: 0 | H68: 0 | I68: 0 | J68: 0 | K68: 0 | L68: 0
C69: Intangible and Long-Term Other Assets | F69: ='Financials from CIP'!D54/1000 -> 4.378482 | G69: ='Financials from CIP'!E54/1000 -> 4.50437 | H69: =G69-H21 -> 4.266418 | I69: =H69-I21 -> 4.028466 | J69: =I69-J21 -> 3.790514 | K69: =J69-K21 -> 3.552562 | L69: =K69-L21 -> 3.31461
C70: Total Assets | F70: =SUM(F64,F67:F69) -> 83.924938 | G70: =SUM(G64,G67:G69) -> 86.938044 | H70: =SUM(H64,H67:H69) -> 56.730951 | I70: =SUM(I64,I67:I69) -> 53.371736 | J70: =SUM(J64,J67:J69) -> 50.045674 | K70: =SUM(K64,K67:K69) -> 46.665592 | L70: =SUM(L64,L67:L69) -> 43.126659
C72: Liabilities & Shareholders' Equity
C74: Accounts Payable | F74: ='Financials from CIP'!D58/1000 -> 2.805817 | G74: ='Financials from CIP'!E58/1000 -> 2.36071 | M74: Link to Working Capital section, below
C75: Wages Payable | F75: ='Financials from CIP'!D59/1000 -> 2.383933 | G75: ='Financials from CIP'!E59/1000 -> 2.788038 | M75: Link to Working Capital section, below
C76: Accrued Expenses & Other | F76: ='Financials from CIP'!D60/1000 -> 2.057908 | G76: ='Financials from CIP'!E60/1000 -> 3.202031 | M76: Link to Working Capital section, below
C77: Total Current Liabilities | F77: =SUM(F74:F76) -> 7.247658 | G77: =SUM(G74:G76) -> 8.350779 | H77: =SUM(H74:H76) -> 0 | I77: =SUM(I74:I76) -> 0 | J77: =SUM(J74:J76) -> 0 | K77: =SUM(K74:K76) -> 0 | L77: =SUM(L74:L76) -> 0
C78: Revolver | F78: ='Financials from CIP'!D63/1000 -> 0.645883 | G78: ='Financials from CIP'!E63/1000 -> 1.2893
C79: Term Loan A | F79: ='Financials from CIP'!D64/1000 -> 18.943222 | G79: ='Financials from CIP'!E64/1000 -> 12.001451
C80: Subordinated - Note 1 | F80: ='Financials from CIP'!D65/1000 -> 0.545333 | G80: ='Financials from CIP'!E65/1000 -> 0.085338
C81: Subordinated - Note 2 | F81: ='Financials from CIP'!D66/1000 -> 0.092448 | G81: ='Financials from CIP'!E66/1000 -> 0.012667
C82: Total Debt | F82: =SUM(F78:F81) -> 20.226886 | G82: =SUM(G78:G81) -> 13.388756 | H82: =SUM(H78:H81) -> 0 | I82: =SUM(I78:I81) -> 0 | J82: =SUM(J78:J81) -> 0 | K82: =SUM(K78:K81) -> 0 | L82: =SUM(L78:L81) -> 0
C83: Other Long-term Liabilities | F83: ='Financials from CIP'!D67/1000 -> 0.417874 | G83: ='Financials from CIP'!E67/1000 -> 0.429888 | H83: =G83 -> 0.429888 | I83: =H83 -> 0.429888 | J83: =I83 -> 0.429888 | K83: =J83 -> 0.429888 | L83: =K83 -> 0.429888
C84: Total liabilities | F84: =SUM(F77,F82:F83) -> 27.892418 | G84: =SUM(G77,G82:G83) -> 22.169423 | H84: =SUM(H77,H82:H83) -> 0.429888 | I84: =SUM(I77,I82:I83) -> 0.429888 | J84: =SUM(J77,J82:J83) -> 0.429888 | K84: =SUM(K77,K82:K83) -> 0.429888 | L84: =SUM(L77,L82:L83) -> 0.429888
C85: Common Stock | F85: ='Financials from CIP'!D71/1000 -> 7.7836338 | G85: ='Financials from CIP'!E71/1000 -> 8.9161157 | H85: =G85 -> 8.9161157 | I85: =H85 -> 8.9161157 | J85: =I85 -> 8.9161157 | K85: =J85 -> 8.9161157 | L85: =K85 -> 8.9161157
C86: Retained Earnings | F86: ='Financials from CIP'!D72/1000 -> 48.248887 | G86: ='Financials from CIP'!E72/1000 -> 55.852505 | H86: =G86+H33 -> 62.930877 | I86: =H86+I33 -> 71.528192 | J86: =I86+J33 -> 81.494142 | K86: =J86+K33 -> 92.567038 | L86: =K86+L33 -> 104.37951
C87: Total Liabilities & Shareholders' Equity | F87: =SUM(F84:F86) -> 83.924939 | G87: =SUM(G84:G86) -> 86.938043 | H87: =SUM(H84:H86) -> 72.276881 | I87: =SUM(I84:I86) -> 80.874196 | J87: =SUM(J84:J86) -> 90.840146 | K87: =SUM(K84:K86) -> 101.91304 | L87: =SUM(L84:L86) -> 113.72551
C89: Check (should be zero) | F89: =F87-F70 -> 8.2790072e-07 | G89: =G87-G70 -> -5.041918e-07 | H89: =H87-H70 -> 15.54593 | I89: =I87-I70 -> 27.50246 | J89: =J87-J70 -> 40.794472 | K89: =K87-K70 -> 55.24745 | L89: =L87-L70 -> 70.598855
B93: x | C93: Working Capital
F95: MRY | G95: MRY | H95: Fiscal Years Ending December 31,
C96: ($ in millions) | F96: =F$11 -> 45291 | G96: =G$11 -> 45657 | H96: =H$11 -> 46022 | I96: =I$11 -> 46387 | J96: =J$11 -> 46752 | K96: =K$11 -> 47118 | L96: =L$11 -> 47483
C98: Net Working Capital
C100: =C61 -> Accounts Receivable, Net | M100: Accounts Receivable is the amount of money that people owe you for goods and services. It tends to correlate with Revenue - if Revenue goes up, it is likely that more people will owe you money. As such, this item follows Revenue, variably, through a ratio called Days Sales Outstanding, or DSO. See more on DSO, below. We use DSOs to inform us what our Accounts Receivable will be at the Revenue we are projecting. The formula is (Sales/# of Days in the Period)*DSO Ratio
C101: =C62 -> Inventory | M101: Inventory is the stuff that you sell. As such, it tends to correlate with CoGS. The higher my Sales, will mean that my CoGS go up too (see above) so I may want to keep more inventory around to keep up. As such, this item follows CoGS, variably, through a ratio called DIOH. See more on DIOH, below. We use DIOH to project how much inventory we will keep around to keep up with our Sales momentum. The formula to use is (CoGS/# of Days in the Period)*DIOH Ratio
C102: =C63 -> Prepaids and Other Current Assets | M102: What's in Other Assets? I don't know either. We know that it is some Prepaid Costs, such as Insurance, but what else? It could be Supplies. Because we don't know, we use SG&A as a Driver, assuming that things we typically Prepay (Rent and Insurance) would be SG&A. The formula to use here is the % we calculated, below * SG&A. I will make this driver variable because SG&A was variable
C103: Non-Cash Current Assets | F103: =SUM(F100:F102) -> 0 | G103: =SUM(G100:G102) -> 0 | H103: =SUM(H100:H102) -> 0 | I103: =SUM(I100:I102) -> 0 | J103: =SUM(J100:J102) -> 0 | K103: =SUM(K100:K102) -> 0 | L103: =SUM(L100:L102) -> 0
C105: =C74 -> Accounts Payable | M105: Accounts Payable is the amount of money that you owe your vendors for the goods and services that go into your CoGS. It tends to correlate with CoGS - if CoGS go up, it is likely that you will buy more things and your bills will be higher. As such, this item follows CoGS, variably, through a ratio called Days Payable Outstanding, or DPO. See more on DPO, below. We use DPOs to inform us what our Accounts Payable will be at the Revenue we are projecting. The formula is (CoGS/# of Days in the Period)*DPO Ratio
C106: =C75 -> Wages Payable | M106: Wages Payable is for money we owe to our employees but have not paid yet. This is common in business practice. When you first start a job, it is common for you to start getting paid a few weeks after you start - because people are paid behind when they earn it, called "Arrears." If you leave a job, you are paid what you owe up to that day. The formula to use here is the % we calculated, below *SG&A because that is where the costs of Payroll and Wages are captured
C107: =C76 -> Accrued Expenses & Other | M107: Accrued Expenses are just like Accounts Payable except it is for other money we owe. See the explanation below. The formula to use here is the % we calculated, below *SG&A
C108: Non-Debt Current Liabilities | F108: =SUM(F105:F107) -> 0 | G108: =SUM(G105:G107) -> 0 | H108: =SUM(H105:H107) -> 0 | I108: =SUM(I105:I107) -> 0 | J108: =SUM(J105:J107) -> 0 | K108: =SUM(K105:K107) -> 0 | L108: =SUM(L105:L107) -> 0
C109: Net Working Capital, without Cash | F109: =F103-F108 -> 0 | G109: =G103-G108 -> 0 | H109: =H103-H108 -> 0 | I109: =I103-I108 -> 0 | J109: =J103-J108 -> 0 | K109: =K103-K108 -> 0 | L109: =L103-L108 -> 0
C111: Change in Net Working Capital | M111: Given this is important for the Cash Flow Statement, let's make sure we calculate this here now. It is equal to this period's Net Working Capital minus last period's Net Working Capital
C113: Working Capital Drivers
C115: Sales | M115: Link to Sales in P&L (this just makes life a little easier for the ratios we will build, below)
C116: COGS | M116: Link to Sales in P&L (this just makes life a little easier for the ratios we will build, below)
C117: SG&A | M117: Link to Sales in P&L (this just makes life a little easier for the ratios we will build, below)
C119: DSO - Accounts Receivable Days Outstanding | M119: DSO stands for "Days Sales Outstanding." It tells you how long it takes you to collect from customers, on average, by giving you the number of days of individual sales that are outstanding (aka, have not been collected yet). It is calculated as: Accounts Receivable Balance / (Total Sales / # Days in the Period)
C120: DIOH - Day of Inventory on Hand | M120: DIOH stands for "Days of Inventory On Hand." It tells you how much inventory you carry at your location, on average, by giving you the number of days of individual CoGS that you have in inventory (aka, how much inventory do I have now)
C121: Prepaids & Other Current Assets / SG&A (%) | M121: We don't really have a good driver for this, so let's choose SG&A, given that's where the costs are most likely captured. It will fluctuate as SG&A moves around
C123: DPO - Accounts Payable Days Outstanding | M123: DPO stands for "Days Payable Outstanding." It tells you how long it takes you to pay your vendors (usually related to CoGS only), on average, by giving you the number of days of individual CoGS that are outstanding (aka, have you have not paid yet). It is calculated as: Accounts Payable Balance / (Total CoGS / # Days in the Period)
C124: Wages Payable / SG&A (%) | M124: We don't really have a good driver for this, so let's choose SG&A, given that's where the costs are captured. It will fluctuate as SG&A moves around
C125: Accrued Expenses & Other / SG&A (%) | M125: Accrued Expenses is how much money you owe your vendors that are not CoGS (think like your utility bill, etc). We can also make this one a % but it will most closely follow SG&A. Let's choose that as our driver
B130: x | C130: Checks to Source
C131: Income Statement
C132: Revenue | F132: ='Financials from CIP'!D13/1000-'Step 4'!F13 -> 0 | G132: ='Financials from CIP'!E13/1000-'Step 4'!G13 -> 0
C133: Gross Profit | F133: ='Financials from CIP'!D19/1000-'Step 4'!F15 -> 0 | G133: ='Financials from CIP'!E19/1000-'Step 4'!G15 -> 0
C134: EBITDA | F134: ='Financials from CIP'!D36/1000-'Step 4'!F18 -> 0 | G134: ='Financials from CIP'!E36/1000-'Step 4'!G18 -> 0
C135: Net Income | F135: ='Financials from CIP'!D34/1000-'Step 4'!F33 -> 0 | G135: ='Financials from CIP'!E34/1000-'Step 4'!G33 -> 0
C137: Balance Sheet
C138: Cash | F138: ='Financials from CIP'!D46/1000-'Step 4'!F60 -> 0 | G138: ='Financials from CIP'!E46/1000-'Step 4'!G60 -> 0
...

Sheet Step 4 Answer Key
C2: Athena Modeling Exercise
C3: Step 4 - More Balance Sheet - Net Working Capital
J5: Black font = Calculation
C6: YELLOWS ARE FILLS | F6: SKIP FOR NOW | J6: Blue font = Hardcoded Input/Assumption
J7: Green font = Pulled from another Sheet
B8: x | C8: Income Statement
F10: MRY | G10: MRY | H10: Fiscal Years Ending December 31,
C11: ($ in millions) | F11: =EOMONTH(G11,-12) -> 45291 | G11: 45657 | H11: =EOMONTH(G11,12) -> 46022 | I11: =EOMONTH(H11,12) -> 46387 | J11: =EOMONTH(I11,12) -> 46752 | K11: =EOMONTH(J11,12) -> 47118 | L11: =EOMONTH(K11,12) -> 47483
C13: Total Revenue | F13: ='Financials from CIP'!D13/1000 -> 78.565676 | G13: ='Financials from CIP'!E13/1000 -> 90.614008 | H13: =(1+H41)*G13 -> 104.51 | I13: =(1+I41)*H13 -> 120.53698 | J13: =(1+J41)*I13 -> 135.40566 | K13: =(1+K41)*J13 -> 148.04627 | L13: =(1+L41)*K13 -> 157.42554
C14: COGS | F14: =SUM('Financials from CIP'!D15:D17)/1000 -> 51.562189 | G14: =SUM('Financials from CIP'!E15:E17)/1000 -> 61.618676 | H14: =H43*H13 -> 69.828708 | I14: =I43*I13 -> 80.537195 | J14: =J43*J13 -> 90.47175 | K14: =K43*K13 -> 98.917617 | L14: =L43*L13 -> 105.18441
C15: Gross Profit | F15: =F13-F14 -> 27.003487 | G15: =G13-G14 -> 28.995332 | H15: =H13-H14 -> 34.681287 | I15: =I13-I14 -> 39.999789 | J15: =J13-J14 -> 44.933908 | K15: =K13-K14 -> 49.128652 | L15: =L13-L14 -> 52.24113
C16: Gross Margin (%) | F16: =IFERROR(F15/F$13,"N/M") -> 0.34370591 | G16: =IFERROR(G15/G$13,"N/M") -> 0.3199873 | H16: =IFERROR(H15/H$13,"N/M") -> 0.33184661 | I16: =IFERROR(I15/I$13,"N/M") -> 0.33184661 | J16: =IFERROR(J15/J$13,"N/M") -> 0.33184661 | K16: =IFERROR(K15/K$13,"N/M") -> 0.33184661 | L16: =IFERROR(L15/L$13,"N/M") -> 0.33184661
C17: SG&A | F17: =SUM('Financials from CIP'!D23:D24,'Financials from CIP'!D28)/1000 -> 14.179915 | G17: =SUM('Financials from CIP'!E23:E24,'Financials from CIP'!E28)/1000 -> 15.436689 | H17: =H44*H13 -> 18.333217 | I17: =I44*I13 -> 21.144682 | J17: =J44*J13 -> 23.752955 | K17: =K44*K13 -> 25.97038 | L17: =L44*L13 -> 27.615698
C18: EBITDA | F18: =F15-F17 -> 12.823572 | G18: =G15-G17 -> 13.558643 | H18: =H15-H17 -> 16.348071 | I18: =I15-I17 -> 18.855107 | J18: =J15-J17 -> 21.180953 | K18: =K15-K17 -> 23.158272 | L18: =L15-L17 -> 24.625432
C19: EBITDA Margin (%) | F19: =IFERROR(F18/F$13,"N/M") -> 0.16322105 | G19: =IFERROR(G18/G$13,"N/M") -> 0.14963076 | H19: =IFERROR(H18/H$13,"N/M") -> 0.15642591 | I19: =IFERROR(I18/I$13,"N/M") -> 0.15642591 | J19: =IFERROR(J18/J$13,"N/M") -> 0.15642591 | K19: =IFERROR(K18/K$13,"N/M") -> 0.15642591 | L19: =IFERROR(L18/L$13,"N/M") -> 0.15642591
C20: Depreciation | F20: ='Financials from CIP'!D25/1000 -> 1.1801621 | G20: ='Financials from CIP'!E25/1000 -> 1.1617643 | H20: =H164 -> 5.8293926 | I20: =I164 -> 6.1302958 | J20: =J164 -> 6.4683165 | K20: =K164 -> 6.8378927 | L20: =L164 -> 7.2308829
C21: Amortization | F21: ='Financials from CIP'!D26/1000 -> 0.208264 | G21: ='Financials from CIP'!E26/1000 -> 0.237952 | H21: =MIN(G21,G69) -> 0.237952 | I21: =MIN(H21,H69) -> 0.237952 | J21: =MIN(I21,I69) -> 0.237952 | K21: =MIN(J21,J69) -> 0.237952 | L21: =MIN(K21,K69) -> 0.237952
C22: EBIT | F22: =F18-SUM(F20:F21) -> 11.435146 | G22: =G18-SUM(G20:G21) -> 12.158927 | H22: =H18-SUM(H20:H21) -> 10.280726 | I22: =I18-SUM(I20:I21) -> 12.486859 | J22: =J18-SUM(J20:J21) -> 14.474684 | K22: =K18-SUM(K20:K21) -> 16.082427 | L22: =L18-SUM(L20:L21) -> 17.156597
C23: Interest (Income) / Expense
C24: Revolver – Interest
C25: Revolver – Undrawn Commitment Fee
C26: =+C79 -> Term Loan A
C27: =+C80 -> Subordinated - Note 1
C28: =+C81 -> Subordinated - Note 2
C29: Interest (Income) / Expense | F29: ='Financials from CIP'!D27/1000 -> 2.224955 | G29: ='Financials from CIP'!E27/1000 -> 1.472763 | H29: =SUM(H24:H28) -> 0 | I29: =SUM(I24:I28) -> 0 | J29: =SUM(J24:J28) -> 0 | K29: =SUM(K24:K28) -> 0 | L29: =SUM(L24:L28) -> 0
C30: Other (Income) / Expense | F30: ='Financials from CIP'!D32/1000 -> 0.147371 | G30: ='Financials from CIP'!E32/1000 -> 0.273439 | H30: 0 | I30: 0 | J30: 0 | K30: 0 | L30: 0
C31: Income Before Taxes | F31: =F22-F29-F30 -> 9.0628199 | G31: =G22-G29-G30 -> 10.412725 | H31: =H22-H29-H30 -> 10.280726 | I31: =I22-I29-I30 -> 12.486859 | J31: =J22-J29-J30 -> 14.474684 | K31: =K22-K29-K30 -> 16.082427 | L31: =L22-L29-L30 -> 17.156597
C32: Provision for Tax | F32: ='Financials from CIP'!D29/1000 -> 3.201039 | G32: ='Financials from CIP'!E29/1000 -> 2.809107 | H32: =H46*H31 -> 3.2023536 | I32: =I46*I31 -> 3.8895441 | J32: =J46*J31 -> 4.5087338 | K32: =K46*K31 -> 5.0095311 | L32: =L46*L31 -> 5.3441256
C33: Net Income | F33: =F31-F32 -> 5.8617809 | G33: =G31-G32 -> 7.6036178 | H33: =H31-H32 -> 7.0783725 | I33: =I31-I32 -> 8.5973148 | J33: =J31-J32 -> 9.9659504 | K33: =K31-K32 -> 11.072896 | L33: =L31-L32 -> 11.812472
C34: Profit Margin (%) | F34: =IFERROR(F33/F$13,"N/M") -> 0.074609947 | G34: =IFERROR(G33/G$13,"N/M") -> 0.083912167 | H34: =IFERROR(H33/H$13,"N/M") -> 0.067729144 | I34: =IFERROR(I33/I$13,"N/M") -> 0.07132512 | J34: =IFERROR(J33/J$13,"N/M") -> 0.073600694 | K34: =IFERROR(K33/K$13,"N/M") -> 0.074793481 | L34: =IFERROR(L33/L$13,"N/M") -> 0.075035296
C36: Capital Expenditures | G36: =('Financials from CIP'!E53-'Financials from CIP'!D53+'Financials from CIP'!E25)/1000 -> 2.2620483 | H36: =H48*H13 -> 2.6089416 | I36: =I48*I13 -> 3.0090323 | J36: =J48*J13 -> 3.3802074 | K36: =K48*K13 -> 3.695762 | L36: =L48*L13 -> 3.929902
C39: Key Performance Metrics & Drivers
C41: Sales Growth (%) | G41: =G13/F13-1 -> 0.15335363 | H41: =G41 -> 0.15335363 | I41: =H41 -> 0.15335363 | J41: =I41-3% -> 0.12335363 | K41: =J41-3% -> 0.093353635 | L41: =K41-3% -> 0.063353635
C43: COGS / Sales (%) | F43: =F14/F13 -> 0.65629409 | G43: =G14/G13 -> 0.6800127 | H43: =AVERAGE(F43:G43) -> 0.66815339 | I43: =H43 -> 0.66815339 | J43: =I43 -> 0.66815339 | K43: =J43 -> 0.66815339 | L43: =K43 -> 0.66815339
C44: SG&A / Sales (%) | F44: =F17/F13 -> 0.18048486 | G44: =G17/G13 -> 0.17035654 | H44: =AVERAGE(F44:G44) -> 0.1754207 | I44: =H44 -> 0.1754207 | J44: =I44 -> 0.1754207 | K44: =J44 -> 0.1754207 | L44: =K44 -> 0.1754207
C46: Tax Rate (%) | F46: =F32/F31 -> 0.35320563 | G46: =G32/G31 -> 0.26977636 | H46: =AVERAGE(F46:G46) -> 0.31149099 | I46: =H46 -> 0.31149099 | J46: =I46 -> 0.31149099 | K46: =J46 -> 0.31149099 | L46: =K46 -> 0.31149099
C48: Capex / Sales (%) | G48: =G36/G13 -> 0.024963561 | H48: =G48 -> 0.024963561 | I48: =H48 -> 0.024963561 | J48: =I48 -> 0.024963561 | K48: =J48 -> 0.024963561 | L48: =K48 -> 0.024963561
B53: x | C53: Balance Sheet
F55: MRY | G55: MRY | H55: Fiscal Years Ending December 31,
C56: ($ in millions) | F56: =EOMONTH(G56,-12) -> 45291 | G56: =G$11 -> 45657 | H56: =H$11 -> 46022 | I56: =I$11 -> 46387 | J56: =J$11 -> 46752 | K56: =K$11 -> 47118 | L56: =L$11 -> 47483
C58: Assets
C60: Cash and Equivalents | F60: ='Financials from CIP'!D46/1000 -> 7.105652 | G60: ='Financials from CIP'!E46/1000 -> 2.957992
C61: Accounts Receivable, Net | F61: =SUM('Financials from CIP'!D47:D48)/1000 -> 16.781419 | G61: =SUM('Financials from CIP'!E47:E48)/1000 -> 22.284722 | H61: =H100 -> 24.012611 | I61: =I100 -> 27.695032 | J61: =J100 -> 31.111315 | K61: =K100 -> 34.015669 | L61: =L100 -> 36.170685 | M61: Link to Working Capital section, below
C62: Inventory | F62: ='Financials from CIP'!D49/1000 -> 0.804901 | G62: ='Financials from CIP'!E49/1000 -> 1.161057 | H62: =H101 -> 1.2029011 | I62: =I101 -> 1.3873704 | J62: =J101 -> 1.5585076 | K62: =K101 -> 1.7039999 | L62: =L101 -> 1.8119545 | M62: Link to Working Capital section, below
C63: Prepaids and Other Current Assets | F63: ='Financials from CIP'!D50/1000 -> 0.269784 | G63: ='Financials from CIP'!E50/1000 -> 0.344919 | H63: =H102 -> 0.37922157 | I63: =I102 -> 0.43737657 | J63: =J102 -> 0.49132856 | K63: =K102 -> 0.53719587 | L63: =L102 -> 0.57122918 | M63: Link to Working Capital section, below
C64: Total Current Assets | F64: =SUM(F60:F63) -> 24.961756 | G64: =SUM(G60:G63) -> 26.74869 | H64: =SUM(H60:H63) -> 25.594734 | I64: =SUM(I60:I63) -> 29.519779 | J64: =SUM(J60:J63) -> 33.161151 | K64: =SUM(K60:K63) -> 36.256865 | L64: =SUM(L60:L63) -> 38.553869
C65: PP&E, Gross | H65: =G67+H36 -> 58.293926 | I65: =H65+I36 -> 61.302958 | J65: =I65+J36 -> 64.683165 | K65: =J65+K36 -> 68.378927 | L65: =K65+L36 -> 72.308829
C66: ( – ) Accumulated Depreciation | H66: =G66-H20 -> -5.8293926 | I66: =H66-I20 -> -11.959688 | J66: =I66-J20 -> -18.428005 | K66: =J66-K20 -> -25.265898 | L66: =K66-L20 -> -32.496781
C67: PP&E, Net | F67: ='Financials from CIP'!D53/1000 -> 54.5847 | G67: ='Financials from CIP'!E53/1000 -> 55.684984 | H67: =SUM(H65:H66) -> 52.464533 | I67: =SUM(I65:I66) -> 49.34327 | J67: =SUM(J65:J66) -> 46.25516 | K67: =SUM(K65:K66) -> 43.11303 | L67: =SUM(L65:L66) -> 39.812049
C68: Goodwill | F68: 0 | G68: 0 | H68: 0 | I68: 0 | J68: 0 | K68: 0 | L68: 0
C69: Intangible and Long-Term Other Assets | F69: ='Financials from CIP'!D54/1000 -> 4.378482 | G69: ='Financials from CIP'!E54/1000 -> 4.50437 | H69: =G69-H21 -> 4.266418 | I69: =H69-I21 -> 4.028466 | J69: =I69-J21 -> 3.790514 | K69: =J69-K21 -> 3.552562 | L69: =K69-L21 -> 3.31461
C70: Total Assets | F70: =SUM(F64,F67:F69) -> 83.924938 | G70: =SUM(G64,G67:G69) -> 86.938044 | H70: =SUM(H64,H67:H69) -> 82.325685 | I70: =SUM(I64,I67:I69) -> 82.891514 | J70: =SUM(J64,J67:J69) -> 83.206825 | K70: =SUM(K64,K67:K69) -> 82.922457 | L70: =SUM(L64,L67:L69) -> 81.680528
C72: Liabilities & Shareholders' Equity
C74: Accounts Payable | F74: ='Financials from CIP'!D58/1000 -> 2.805817 | G74: ='Financials from CIP'!E58/1000 -> 2.36071 | H74: =H105 -> 3.2375303 | I74: =I105 -> 3.7340173 | J74: =J105 -> 4.1946219 | K74: =K105 -> 4.5862051 | L74: =L105 -> 4.8767579 | M74: Link to Working Capital section, below
C75: Wages Payable | F75: ='Financials from CIP'!D59/1000 -> 2.383933 | G75: ='Financials from CIP'!E59/1000 -> 2.788038 | H75: =H106 -> 3.1966854 | I75: =I106 -> 3.6869088 | J75: =J106 -> 4.1417024 | K75: =K106 -> 4.5283453 | L75: =L106 -> 4.8152325 | M75: Link to Working Capital section, below
C76: Accrued Expenses & Other | F76: ='Financials from CIP'!D60/1000 -> 2.057908 | G76: ='Financials from CIP'!E60/1000 -> 3.202031 | H76: =H107 -> 3.2317637 | I76: =I107 -> 3.7273664 | J76: =J107 -> 4.1871506 | K76: =K107 -> 4.5780363 | L76: =L107 -> 4.8680716 | M76: Link to Working Capital section, below
C77: Total Current Liabilities | F77: =SUM(F74:F76) -> 7.247658 | G77: =SUM(G74:G76) -> 8.350779 | H77: =SUM(H74:H76) -> 9.6659794 | I77: =SUM(I74:I76) -> 11.148292 | J77: =SUM(J74:J76) -> 12.523475 | K77: =SUM(K74:K76) -> 13.692587 | L77: =SUM(L74:L76) -> 14.560062
C78: Revolver | F78: ='Financials from CIP'!D63/1000 -> 0.645883 | G78: ='Financials from CIP'!E63/1000 -> 1.2893
C79: Term Loan A | F79: ='Financials from CIP'!D64/1000 -> 18.943222 | G79: ='Financials from CIP'!E64/1000 -> 12.001451
C80: Subordinated - Note 1 | F80: ='Financials from CIP'!D65/1000 -> 0.545333 | G80: ='Financials from CIP'!E65/1000 -> 0.085338
C81: Subordinated - Note 2 | F81: ='Financials from CIP'!D66/1000 -> 0.092448 | G81: ='Financials from CIP'!E66/1000 -> 0.012667
C82: Total Debt | F82: =SUM(F78:F81) -> 20.226886 | G82: =SUM(G78:G81) -> 13.388756 | H82: =SUM(H78:H81) -> 0 | I82: =SUM(I78:I81) -> 0 | J82: =SUM(J78:J81) -> 0 | K82: =SUM(K78:K81) -> 0 | L82: =SUM(L78:L81) -> 0
C83: Other Long-term Liabilities | F83: ='Financials from CIP'!D67/1000 -> 0.417874 | G83: ='Financials from CIP'!E67/1000 -> 0.429888 | H83: =G83 -> 0.429888 | I83: =H83 -> 0.429888 | J83: =I83 -> 0.429888 | K83: =J83 -> 0.429888 | L83: =K83 -> 0.429888
C84: Total liabilities | F84: =SUM(F77,F82:F83) -> 27.892418 | G84: =SUM(G77,G82:G83) -> 22.169423 | H84: =SUM(H77,H82:H83) -> 10.095867 | I84: =SUM(I77,I82:I83) -> 11.57818 | J84: =SUM(J77,J82:J83) -> 12.953363 | K84: =SUM(K77,K82:K83) -> 14.122475 | L84: =SUM(L77,L82:L83) -> 14.98995
C85: Common Stock | F85: ='Financials from CIP'!D71/1000 -> 7.7836338 | G85: ='Financials from CIP'!E71/1000 -> 8.9161157 | H85: =G85 -> 8.9161157 | I85: =H85 -> 8.9161157 | J85: =I85 -> 8.9161157 | K85: =J85 -> 8.9161157 | L85: =K85 -> 8.9161157
C86: Retained Earnings | F86: ='Financials from CIP'!D72/1000 -> 48.248887 | G86: ='Financials from CIP'!E72/1000 -> 55.852505 | H86: =G86+H33 -> 62.930877 | I86: =H86+I33 -> 71.528192 | J86: =I86+J33 -> 81.494142 | K86: =J86+K33 -> 92.567038 | L86: =K86+L33 -> 104.37951
C87: Total Liabilities & Shareholders' Equity | F87: =SUM(F84:F86) -> 83.924939 | G87: =SUM(G84:G86) -> 86.938043 | H87: =SUM(H84:H86) -> 81.94286 | I87: =SUM(I84:I86) -> 92.022488 | J87: =SUM(J84:J86) -> 103.36362 | K87: =SUM(K84:K86) -> 115.60563 | L87: =SUM(L84:L86) -> 128.28558
C89: Check (should be zero) | F89: =F87-F70 -> 8.2790072e-07 | G89: =G87-G70 -> -5.041918e-07 | H89: =H87-H70 -> -0.38282416 | I89: =I87-I70 -> 9.1309738 | J89: =J87-J70 -> 20.156796 | K89: =K87-K70 -> 32.683172 | L89: =L87-L70 -> 46.605048
B93: x | C93: Working Capital
F95: MRY | G95: MRY | H95: Fiscal Years Ending December 31,
C96: ($ in millions) | F96: =F$11 -> 45291 | G96: =G$11 -> 45657 | H96: =H$11 -> 46022 | I96: =I$11 -> 46387 | J96: =J$11 -> 46752 | K96: =K$11 -> 47118 | L96: =L$11 -> 47483
C98: Net Working Capital
C100: =C61 -> Accounts Receivable, Net | F100: =F61 -> 16.781419 | G100: =G61 -> 22.284722 | H100: =(H115/365)*H119 -> 24.012611 | I100: =(I115/365)*I119 -> 27.695032 | J100: =(J115/365)*J119 -> 31.111315 | K100: =(K115/365)*K119 -> 34.015669 | L100: =(L115/365)*L119 -> 36.170685 | M100: Accounts Receivable is the amount of money that people owe you for goods and services. It tends to correlate with Revenue - if Revenue goes up, it is likely that more people will owe you money. As such, this item follows Revenue, variably, through a ratio called Days Sales Outstanding, or DSO. See more on DSO, below. We use DSOs to inform us what our Accounts Receivable will be at the Revenue we are projecting. The formula is (Sales/# of Days in the Period)*DSO Ratio
C101: =C62 -> Inventory | F101: =F62 -> 0.804901 | G101: =G62 -> 1.161057 | H101: =(H116/365)*H120 -> 1.2029011 | I101: =(I116/365)*I120 -> 1.3873704 | J101: =(J116/365)*J120 -> 1.5585076 | K101: =(K116/365)*K120 -> 1.7039999 | L101: =(L116/365)*L120 -> 1.8119545 | M101: Inventory is the stuff that you sell. As such, it tends to correlate with CoGS. The higher my Sales, will mean that my CoGS go up too (see above) so I may want to keep more inventory around to keep up. As such, this item follows CoGS, variably, through a ratio called DIOH. See more on DIOH, below. We use DIOH to project how much inventory we will keep around to keep up with our Sales momentum. The formula to use is (CoGS/# of Days in the Period)*DIOH Ratio
C102: =C63 -> Prepaids and Other Current Assets | F102: =F63 -> 0.269784 | G102: =G63 -> 0.344919 | H102: =H121*H117 -> 0.37922157 | I102: =I121*I117 -> 0.43737657 | J102: =J121*J117 -> 0.49132856 | K102: =K121*K117 -> 0.53719587 | L102: =L121*L117 -> 0.57122918 | M102: What's in Other Assets? I don't know either. We know that it is some Prepaid Costs, such as Insurance, but what else? It could be Supplies. Because we don't know, we use SG&A as a Driver, assuming that things we typically Prepay (Rent and Insurance) would be SG&A. The formula to use here is the % we calculated, below * SG&A. I will make this driver variable because SG&A was variable
C103: Non-Cash Current Assets | F103: =SUM(F100:F102) -> 17.856104 | G103: =SUM(G100:G102) -> 23.790698 | H103: =SUM(H100:H102) -> 25.594734 | I103: =SUM(I100:I102) -> 29.519779 | J103: =SUM(J100:J102) -> 33.161151 | K103: =SUM(K100:K102) -> 36.256865 | L103: =SUM(L100:L102) -> 38.553869
C105: =C74 -> Accounts Payable | F105: =F74 -> 2.805817 | G105: =G74 -> 2.36071 | H105: =(H116/365)*H123 -> 3.2375303 | I105: =(I116/365)*I123 -> 3.7340173 | J105: =(J116/365)*J123 -> 4.1946219 | K105: =(K116/365)*K123 -> 4.5862051 | L105: =(L116/365)*L123 -> 4.8767579 | M105: Accounts Payable is the amount of money that you owe your vendors for the goods and services that go into your CoGS. It tends to correlate with CoGS - if CoGS go up, it is likely that you will buy more things and your bills will be higher. As such, this item follows CoGS, variably, through a ratio called Days Payable Outstanding, or DPO. See more on DPO, below. We use DPOs to inform us what our Accounts Payable will be at the Revenue we are projecting. The formula is (CoGS/# of Days in the Period)*DPO Ratio
C106: =C75 -> Wages Payable | F106: =F75 -> 2.383933 | G106: =G75 -> 2.788038 | H106: =H124*H117 -> 3.1966854 | I106: =I124*I117 -> 3.6869088 | J106: =J124*J117 -> 4.1417024 | K106: =K124*K117 -> 4.5283453 | L106: =L124*L117 -> 4.8152325 | M106: Wages Payable is for money we owe to our employees but have not paid yet. This is common in business practice. When you first start a job, it is common for you to start getting paid a few weeks after you start - because people are paid behind when they earn it, called "Arrears." If you leave a job, you are paid what you owe up to that day. The formula to use here is the % we calculated, below *SG&A because that is where the costs of Payroll and Wages are captured
C107: =C76 -> Accrued Expenses & Other | F107: =F76 -> 2.057908 | G107: =G76 -> 3.202031 | H107: =H125*H117 -> 3.2317637 | I107: =I125*I117 -> 3.7273664 | J107: =J125*J117 -> 4.1871506 | K107: =K125*K117 -> 4.5780363 | L107: =L125*L117 -> 4.8680716 | M107: Accrued Expenses are just like Accounts Payable except it is for other money we owe. See the explanation below. The formula to use here is the % we calculated, below *SG&A
C108: Non-Debt Current Liabilities | F108: =SUM(F105:F107) -> 7.247658 | G108: =SUM(G105:G107) -> 8.350779 | H108: =SUM(H105:H107) -> 9.6659794 | I108: =SUM(I105:I107) -> 11.148292 | J108: =SUM(J105:J107) -> 12.523475 | K108: =SUM(K105:K107) -> 13.692587 | L108: =SUM(L105:L107) -> 14.560062
C109: Net Working Capital, without Cash | F109: =F103-F108 -> 10.608446 | G109: =G103-G108 -> 15.439919 | H109: =H103-H108 -> 15.928754 | I109: =I103-I108 -> 18.371486 | J109: =J103-J108 -> 20.637676 | K109: =K103-K108 -> 22.564278 | L109: =L103-L108 -> 23.993807
C111: Change in Net Working Capital | G111: =G109-F109 -> 4.831473 | H111: =H109-G109 -> 0.4888351 | I111: =I109-H109 -> 2.4427323 | J111: =J109-I109 -> 2.2661896 | K111: =K109-J109 -> 1.9266021 | L111: =L109-K109 -> 1.429529 | M111: Given this is important for the Cash Flow Statement, let's make sure we calculate this here now. It is equal to this period's Net Working Capital minus last period's Net Working Capital
C113: Working Capital Drivers
C115: Sales | F115: =F13 -> 78.565676 | G115: =G13 -> 90.614008 | H115: =H13 -> 104.51 | I115: =I13 -> 120.53698 | J115: =J13 -> 135.40566 | K115: =K13 -> 148.04627 | L115: =L13 -> 157.42554 | M115: Link to Sales in P&L (this just makes life a little easier for the ratios we will build, below)
C116: COGS | F116: =F14 -> 51.562189 | G116: =G14 -> 61.618676 | H116: =H14 -> 69.828708 | I116: =I14 -> 80.537195 | J116: =J14 -> 90.47175 | K116: =K14 -> 98.917617 | L116: =L14 -> 105.18441 | M116: Link to Sales in P&L (this just makes life a little easier for the ratios we will build, below)
C117: SG&A | F117: =F17 -> 14.179915 | G117: =G17 -> 15.436689 | H117: =H17 -> 18.333217 | I117: =I17 -> 21.144682 | J117: =J17 -> 23.752955 | K117: =K17 -> 25.97038 | L117: =L17 -> 27.615698 | M117: Link to Sales in P&L (this just makes life a little easier for the ratios we will build, below)
C119: DSO - Accounts Receivable Days Outstanding | F119: =F100/(F115/365) -> 77.963027 | G119: =G100/(G115/365) -> 89.764527 | H119: =AVERAGE(F119:G119) -> 83.863777 | I119: =H119 -> 83.863777 | J119: =I119 -> 83.863777 | K119: =J119 -> 83.863777 | L119: =K119 -> 83.863777 | M119: DSO stands for "Days Sales Outstanding." It tells you how long it takes you to collect from customers, on average, by giving you the number of days of individual sales that are outstanding (aka, have not been collected yet). It is calculated as: Accounts Receivable Balance / (Total Sales / # Days in the Period)
C120: DIOH - Day of Inventory on Hand | F120: =F101/(F116/365) -> 5.6977578 | G120: =G101/(G116/365) -> 6.8775545 | H120: =AVERAGE(F120:G120) -> 6.2876562 | I120: =H120 -> 6.2876562 | J120: =I120 -> 6.2876562 | K120: =J120 -> 6.2876562 | L120: =K120 -> 6.2876562 | M120: DIOH stands for "Days of Inventory On Hand." It tells you how much inventory you carry at your location, on average, by giving you the number of days of individual CoGS that you have in inventory (aka, how much inventory do I have now)
C121: Prepaids & Other Current Assets / SG&A (%) | F121: =F102/F117 -> 0.019025784 | G121: =G102/G117 -> 0.022344105 | H121: =AVERAGE(F121:G121) -> 0.020684945 | I121: =H121 -> 0.020684945 | J121: =I121 -> 0.020684945 | K121: =J121 -> 0.020684945 | L121: =K121 -> 0.020684945 | M121: We don't really have a good driver for this, so let's choose SG&A, given that's where the costs are most likely captured. It will fluctuate as SG&A moves around
C123: DPO - Accounts Payable Days Outstanding | F123: =F105/(F116/365) -> 19.861903 | G123: =G105/(G116/365) -> 13.983734 | H123: =AVERAGE(F123:G123) -> 16.922818 | I123: =H123 -> 16.922818 | J123: =I123 -> 16.922818 | K123: =J123 -> 16.922818 | L123: =K123 -> 16.922818 | M123: DPO stands for "Days Payable Outstanding." It tells you how long it takes you to pay your vendors (usually related to CoGS only), on average, by giving you the number of days of individual CoGS that are outstanding (aka, have you have not paid yet). It is calculated as: Accounts Payable Balance / (Total CoGS / # Days in the Period)
C124: Wages Payable / SG&A (%) | F124: =F106/F117 -> 0.1681204 | G124: =G106/G117 -> 0.18061114 | H124: =AVERAGE(F124:G124) -> 0.17436577 | I124: =H124 -> 0.17436577 | J124: =I124 -> 0.17436577 | K124: =J124 -> 0.17436577 | L124: =K124 -> 0.17436577 | M124: We don't really have a good driver for this, so let's choose SG&A, given that's where the costs are captured. It will fluctuate as SG&A moves around
C125: Accrued Expenses & Other / SG&A (%) | F125: =F107/F117 -> 0.14512837 | G125: =G107/G117 -> 0.20742991 | H125: =AVERAGE(F125:G125) -> 0.17627914 | I125: =H125 -> 0.17627914 | J125: =I125 -> 0.17627914 | K125: =J125 -> 0.17627914 | L125: =K125 -> 0.17627914 | M125: Accrued Expenses is how much money you owe your vendors that are not CoGS (think like your utility bill, etc). We can also make this one a % but it will most closely follow SG&A. Let's choose that as our driver
B130: x | C130: Checks to Source
C131: Income Statement
C132: Revenue | F132: ='Financials from CIP'!D13/1000-'Step 4 Answer Key'!F13 -> 0 | G132: ='Financials from CIP'!E13/1000-'Step 4 Answer Key'!G13 -> 0
C133: Gross Profit | F133: ='Financials from CIP'!D19/1000-'Step 4 Answer Key'!F15 -> 0 | G133: ='Financials from CIP'!E19/1000-'Step 4 Answer Key'!G15 -> 0
C134: EBITDA | F134: ='Financials from CIP'!D36/1000-'Step 4 Answer Key'!F18 -> 0 | G134: ='Financials from CIP'!E36/1000-'Step 4 Answer Key'!G18 -> 0
C135: Net Income | F135: ='Financials from CIP'!D34/1000-'Step 4 Answer Key'!F33 -> 0 | G135: ='Financials from CIP'!E34/1000-'Step 4 Answer Key'!G33 -> 0
C137: Balance Sheet
C138: Cash | F138: ='Financials from CIP'!D46/1000-'Step 4 Answer Key'!F60 -> 0 | G138: ='Financials from CIP'!E46/1000-'Step 4 Answer Key'!G60 -> 0
...

Sheet Step 5
C2: Athena Modeling Exercise
C3: Step 5 - Watch. Cash. Flow
N4: Quote the Banker, “Watch Cash Flow” ~ Herbert S Bailey Jr, © 1975
J5: Black font = Calculation
C6: YELLOWS ARE FILLS | F6: SKIP FOR NOW | J6: Blue font = Hardcoded Input/Assumption
J7: Green font = Pulled from another Sheet
B8: x | C8: Income Statement
F10: MRY | G10: MRY | H10: Fiscal Years Ending December 31,
C11: ($ in millions) | F11: =EOMONTH(G11,-12) -> 45291 | G11: 45657 | H11: =EOMONTH(G11,12) -> 46022 | I11: =EOMONTH(H11,12) -> 46387 | J11: =EOMONTH(I11,12) -> 46752 | K11: =EOMONTH(J11,12) -> 47118 | L11: =EOMONTH(K11,12) -> 47483
C13: Total Revenue | F13: ='Financials from CIP'!D13/1000 -> 78.565676 | G13: ='Financials from CIP'!E13/1000 -> 90.614008 | H13: =(1+H41)*G13 -> 104.51 | I13: =(1+I41)*H13 -> 120.53698 | J13: =(1+J41)*I13 -> 135.40566 | K13: =(1+K41)*J13 -> 148.04627 | L13: =(1+L41)*K13 -> 157.42554
C14: COGS | F14: =SUM('Financials from CIP'!D15:D17)/1000 -> 51.562189 | G14: =SUM('Financials from CIP'!E15:E17)/1000 -> 61.618676 | H14: =H43*H13 -> 69.828708 | I14: =I43*I13 -> 80.537195 | J14: =J43*J13 -> 90.47175 | K14: =K43*K13 -> 98.917617 | L14: =L43*L13 -> 105.18441
C15: Gross Profit | F15: =F13-F14 -> 27.003487 | G15: =G13-G14 -> 28.995332 | H15: =H13-H14 -> 34.681287 | I15: =I13-I14 -> 39.999789 | J15: =J13-J14 -> 44.933908 | K15: =K13-K14 -> 49.128652 | L15: =L13-L14 -> 52.24113
C16: Gross Margin (%) | F16: =IFERROR(F15/F$13,"N/M") -> 0.34370591 | G16: =IFERROR(G15/G$13,"N/M") -> 0.3199873 | H16: =IFERROR(H15/H$13,"N/M") -> 0.33184661 | I16: =IFERROR(I15/I$13,"N/M") -> 0.33184661 | J16: =IFERROR(J15/J$13,"N/M") -> 0.33184661 | K16: =IFERROR(K15/K$13,"N/M") -> 0.33184661 | L16: =IFERROR(L15/L$13,"N/M") -> 0.33184661
C17: SG&A | F17: =SUM('Financials from CIP'!D23:D24,'Financials from CIP'!D28)/1000 -> 14.179915 | G17: =SUM('Financials from CIP'!E23:E24,'Financials from CIP'!E28)/1000 -> 15.436689 | H17: =H44*H13 -> 18.333217 | I17: =I44*I13 -> 21.144682 | J17: =J44*J13 -> 23.752955 | K17: =K44*K13 -> 25.97038 | L17: =L44*L13 -> 27.615698
C18: EBITDA | F18: =F15-F17 -> 12.823572 | G18: =G15-G17 -> 13.558643 | H18: =H15-H17 -> 16.348071 | I18: =I15-I17 -> 18.855107 | J18: =J15-J17 -> 21.180953 | K18: =K15-K17 -> 23.158272 | L18: =L15-L17 -> 24.625432
C19: EBITDA Margin (%) | F19: =IFERROR(F18/F$13,"N/M") -> 0.16322105 | G19: =IFERROR(G18/G$13,"N/M") -> 0.14963076 | H19: =IFERROR(H18/H$13,"N/M") -> 0.15642591 | I19: =IFERROR(I18/I$13,"N/M") -> 0.15642591 | J19: =IFERROR(J18/J$13,"N/M") -> 0.15642591 | K19: =IFERROR(K18/K$13,"N/M") -> 0.15642591 | L19: =IFERROR(L18/L$13,"N/M") -> 0.15642591
C20: Depreciation | F20: ='Financials from CIP'!D25/1000 -> 1.1801621 | G20: ='Financials from CIP'!E25/1000 -> 1.1617643 | H20: =H194 -> 5.8293926 | I20: =I194 -> 6.1302958 | J20: =J194 -> 6.4683165 | K20: =K194 -> 6.8378927 | L20: =L194 -> 7.2308829
C21: Amortization | F21: ='Financials from CIP'!D26/1000 -> 0.208264 | G21: ='Financials from CIP'!E26/1000 -> 0.237952 | H21: =MIN(G21,G69) -> 0.237952 | I21: =MIN(H21,H69) -> 0.237952 | J21: =MIN(I21,I69) -> 0.237952 | K21: =MIN(J21,J69) -> 0.237952 | L21: =MIN(K21,K69) -> 0.237952
C22: EBIT | F22: =F18-SUM(F20:F21) -> 11.435146 | G22: =G18-SUM(G20:G21) -> 12.158927 | H22: =H18-SUM(H20:H21) -> 10.280726 | I22: =I18-SUM(I20:I21) -> 12.486859 | J22: =J18-SUM(J20:J21) -> 14.474684 | K22: =K18-SUM(K20:K21) -> 16.082427 | L22: =L18-SUM(L20:L21) -> 17.156597
C23: Interest (Income) / Expense
C24: Revolver – Interest
C25: Revolver – Undrawn Commitment Fee
C26: =+C79 -> Term Loan A
C27: =+C80 -> Subordinated - Note 1
C28: =+C81 -> Subordinated - Note 2
C29: Interest (Income) / Expense | F29: ='Financials from CIP'!D27/1000 -> 2.224955 | G29: ='Financials from CIP'!E27/1000 -> 1.472763 | H29: =SUM(H24:H28) -> 0 | I29: =SUM(I24:I28) -> 0 | J29: =SUM(J24:J28) -> 0 | K29: =SUM(K24:K28) -> 0 | L29: =SUM(L24:L28) -> 0
C30: Other (Income) / Expense | F30: ='Financials from CIP'!D32/1000 -> 0.147371 | G30: ='Financials from CIP'!E32/1000 -> 0.273439 | H30: 0 | I30: 0 | J30: 0 | K30: 0 | L30: 0
C31: Income Before Taxes | F31: =F22-F29-F30 -> 9.0628199 | G31: =G22-G29-G30 -> 10.412725 | H31: =H22-H29-H30 -> 10.280726 | I31: =I22-I29-I30 -> 12.486859 | J31: =J22-J29-J30 -> 14.474684 | K31: =K22-K29-K30 -> 16.082427 | L31: =L22-L29-L30 -> 17.156597
C32: Provision for Tax | F32: ='Financials from CIP'!D29/1000 -> 3.201039 | G32: ='Financials from CIP'!E29/1000 -> 2.809107 | H32: =H46*H31 -> 3.2023536 | I32: =I46*I31 -> 3.8895441 | J32: =J46*J31 -> 4.5087338 | K32: =K46*K31 -> 5.0095311 | L32: =L46*L31 -> 5.3441256
C33: Net Income | F33: =F31-F32 -> 5.8617809 | G33: =G31-G32 -> 7.6036178 | H33: =H31-H32 -> 7.0783725 | I33: =I31-I32 -> 8.5973148 | J33: =J31-J32 -> 9.9659504 | K33: =K31-K32 -> 11.072896 | L33: =L31-L32 -> 11.812472
C34: Profit Margin (%) | F34: =IFERROR(F33/F$13,"N/M") -> 0.074609947 | G34: =IFERROR(G33/G$13,"N/M") -> 0.083912167 | H34: =IFERROR(H33/H$13,"N/M") -> 0.067729144 | I34: =IFERROR(I33/I$13,"N/M") -> 0.07132512 | J34: =IFERROR(J33/J$13,"N/M") -> 0.073600694 | K34: =IFERROR(K33/K$13,"N/M") -> 0.074793481 | L34: =IFERROR(L33/L$13,"N/M") -> 0.075035296
C36: Capital Expenditures | G36: =('Financials from CIP'!E53-'Financials from CIP'!D53+'Financials from CIP'!E25)/1000 -> 2.2620483 | H36: =H48*H13 -> 2.6089416 | I36: =I48*I13 -> 3.0090323 | J36: =J48*J13 -> 3.3802074 | K36: =K48*K13 -> 3.695762 | L36: =L48*L13 -> 3.929902
C39: Key Performance Metrics & Drivers
C41: Sales Growth (%) | G41: =G13/F13-1 -> 0.15335363 | H41: =G41 -> 0.15335363 | I41: =H41 -> 0.15335363 | J41: =I41-3% -> 0.12335363 | K41: =J41-3% -> 0.093353635 | L41: =K41-3% -> 0.063353635
C43: COGS / Sales (%) | F43: =F14/F13 -> 0.65629409 | G43: =G14/G13 -> 0.6800127 | H43: =AVERAGE(F43:G43) -> 0.66815339 | I43: =H43 -> 0.66815339 | J43: =I43 -> 0.66815339 | K43: =J43 -> 0.66815339 | L43: =K43 -> 0.66815339
C44: SG&A / Sales (%) | F44: =F17/F13 -> 0.18048486 | G44: =G17/G13 -> 0.17035654 | H44: =AVERAGE(F44:G44) -> 0.1754207 | I44: =H44 -> 0.1754207 | J44: =I44 -> 0.1754207 | K44: =J44 -> 0.1754207 | L44: =K44 -> 0.1754207
C46: Tax Rate (%) | F46: =F32/F31 -> 0.35320563 | G46: =G32/G31 -> 0.26977636 | H46: =AVERAGE(F46:G46) -> 0.31149099 | I46: =H46 -> 0.31149099 | J46: =I46 -> 0.31149099 | K46: =J46 -> 0.31149099 | L46: =K46 -> 0.31149099
C48: Capex / Sales (%) | G48: =G36/G13 -> 0.024963561 | H48: =G48 -> 0.024963561 | I48: =H48 -> 0.024963561 | J48: =I48 -> 0.024963561 | K48: =J48 -> 0.024963561 | L48: =K48 -> 0.024963561
B53: x | C53: Balance Sheet
F55: MRY | G55: MRY | H55: Fiscal Years Ending December 31,
C56: ($ in millions) | F56: =EOMONTH(G56,-12) -> 45291 | G56: =G$11 -> 45657 | H56: =H$11 -> 46022 | I56: =I$11 -> 46387 | J56: =J$11 -> 46752 | K56: =K$11 -> 47118 | L56: =L$11 -> 47483
C58: Assets
C60: Cash and Equivalents | F60: ='Financials from CIP'!D46/1000 -> 7.105652 | G60: ='Financials from CIP'!E46/1000 -> 2.957992 | M60: Cash will move based on the Net Income you made and how your business ran (Operating Activities), the cash you invested (Investing Activities) and the cash you had come in or out from Financing (Financing Activites, which we will do in a later step). The Cash balance on this line is the Cash resulting at the END of each period. So it is equal to the Cash from last period + the change in cash this period. As such, Cash in 2025 is equal to Cash Balance from last year (G60) plus the change in cash this year (H119).
C61: Accounts Receivable, Net | F61: =SUM('Financials from CIP'!D47:D48)/1000 -> 16.781419 | G61: =SUM('Financials from CIP'!E47:E48)/1000 -> 22.284722 | H61: =H130 -> 24.012611 | I61: =I130 -> 27.695032 | J61: =J130 -> 31.111315 | K61: =K130 -> 34.015669 | L61: =L130 -> 36.170685
C62: Inventory | F62: ='Financials from CIP'!D49/1000 -> 0.804901 | G62: ='Financials from CIP'!E49/1000 -> 1.161057 | H62: =H131 -> 1.2029011 | I62: =I131 -> 1.3873704 | J62: =J131 -> 1.5585076 | K62: =K131 -> 1.7039999 | L62: =L131 -> 1.8119545
C63: Prepaids and Other Current Assets | F63: ='Financials from CIP'!D50/1000 -> 0.269784 | G63: ='Financials from CIP'!E50/1000 -> 0.344919 | H63: =H132 -> 0.37922157 | I63: =I132 -> 0.43737657 | J63: =J132 -> 0.49132856 | K63: =K132 -> 0.53719587 | L63: =L132 -> 0.57122918
C64: Total Current Assets | F64: =SUM(F60:F63) -> 24.961756 | G64: =SUM(G60:G63) -> 26.74869 | H64: =SUM(H60:H63) -> 25.594734 | I64: =SUM(I60:I63) -> 29.519779 | J64: =SUM(J60:J63) -> 33.161151 | K64: =SUM(K60:K63) -> 36.256865 | L64: =SUM(L60:L63) -> 38.553869
C65: PP&E, Gross | H65: =G67+H36 -> 58.293926 | I65: =H65+I36 -> 61.302958 | J65: =I65+J36 -> 64.683165 | K65: =J65+K36 -> 68.378927 | L65: =K65+L36 -> 72.308829
C66: ( – ) Accumulated Depreciation | H66: =G66-H20 -> -5.8293926 | I66: =H66-I20 -> -11.959688 | J66: =I66-J20 -> -18.428005 | K66: =J66-K20 -> -25.265898 | L66: =K66-L20 -> -32.496781
C67: PP&E, Net | F67: ='Financials from CIP'!D53/1000 -> 54.5847 | G67: ='Financials from CIP'!E53/1000 -> 55.684984 | H67: =SUM(H65:H66) -> 52.464533 | I67: =SUM(I65:I66) -> 49.34327 | J67: =SUM(J65:J66) -> 46.25516 | K67: =SUM(K65:K66) -> 43.11303 | L67: =SUM(L65:L66) -> 39.812049
C68: Goodwill | F68: 0 | G68: 0 | H68: 0 | I68: 0 | J68: 0 | K68: 0 | L68: 0
C69: Intangible and Long-Term Other Assets | F69: ='Financials from CIP'!D54/1000 -> 4.378482 | G69: ='Financials from CIP'!E54/1000 -> 4.50437 | H69: =G69-H21 -> 4.266418 | I69: =H69-I21 -> 4.028466 | J69: =I69-J21 -> 3.790514 | K69: =J69-K21 -> 3.552562 | L69: =K69-L21 -> 3.31461
C70: Total Assets | F70: =SUM(F64,F67:F69) -> 83.924938 | G70: =SUM(G64,G67:G69) -> 86.938044 | H70: =SUM(H64,H67:H69) -> 82.325685 | I70: =SUM(I64,I67:I69) -> 82.891514 | J70: =SUM(J64,J67:J69) -> 83.206825 | K70: =SUM(K64,K67:K69) -> 82.922457 | L70: =SUM(L64,L67:L69) -> 81.680528
C72: Liabilities & Shareholders' Equity
C74: Accounts Payable | F74: ='Financials from CIP'!D58/1000 -> 2.805817 | G74: ='Financials from CIP'!E58/1000 -> 2.36071 | H74: =H135 -> 3.2375303 | I74: =I135 -> 3.7340173 | J74: =J135 -> 4.1946219 | K74: =K135 -> 4.5862051 | L74: =L135 -> 4.8767579
C75: Wages Payable | F75: ='Financials from CIP'!D59/1000 -> 2.383933 | G75: ='Financials from CIP'!E59/1000 -> 2.788038 | H75: =H136 -> 3.1966854 | I75: =I136 -> 3.6869088 | J75: =J136 -> 4.1417024 | K75: =K136 -> 4.5283453 | L75: =L136 -> 4.8152325
C76: Accrued Expenses & Other | F76: ='Financials from CIP'!D60/1000 -> 2.057908 | G76: ='Financials from CIP'!E60/1000 -> 3.202031 | H76: =H137 -> 3.2317637 | I76: =I137 -> 3.7273664 | J76: =J137 -> 4.1871506 | K76: =K137 -> 4.5780363 | L76: =L137 -> 4.8680716
C77: Total Current Liabilities | F77: =SUM(F74:F76) -> 7.247658 | G77: =SUM(G74:G76) -> 8.350779 | H77: =SUM(H74:H76) -> 9.6659794 | I77: =SUM(I74:I76) -> 11.148292 | J77: =SUM(J74:J76) -> 12.523475 | K77: =SUM(K74:K76) -> 13.692587 | L77: =SUM(L74:L76) -> 14.560062
C78: Revolver | F78: ='Financials from CIP'!D63/1000 -> 0.645883 | G78: ='Financials from CIP'!E63/1000 -> 1.2893
C79: Term Loan A | F79: ='Financials from CIP'!D64/1000 -> 18.943222 | G79: ='Financials from CIP'!E64/1000 -> 12.001451
C80: Subordinated - Note 1 | F80: ='Financials from CIP'!D65/1000 -> 0.545333 | G80: ='Financials from CIP'!E65/1000 -> 0.085338
C81: Subordinated - Note 2 | F81: ='Financials from CIP'!D66/1000 -> 0.092448 | G81: ='Financials from CIP'!E66/1000 -> 0.012667
C82: Total Debt | F82: =SUM(F78:F81) -> 20.226886 | G82: =SUM(G78:G81) -> 13.388756 | H82: =SUM(H78:H81) -> 0 | I82: =SUM(I78:I81) -> 0 | J82: =SUM(J78:J81) -> 0 | K82: =SUM(K78:K81) -> 0 | L82: =SUM(L78:L81) -> 0
C83: Other Long-term Liabilities | F83: ='Financials from CIP'!D67/1000 -> 0.417874 | G83: ='Financials from CIP'!E67/1000 -> 0.429888 | H83: =G83 -> 0.429888 | I83: =H83 -> 0.429888 | J83: =I83 -> 0.429888 | K83: =J83 -> 0.429888 | L83: =K83 -> 0.429888
C84: Total liabilities | F84: =SUM(F77,F82:F83) -> 27.892418 | G84: =SUM(G77,G82:G83) -> 22.169423 | H84: =SUM(H77,H82:H83) -> 10.095867 | I84: =SUM(I77,I82:I83) -> 11.57818 | J84: =SUM(J77,J82:J83) -> 12.953363 | K84: =SUM(K77,K82:K83) -> 14.122475 | L84: =SUM(L77,L82:L83) -> 14.98995
C85: Common Stock | F85: ='Financials from CIP'!D71/1000 -> 7.7836338 | G85: ='Financials from CIP'!E71/1000 -> 8.9161157 | H85: =G85 -> 8.9161157 | I85: =H85 -> 8.9161157 | J85: =I85 -> 8.9161157 | K85: =J85 -> 8.9161157 | L85: =K85 -> 8.9161157
C86: Retained Earnings | F86: ='Financials from CIP'!D72/1000 -> 48.248887 | G86: ='Financials from CIP'!E72/1000 -> 55.852505 | H86: =G86+H33 -> 62.930877 | I86: =H86+I33 -> 71.528192 | J86: =I86+J33 -> 81.494142 | K86: =J86+K33 -> 92.567038 | L86: =K86+L33 -> 104.37951
C87: Total Liabilities & Shareholders' Equity | F87: =SUM(F84:F86) -> 83.924939 | G87: =SUM(G84:G86) -> 86.938043 | H87: =SUM(H84:H86) -> 81.94286 | I87: =SUM(I84:I86) -> 92.022488 | J87: =SUM(J84:J86) -> 103.36362 | K87: =SUM(K84:K86) -> 115.60563 | L87: =SUM(L84:L86) -> 128.28558
C89: Check (should be zero) | F89: =F87-F70 -> 8.2790072e-07 | G89: =G87-G70 -> -5.041918e-07 | H89: =H87-H70 -> -0.38282416 | I89: =I87-I70 -> 9.1309738 | J89: =J87-J70 -> 20.156796 | K89: =K87-K70 -> 32.683172 | L89: =L87-L70 -> 46.605048
B93: x | C93: Cash Flow Statement
F95: MRY | G95: MRY | H95: Fiscal Years Ending December 31,
C96: ($ in millions) | F96: =F$11 -> 45291 | G96: =G$11 -> 45657 | H96: =H$11 -> 46022 | I96: =I$11 -> 46387 | J96: =J$11 -> 46752 | K96: =K$11 -> 47118 | L96: =L$11 -> 47483
C98: Operating Activities | M98: Now it is time to tie everything together with cash flow. Let's map the change in Cash (WHERE did Cash go) using WHAT happened in the Income Statement and HOW it affected the business on the Balance Sheet
C100: Net Income | M100: Start with Net Income - this is the result of ALL Revenue and Expenses (including ones that do not affect cash). Starting here, we will next add the non-cash expenses from the P&L. Link this to the P&L as a POSITIVE to INCREASE the effect on cash - Net income removed it, we add it back to CASH flow
C101: Depreciation | M101: Depreciation is an expense that reflects the decrease in value of long-term, physical (tangible) assets. It does not affect Cash - it is a non-Cash expense that is meant to reflect the "wear and tear" of Long-term Assets that you are using to produce Revenue over time. However, Deprecistion does affect the value of Long-term Assets directly - it is a reduction to our Assets for the loss in value of the Assets related to "wear and tear" and aging. So because we are "losing" the value of these Assets because we are using them, and because they are getting older - and presumably "less useful to us", it is a reduction in our ownership value of those Assets too. That reduction in ownership value shows as an Expense and, eventually, to Equity through Retained Earnings. As such, because it is a non-cash expense, we add in back to Net Income for the purposes of the CASH Flow statement. Link this to the P&L as a POSITIVE to INCREASE the effect on cash - Net Income is already lower because Depreciation Expense is in it... so we add it back to CASH Flow to REMOVE the effect that Depreciation has on Net Income to show actual Cash Flow
C102: Amortization of Intangibles | M102: Amortization is an expense that reflects the decrease in value of long-term, non-physical (intangible) assets. It also does not affect Cash - it is a non-Cash expense that is meant to reflect the "use" of Long-term Intangible Assets that you are using to produce Revenue over time. However, Amortization does affect the value of Long-term Intangible Assets directly - it is a reduction to our Assets for the loss in value of the Intangible Assets related to use and aging. So because we are "losing" the value of these Assets because we are using them, and because they are getting older - and presumably "less useful to us", it is a reduction in our ownership value of those Intangible Assets too. That reduction in ownership value shows as an Expense and, eventually, to Equity through Retained Earnings. As such, because it is a non-cash expense, we add in back to Net Income for the purposes of the CASH Flow statement. Link this to the P&L as a POSITIVE to INCREASE the effect on cash - Net Income is already lower because Amortization Expense is in it... so we add it back to CASH Flow to REMOVE the effect that Amortization has on Net Income to show actual Cash Flow
C103: Net Income + Non-Cash Expense Adjustments | H103: =SUM(H100:H102) -> 0 | I103: =SUM(I100:I102) -> 0 | J103: =SUM(J100:J102) -> 0 | K103: =SUM(K100:K102) -> 0 | L103: =SUM(L100:L102) -> 0 | M103: These are the total adjustments added to Net Income to get a "cash basis" of Net Income. However, these adjustments are only the first step in calculating our changes in Cash related to Operating activities. HOW fast the business collected money, paid money, etc also needs to be considered for the change in CASH. As such, we look at the change in Current Assets and Current Liabilities that are not Debt to see the effect they have on cash as well
C104: (Increase) / Decrease in Working Capital | M104: Working Capital can be tricky to think through and counter intuitive but think of it this way: If Working Capital goes up, it means that we have an INCREASE in Assets compared with the change in Liabilities. This means that Assets either went up or Liabilities went down period over period. If Assets go up, it means that we either did not collect money, or used money, for our Assets to increase. Althernatively, if Liabilities went down we USED money to pay off some money we owe. Either way, an INCREASE in Working Capital is a DECREASE in cash - we have less cash in our pocket. We link to the Working Capital section, below
C105: Cash flow from Operating Activities | H105: =+SUM(H103:H104) -> 0 | I105: =+SUM(I103:I104) -> 0 | J105: =+SUM(J103:J104) -> 0 | K105: =+SUM(K103:K104) -> 0 | L105: =+SUM(L103:L104) -> 0
C107: Investing Activities
C109: Cash flow from Investment Activities - CapEx | M109: Cash flow from investing activities is the cash paid for Long-term Assets (physical and non-physical. Is is a USE of Cash when Assets go up (we bought something) so it DECREASES the Cash balance. If our value went down, it would most likely meant we sold something (net of Depreciation). We link it to CapEx and remove it to DECREASE the cash balance, here
C111: Financing Activities
C113: Revolver
C114: =+C79 -> Term Loan A
C115: =+C80 -> Subordinated - Note 1
C116: =+C81 -> Subordinated - Note 2
C117: Cash flow from Financing Activities | H117: =SUM(H113:H116) -> 0 | I117: =SUM(I113:I116) -> 0 | J117: =SUM(J113:J116) -> 0 | K117: =SUM(K113:K116) -> 0 | L117: =SUM(L113:L116) -> 0
C119: Change in Cash | M119: Sum up the Cash Effects from the Operating Activites, Investing Activities and Financing Activities sections
B123: x | C123: Working Capital
F125: MRY | G125: MRY | H125: Fiscal Years Ending December 31,
C126: ($ in millions) | F126: =F$11 -> 45291 | G126: =G$11 -> 45657 | H126: =H$11 -> 46022 | I126: =I$11 -> 46387 | J126: =J$11 -> 46752 | K126: =K$11 -> 47118 | L126: =L$11 -> 47483
C128: Net Working Capital
C130: =C61 -> Accounts Receivable, Net | F130: =F61 -> 16.781419 | G130: =G61 -> 22.284722 | H130: =(H145/365)*H149 -> 24.012611 | I130: =(I145/365)*I149 -> 27.695032 | J130: =(J145/365)*J149 -> 31.111315 | K130: =(K145/365)*K149 -> 34.015669 | L130: =(L145/365)*L149 -> 36.170685
C131: =C62 -> Inventory | F131: =F62 -> 0.804901 | G131: =G62 -> 1.161057 | H131: =(H146/365)*H150 -> 1.2029011 | I131: =(I146/365)*I150 -> 1.3873704 | J131: =(J146/365)*J150 -> 1.5585076 | K131: =(K146/365)*K150 -> 1.7039999 | L131: =(L146/365)*L150 -> 1.8119545
C132: =C63 -> Prepaids and Other Current Assets | F132: =F63 -> 0.269784 | G132: =G63 -> 0.344919 | H132: =H151*H147 -> 0.37922157 | I132: =I151*I147 -> 0.43737657 | J132: =J151*J147 -> 0.49132856 | K132: =K151*K147 -> 0.53719587 | L132: =L151*L147 -> 0.57122918
C133: Non-Cash Current Assets | F133: =SUM(F130:F132) -> 17.856104 | G133: =SUM(G130:G132) -> 23.790698 | H133: =SUM(H130:H132) -> 25.594734 | I133: =SUM(I130:I132) -> 29.519779 | J133: =SUM(J130:J132) -> 33.161151 | K133: =SUM(K130:K132) -> 36.256865 | L133: =SUM(L130:L132) -> 38.553869
C135: =C74 -> Accounts Payable | F135: =F74 -> 2.805817 | G135: =G74 -> 2.36071 | H135: =(H146/365)*H153 -> 3.2375303 | I135: =(I146/365)*I153 -> 3.7340173 | J135: =(J146/365)*J153 -> 4.1946219 | K135: =(K146/365)*K153 -> 4.5862051 | L135: =(L146/365)*L153 -> 4.8767579
C136: =C75 -> Wages Payable | F136: =F75 -> 2.383933 | G136: =G75 -> 2.788038 | H136: =H154*H147 -> 3.1966854 | I136: =I154*I147 -> 3.6869088 | J136: =J154*J147 -> 4.1417024 | K136: =K154*K147 -> 4.5283453 | L136: =L154*L147 -> 4.8152325
C137: =C76 -> Accrued Expenses & Other | F137: =F76 -> 2.057908 | G137: =G76 -> 3.202031 | H137: =H155*H147 -> 3.2317637 | I137: =I155*I147 -> 3.7273664 | J137: =J155*J147 -> 4.1871506 | K137: =K155*K147 -> 4.5780363 | L137: =L155*L147 -> 4.8680716
C138: Non-Debt Current Liabilities | F138: =SUM(F135:F137) -> 7.247658 | G138: =SUM(G135:G137) -> 8.350779 | H138: =SUM(H135:H137) -> 9.6659794 | I138: =SUM(I135:I137) -> 11.148292 | J138: =SUM(J135:J137) -> 12.523475 | K138: =SUM(K135:K137) -> 13.692587 | L138: =SUM(L135:L137) -> 14.560062
...

Sheet Step 5 Answer Key
C2: Athena Modeling Exercise
C3: Step 5 - Watch. Cash. Flow
N4: Quote the Banker, “Watch Cash Flow” ~ Herbert S Bailey Jr, © 1975
J5: Black font = Calculation
C6: YELLOWS ARE FILLS | F6: SKIP FOR NOW | J6: Blue font = Hardcoded Input/Assumption
J7: Green font = Pulled from another Sheet
B8: x | C8: Income Statement
F10: MRY | G10: MRY | H10: Fiscal Years Ending December 31,
C11: ($ in millions) | F11: =EOMONTH(G11,-12) -> 45291 | G11: 45657 | H11: =EOMONTH(G11,12) -> 46022 | I11: =EOMONTH(H11,12) -> 46387 | J11: =EOMONTH(I11,12) -> 46752 | K11: =EOMONTH(J11,12) -> 47118 | L11: =EOMONTH(K11,12) -> 47483
C13: Total Revenue | F13: ='Financials from CIP'!D13/1000 -> 78.565676 | G13: ='Financials from CIP'!E13/1000 -> 90.614008 | H13: =(1+H41)*G13 -> 104.51 | I13: =(1+I41)*H13 -> 120.53698 | J13: =(1+J41)*I13 -> 135.40566 | K13: =(1+K41)*J13 -> 148.04627 | L13: =(1+L41)*K13 -> 157.42554
C14: COGS | F14: =SUM('Financials from CIP'!D15:D17)/1000 -> 51.562189 | G14: =SUM('Financials from CIP'!E15:E17)/1000 -> 61.618676 | H14: =H43*H13 -> 69.828708 | I14: =I43*I13 -> 80.537195 | J14: =J43*J13 -> 90.47175 | K14: =K43*K13 -> 98.917617 | L14: =L43*L13 -> 105.18441
C15: Gross Profit | F15: =F13-F14 -> 27.003487 | G15: =G13-G14 -> 28.995332 | H15: =H13-H14 -> 34.681287 | I15: =I13-I14 -> 39.999789 | J15: =J13-J14 -> 44.933908 | K15: =K13-K14 -> 49.128652 | L15: =L13-L14 -> 52.24113
C16: Gross Margin (%) | F16: =IFERROR(F15/F$13,"N/M") -> 0.34370591 | G16: =IFERROR(G15/G$13,"N/M") -> 0.3199873 | H16: =IFERROR(H15/H$13,"N/M") -> 0.33184661 | I16: =IFERROR(I15/I$13,"N/M") -> 0.33184661 | J16: =IFERROR(J15/J$13,"N/M") -> 0.33184661 | K16: =IFERROR(K15/K$13,"N/M") -> 0.33184661 | L16: =IFERROR(L15/L$13,"N/M") -> 0.33184661
C17: SG&A | F17: =SUM('Financials from CIP'!D23:D24,'Financials from CIP'!D28)/1000 -> 14.179915 | G17: =SUM('Financials from CIP'!E23:E24,'Financials from CIP'!E28)/1000 -> 15.436689 | H17: =H44*H13 -> 18.333217 | I17: =I44*I13 -> 21.144682 | J17: =J44*J13 -> 23.752955 | K17: =K44*K13 -> 25.97038 | L17: =L44*L13 -> 27.615698
C18: EBITDA | F18: =F15-F17 -> 12.823572 | G18: =G15-G17 -> 13.558643 | H18: =H15-H17 -> 16.348071 | I18: =I15-I17 -> 18.855107 | J18: =J15-J17 -> 21.180953 | K18: =K15-K17 -> 23.158272 | L18: =L15-L17 -> 24.625432
C19: EBITDA Margin (%) | F19: =IFERROR(F18/F$13,"N/M") -> 0.16322105 | G19: =IFERROR(G18/G$13,"N/M") -> 0.14963076 | H19: =IFERROR(H18/H$13,"N/M") -> 0.15642591 | I19: =IFERROR(I18/I$13,"N/M") -> 0.15642591 | J19: =IFERROR(J18/J$13,"N/M") -> 0.15642591 | K19: =IFERROR(K18/K$13,"N/M") -> 0.15642591 | L19: =IFERROR(L18/L$13,"N/M") -> 0.15642591
C20: Depreciation | F20: ='Financials from CIP'!D25/1000 -> 1.1801621 | G20: ='Financials from CIP'!E25/1000 -> 1.1617643 | H20: =H194 -> 5.8293926 | I20: =I194 -> 6.1302958 | J20: =J194 -> 6.4683165 | K20: =K194 -> 6.8378927 | L20: =L194 -> 7.2308829
C21: Amortization | F21: ='Financials from CIP'!D26/1000 -> 0.208264 | G21: ='Financials from CIP'!E26/1000 -> 0.237952 | H21: =MIN(G21,G69) -> 0.237952 | I21: =MIN(H21,H69) -> 0.237952 | J21: =MIN(I21,I69) -> 0.237952 | K21: =MIN(J21,J69) -> 0.237952 | L21: =MIN(K21,K69) -> 0.237952
C22: EBIT | F22: =F18-SUM(F20:F21) -> 11.435146 | G22: =G18-SUM(G20:G21) -> 12.158927 | H22: =H18-SUM(H20:H21) -> 10.280726 | I22: =I18-SUM(I20:I21) -> 12.486859 | J22: =J18-SUM(J20:J21) -> 14.474684 | K22: =K18-SUM(K20:K21) -> 16.082427 | L22: =L18-SUM(L20:L21) -> 17.156597
C23: Interest (Income) / Expense
C24: Revolver – Interest
C25: Revolver – Undrawn Commitment Fee
C26: =+C79 -> Term Loan A
C27: =+C80 -> Subordinated - Note 1
C28: =+C81 -> Subordinated - Note 2
C29: Interest (Income) / Expense | F29: ='Financials from CIP'!D27/1000 -> 2.224955 | G29: ='Financials from CIP'!E27/1000 -> 1.472763 | H29: =SUM(H24:H28) -> 0 | I29: =SUM(I24:I28) -> 0 | J29: =SUM(J24:J28) -> 0 | K29: =SUM(K24:K28) -> 0 | L29: =SUM(L24:L28) -> 0
C30: Other (Income) / Expense | F30: ='Financials from CIP'!D32/1000 -> 0.147371 | G30: ='Financials from CIP'!E32/1000 -> 0.273439 | H30: 0 | I30: 0 | J30: 0 | K30: 0 | L30: 0
C31: Income Before Taxes | F31: =F22-F29-F30 -> 9.0628199 | G31: =G22-G29-G30 -> 10.412725 | H31: =H22-H29-H30 -> 10.280726 | I31: =I22-I29-I30 -> 12.486859 | J31: =J22-J29-J30 -> 14.474684 | K31: =K22-K29-K30 -> 16.082427 | L31: =L22-L29-L30 -> 17.156597
C32: Provision for Tax | F32: ='Financials from CIP'!D29/1000 -> 3.201039 | G32: ='Financials from CIP'!E29/1000 -> 2.809107 | H32: =H46*H31 -> 3.2023536 | I32: =I46*I31 -> 3.8895441 | J32: =J46*J31 -> 4.5087338 | K32: =K46*K31 -> 5.0095311 | L32: =L46*L31 -> 5.3441256
C33: Net Income | F33: =F31-F32 -> 5.8617809 | G33: =G31-G32 -> 7.6036178 | H33: =H31-H32 -> 7.0783725 | I33: =I31-I32 -> 8.5973148 | J33: =J31-J32 -> 9.9659504 | K33: =K31-K32 -> 11.072896 | L33: =L31-L32 -> 11.812472
C34: Profit Margin (%) | F34: =IFERROR(F33/F$13,"N/M") -> 0.074609947 | G34: =IFERROR(G33/G$13,"N/M") -> 0.083912167 | H34: =IFERROR(H33/H$13,"N/M") -> 0.067729144 | I34: =IFERROR(I33/I$13,"N/M") -> 0.07132512 | J34: =IFERROR(J33/J$13,"N/M") -> 0.073600694 | K34: =IFERROR(K33/K$13,"N/M") -> 0.074793481 | L34: =IFERROR(L33/L$13,"N/M") -> 0.075035296
C36: Capital Expenditures | G36: =('Financials from CIP'!E53-'Financials from CIP'!D53+'Financials from CIP'!E25)/1000 -> 2.2620483 | H36: =H48*H13 -> 2.6089416 | I36: =I48*I13 -> 3.0090323 | J36: =J48*J13 -> 3.3802074 | K36: =K48*K13 -> 3.695762 | L36: =L48*L13 -> 3.929902
C39: Key Performance Metrics & Drivers
C41: Sales Growth (%) | G41: =G13/F13-1 -> 0.15335363 | H41: =G41 -> 0.15335363 | I41: =H41 -> 0.15335363 | J41: =I41-3% -> 0.12335363 | K41: =J41-3% -> 0.093353635 | L41: =K41-3% -> 0.063353635
C43: COGS / Sales (%) | F43: =F14/F13 -> 0.65629409 | G43: =G14/G13 -> 0.6800127 | H43: =AVERAGE(F43:G43) -> 0.66815339 | I43: =H43 -> 0.66815339 | J43: =I43 -> 0.66815339 | K43: =J43 -> 0.66815339 | L43: =K43 -> 0.66815339
C44: SG&A / Sales (%) | F44: =F17/F13 -> 0.18048486 | G44: =G17/G13 -> 0.17035654 | H44: =AVERAGE(F44:G44) -> 0.1754207 | I44: =H44 -> 0.1754207 | J44: =I44 -> 0.1754207 | K44: =J44 -> 0.1754207 | L44: =K44 -> 0.1754207
C46: Tax Rate (%) | F46: =F32/F31 -> 0.35320563 | G46: =G32/G31 -> 0.26977636 | H46: =AVERAGE(F46:G46) -> 0.31149099 | I46: =H46 -> 0.31149099 | J46: =I46 -> 0.31149099 | K46: =J46 -> 0.31149099 | L46: =K46 -> 0.31149099
C48: Capex / Sales (%) | G48: =G36/G13 -> 0.024963561 | H48: =G48 -> 0.024963561 | I48: =H48 -> 0.024963561 | J48: =I48 -> 0.024963561 | K48: =J48 -> 0.024963561 | L48: =K48 -> 0.024963561
B53: x | C53: Balance Sheet
F55: MRY | G55: MRY | H55: Fiscal Years Ending December 31,
C56: ($ in millions) | F56: =EOMONTH(G56,-12) -> 45291 | G56: =G$11 -> 45657 | H56: =H$11 -> 46022 | I56: =I$11 -> 46387 | J56: =J$11 -> 46752 | K56: =K$11 -> 47118 | L56: =L$11 -> 47483
C58: Assets
C60: Cash and Equivalents | F60: ='Financials from CIP'!D46/1000 -> 7.105652 | G60: ='Financials from CIP'!E46/1000 -> 2.957992 | H60: =G60+H119 -> 13.005932 | I60: =H60+I119 -> 22.51973 | J60: =I60+J119 -> 33.545552 | K60: =J60+K119 -> 46.071929 | L60: =K60+L119 -> 59.993804 | M60: Cash will move based on the Net Income you made and how your business ran (Operating Activities), the cash you invested (Investing Activities) and the cash you had come in or out from Financing (Financing Activites, which we will do in a later step). The Cash balance on this line is the Cash resulting at the END of each period. So it is equal to the Cash from last period + the change in cash this period. As such, Cash in 2025 is equal to Cash Balance from last year (G60) plus the change in cash this year (H119).
C61: Accounts Receivable, Net | F61: =SUM('Financials from CIP'!D47:D48)/1000 -> 16.781419 | G61: =SUM('Financials from CIP'!E47:E48)/1000 -> 22.284722 | H61: =H130 -> 24.012611 | I61: =I130 -> 27.695032 | J61: =J130 -> 31.111315 | K61: =K130 -> 34.015669 | L61: =L130 -> 36.170685
C62: Inventory | F62: ='Financials from CIP'!D49/1000 -> 0.804901 | G62: ='Financials from CIP'!E49/1000 -> 1.161057 | H62: =H131 -> 1.2029011 | I62: =I131 -> 1.3873704 | J62: =J131 -> 1.5585076 | K62: =K131 -> 1.7039999 | L62: =L131 -> 1.8119545
C63: Prepaids and Other Current Assets | F63: ='Financials from CIP'!D50/1000 -> 0.269784 | G63: ='Financials from CIP'!E50/1000 -> 0.344919 | H63: =H132 -> 0.37922157 | I63: =I132 -> 0.43737657 | J63: =J132 -> 0.49132856 | K63: =K132 -> 0.53719587 | L63: =L132 -> 0.57122918
C64: Total Current Assets | F64: =SUM(F60:F63) -> 24.961756 | G64: =SUM(G60:G63) -> 26.74869 | H64: =SUM(H60:H63) -> 38.600666 | I64: =SUM(I60:I63) -> 52.039509 | J64: =SUM(J60:J63) -> 66.706703 | K64: =SUM(K60:K63) -> 82.328794 | L64: =SUM(L60:L63) -> 98.547673
C65: PP&E, Gross | H65: =G67+H36 -> 58.293926 | I65: =H65+I36 -> 61.302958 | J65: =I65+J36 -> 64.683165 | K65: =J65+K36 -> 68.378927 | L65: =K65+L36 -> 72.308829
C66: ( – ) Accumulated Depreciation | H66: =G66-H20 -> -5.8293926 | I66: =H66-I20 -> -11.959688 | J66: =I66-J20 -> -18.428005 | K66: =J66-K20 -> -25.265898 | L66: =K66-L20 -> -32.496781
C67: PP&E, Net | F67: ='Financials from CIP'!D53/1000 -> 54.5847 | G67: ='Financials from CIP'!E53/1000 -> 55.684984 | H67: =SUM(H65:H66) -> 52.464533 | I67: =SUM(I65:I66) -> 49.34327 | J67: =SUM(J65:J66) -> 46.25516 | K67: =SUM(K65:K66) -> 43.11303 | L67: =SUM(L65:L66) -> 39.812049
C68: Goodwill | F68: 0 | G68: 0 | H68: 0 | I68: 0 | J68: 0 | K68: 0 | L68: 0
C69: Intangible and Long-Term Other Assets | F69: ='Financials from CIP'!D54/1000 -> 4.378482 | G69: ='Financials from CIP'!E54/1000 -> 4.50437 | H69: =G69-H21 -> 4.266418 | I69: =H69-I21 -> 4.028466 | J69: =I69-J21 -> 3.790514 | K69: =J69-K21 -> 3.552562 | L69: =K69-L21 -> 3.31461
C70: Total Assets | F70: =SUM(F64,F67:F69) -> 83.924938 | G70: =SUM(G64,G67:G69) -> 86.938044 | H70: =SUM(H64,H67:H69) -> 95.331617 | I70: =SUM(I64,I67:I69) -> 105.41124 | J70: =SUM(J64,J67:J69) -> 116.75238 | K70: =SUM(K64,K67:K69) -> 128.99439 | L70: =SUM(L64,L67:L69) -> 141.67433
C72: Liabilities & Shareholders' Equity
C74: Accounts Payable | F74: ='Financials from CIP'!D58/1000 -> 2.805817 | G74: ='Financials from CIP'!E58/1000 -> 2.36071 | H74: =H135 -> 3.2375303 | I74: =I135 -> 3.7340173 | J74: =J135 -> 4.1946219 | K74: =K135 -> 4.5862051 | L74: =L135 -> 4.8767579
C75: Wages Payable | F75: ='Financials from CIP'!D59/1000 -> 2.383933 | G75: ='Financials from CIP'!E59/1000 -> 2.788038 | H75: =H136 -> 3.1966854 | I75: =I136 -> 3.6869088 | J75: =J136 -> 4.1417024 | K75: =K136 -> 4.5283453 | L75: =L136 -> 4.8152325
C76: Accrued Expenses & Other | F76: ='Financials from CIP'!D60/1000 -> 2.057908 | G76: ='Financials from CIP'!E60/1000 -> 3.202031 | H76: =H137 -> 3.2317637 | I76: =I137 -> 3.7273664 | J76: =J137 -> 4.1871506 | K76: =K137 -> 4.5780363 | L76: =L137 -> 4.8680716
C77: Total Current Liabilities | F77: =SUM(F74:F76) -> 7.247658 | G77: =SUM(G74:G76) -> 8.350779 | H77: =SUM(H74:H76) -> 9.6659794 | I77: =SUM(I74:I76) -> 11.148292 | J77: =SUM(J74:J76) -> 12.523475 | K77: =SUM(K74:K76) -> 13.692587 | L77: =SUM(L74:L76) -> 14.560062
C78: Revolver | F78: ='Financials from CIP'!D63/1000 -> 0.645883 | G78: ='Financials from CIP'!E63/1000 -> 1.2893
C79: Term Loan A | F79: ='Financials from CIP'!D64/1000 -> 18.943222 | G79: ='Financials from CIP'!E64/1000 -> 12.001451
C80: Subordinated - Note 1 | F80: ='Financials from CIP'!D65/1000 -> 0.545333 | G80: ='Financials from CIP'!E65/1000 -> 0.085338
C81: Subordinated - Note 2 | F81: ='Financials from CIP'!D66/1000 -> 0.092448 | G81: ='Financials from CIP'!E66/1000 -> 0.012667
C82: Total Debt | F82: =SUM(F78:F81) -> 20.226886 | G82: =SUM(G78:G81) -> 13.388756 | H82: =SUM(H78:H81) -> 0 | I82: =SUM(I78:I81) -> 0 | J82: =SUM(J78:J81) -> 0 | K82: =SUM(K78:K81) -> 0 | L82: =SUM(L78:L81) -> 0
C83: Other Long-term Liabilities | F83: ='Financials from CIP'!D67/1000 -> 0.417874 | G83: ='Financials from CIP'!E67/1000 -> 0.429888 | H83: =G83 -> 0.429888 | I83: =H83 -> 0.429888 | J83: =I83 -> 0.429888 | K83: =J83 -> 0.429888 | L83: =K83 -> 0.429888
C84: Total liabilities | F84: =SUM(F77,F82:F83) -> 27.892418 | G84: =SUM(G77,G82:G83) -> 22.169423 | H84: =SUM(H77,H82:H83) -> 10.095867 | I84: =SUM(I77,I82:I83) -> 11.57818 | J84: =SUM(J77,J82:J83) -> 12.953363 | K84: =SUM(K77,K82:K83) -> 14.122475 | L84: =SUM(L77,L82:L83) -> 14.98995
C85: Common Stock | F85: ='Financials from CIP'!D71/1000 -> 7.7836338 | G85: ='Financials from CIP'!E71/1000 -> 8.9161157 | H85: =G85 -> 8.9161157 | I85: =H85 -> 8.9161157 | J85: =I85 -> 8.9161157 | K85: =J85 -> 8.9161157 | L85: =K85 -> 8.9161157
C86: Retained Earnings | F86: ='Financials from CIP'!D72/1000 -> 48.248887 | G86: ='Financials from CIP'!E72/1000 -> 55.852505 | H86: =G86+H33 -> 62.930877 | I86: =H86+I33 -> 71.528192 | J86: =I86+J33 -> 81.494142 | K86: =J86+K33 -> 92.567038 | L86: =K86+L33 -> 104.37951
C87: Total Liabilities & Shareholders' Equity | F87: =SUM(F84:F86) -> 83.924939 | G87: =SUM(G84:G86) -> 86.938043 | H87: =SUM(H84:H86) -> 81.94286 | I87: =SUM(I84:I86) -> 92.022488 | J87: =SUM(J84:J86) -> 103.36362 | K87: =SUM(K84:K86) -> 115.60563 | L87: =SUM(L84:L86) -> 128.28558
C89: Check (should be zero) | F89: =F87-F70 -> 8.2790072e-07 | G89: =G87-G70 -> -5.041918e-07 | H89: =H87-H70 -> -13.388757 | I89: =I87-I70 -> -13.388757 | J89: =J87-J70 -> -13.388757 | K89: =K87-K70 -> -13.388757 | L89: =L87-L70 -> -13.388757
B93: x | C93: Cash Flow Statement
F95: MRY | G95: MRY | H95: Fiscal Years Ending December 31,
C96: ($ in millions) | F96: =F$11 -> 45291 | G96: =G$11 -> 45657 | H96: =H$11 -> 46022 | I96: =I$11 -> 46387 | J96: =J$11 -> 46752 | K96: =K$11 -> 47118 | L96: =L$11 -> 47483
C98: Operating Activities | M98: Now it is time to tie everything together with cash flow. Let's map the change in Cash (WHERE did Cash go) using WHAT happened in the Income Statement and HOW it affected the business on the Balance Sheet
C100: Net Income | H100: =H33 -> 7.0783725 | I100: =I33 -> 8.5973148 | J100: =J33 -> 9.9659504 | K100: =K33 -> 11.072896 | L100: =L33 -> 11.812472 | M100: Start with Net Income - this is the result of ALL Revenue and Expenses (including ones that do not affect cash). Starting here, we will next add the non-cash expenses from the P&L. Link this to the P&L as a POSITIVE to INCREASE the effect on cash - Net income removed it, we add it back to CASH flow
C101: Depreciation | H101: =H20 -> 5.8293926 | I101: =I20 -> 6.1302958 | J101: =J20 -> 6.4683165 | K101: =K20 -> 6.8378927 | L101: =L20 -> 7.2308829 | M101: Depreciation is an expense that reflects the decrease in value of long-term, physical (tangible) assets. It does not affect Cash - it is a non-Cash expense that is meant to reflect the "wear and tear" of Long-term Assets that you are using to produce Revenue over time. However, Deprecistion does affect the value of Long-term Assets directly - it is a reduction to our Assets for the loss in value of the Assets related to "wear and tear" and aging. So because we are "losing" the value of these Assets because we are using them, and because they are getting older - and presumably "less useful to us", it is a reduction in our ownership value of those Assets too. That reduction in ownership value shows as an Expense and, eventually, to Equity through Retained Earnings. As such, because it is a non-cash expense, we add in back to Net Income for the purposes of the CASH Flow statement. Link this to the P&L as a POSITIVE to INCREASE the effect on cash - Net Income is already lower because Depreciation Expense is in it... so we add it back to CASH Flow to REMOVE the effect that Depreciation has on Net Income to show actual Cash Flow
C102: Amortization of Intangibles | H102: =H21 -> 0.237952 | I102: =I21 -> 0.237952 | J102: =J21 -> 0.237952 | K102: =K21 -> 0.237952 | L102: =L21 -> 0.237952 | M102: Amortization is an expense that reflects the decrease in value of long-term, non-physical (intangible) assets. It also does not affect Cash - it is a non-Cash expense that is meant to reflect the "use" of Long-term Intangible Assets that you are using to produce Revenue over time. However, Amortization does affect the value of Long-term Intangible Assets directly - it is a reduction to our Assets for the loss in value of the Intangible Assets related to use and aging. So because we are "losing" the value of these Assets because we are using them, and because they are getting older - and presumably "less useful to us", it is a reduction in our ownership value of those Intangible Assets too. That reduction in ownership value shows as an Expense and, eventually, to Equity through Retained Earnings. As such, because it is a non-cash expense, we add in back to Net Income for the purposes of the CASH Flow statement. Link this to the P&L as a POSITIVE to INCREASE the effect on cash - Net Income is already lower because Amortization Expense is in it... so we add it back to CASH Flow to REMOVE the effect that Amortization has on Net Income to show actual Cash Flow
C103: Net Income + Non-Cash Expense Adjustments | H103: =SUM(H100:H102) -> 13.145717 | I103: =SUM(I100:I102) -> 14.965563 | J103: =SUM(J100:J102) -> 16.672219 | K103: =SUM(K100:K102) -> 18.14874 | L103: =SUM(L100:L102) -> 19.281307 | M103: These are the total adjustments added to Net Income to get a "cash basis" of Net Income. However, these adjustments are only the first step in calculating our changes in Cash related to Operating activities. HOW fast the business collected money, paid money, etc also needs to be considered for the change in CASH. As such, we look at the change in Current Assets and Current Liabilities that are not Debt to see the effect they have on cash as well
C104: (Increase) / Decrease in Working Capital | H104: =-(H141) -> -0.4888351 | I104: =-(I141) -> -2.4427323 | J104: =-(J141) -> -2.2661896 | K104: =-(K141) -> -1.9266021 | L104: =-(L141) -> -1.429529 | M104: Working Capital can be tricky to think through and counter intuitive but think of it this way: If Working Capital goes up, it means that we have an INCREASE in Assets compared with the change in Liabilities. This means that Assets either went up or Liabilities went down period over period. If Assets go up, it means that we either did not collect money, or used money, for our Assets to increase. Althernatively, if Liabilities went down we USED money to pay off some money we owe. Either way, an INCREASE in Working Capital is a DECREASE in cash - we have less cash in our pocket. We link to the Working Capital section, below
C105: Cash flow from Operating Activities | H105: =+SUM(H103:H104) -> 12.656882 | I105: =+SUM(I103:I104) -> 12.52283 | J105: =+SUM(J103:J104) -> 14.406029 | K105: =+SUM(K103:K104) -> 16.222138 | L105: =+SUM(L103:L104) -> 17.851778
C107: Investing Activities
C109: Cash flow from Investment Activities - CapEx | H109: =-H36 -> -2.6089416 | I109: =-I36 -> -3.0090323 | J109: =-J36 -> -3.3802074 | K109: =-K36 -> -3.695762 | L109: =-L36 -> -3.929902 | M109: Cash flow from investing activities is the cash paid for Long-term Assets (physical and non-physical. Is is a USE of Cash when Assets go up (we bought something) so it DECREASES the Cash balance. If our value went down, it would most likely meant we sold something (net of Depreciation). We link it to CapEx and remove it to DECREASE the cash balance, here
C111: Financing Activities
C113: Revolver
C114: =+C79 -> Term Loan A
C115: =+C80 -> Subordinated - Note 1
C116: =+C81 -> Subordinated - Note 2
C117: Cash flow from Financing Activities | H117: =SUM(H113:H116) -> 0 | I117: =SUM(I113:I116) -> 0 | J117: =SUM(J113:J116) -> 0 | K117: =SUM(K113:K116) -> 0 | L117: =SUM(L113:L116) -> 0
C119: Change in Cash | H119: =H117+H109+H105 -> 10.04794 | I119: =I117+I109+I105 -> 9.513798 | J119: =J117+J109+J105 -> 11.025822 | K119: =K117+K109+K105 -> 12.526376 | L119: =L117+L109+L105 -> 13.921876 | M119: Sum up the Cash Effects from the Operating Activites, Investing Activities and Financing Activities sections
B123: x | C123: Working Capital
F125: MRY | G125: MRY | H125: Fiscal Years Ending December 31,
C126: ($ in millions) | F126: =F$11 -> 45291 | G126: =G$11 -> 45657 | H126: =H$11 -> 46022 | I126: =I$11 -> 46387 | J126: =J$11 -> 46752 | K126: =K$11 -> 47118 | L126: =L$11 -> 47483
C128: Net Working Capital
C130: =C61 -> Accounts Receivable, Net | F130: =F61 -> 16.781419 | G130: =G61 -> 22.284722 | H130: =(H145/365)*H149 -> 24.012611 | I130: =(I145/365)*I149 -> 27.695032 | J130: =(J145/365)*J149 -> 31.111315 | K130: =(K145/365)*K149 -> 34.015669 | L130: =(L145/365)*L149 -> 36.170685
C131: =C62 -> Inventory | F131: =F62 -> 0.804901 | G131: =G62 -> 1.161057 | H131: =(H146/365)*H150 -> 1.2029011 | I131: =(I146/365)*I150 -> 1.3873704 | J131: =(J146/365)*J150 -> 1.5585076 | K131: =(K146/365)*K150 -> 1.7039999 | L131: =(L146/365)*L150 -> 1.8119545
C132: =C63 -> Prepaids and Other Current Assets | F132: =F63 -> 0.269784 | G132: =G63 -> 0.344919 | H132: =H151*H147 -> 0.37922157 | I132: =I151*I147 -> 0.43737657 | J132: =J151*J147 -> 0.49132856 | K132: =K151*K147 -> 0.53719587 | L132: =L151*L147 -> 0.57122918
C133: Non-Cash Current Assets | F133: =SUM(F130:F132) -> 17.856104 | G133: =SUM(G130:G132) -> 23.790698 | H133: =SUM(H130:H132) -> 25.594734 | I133: =SUM(I130:I132) -> 29.519779 | J133: =SUM(J130:J132) -> 33.161151 | K133: =SUM(K130:K132) -> 36.256865 | L133: =SUM(L130:L132) -> 38.553869
C135: =C74 -> Accounts Payable | F135: =F74 -> 2.805817 | G135: =G74 -> 2.36071 | H135: =(H146/365)*H153 -> 3.2375303 | I135: =(I146/365)*I153 -> 3.7340173 | J135: =(J146/365)*J153 -> 4.1946219 | K135: =(K146/365)*K153 -> 4.5862051 | L135: =(L146/365)*L153 -> 4.8767579
C136: =C75 -> Wages Payable | F136: =F75 -> 2.383933 | G136: =G75 -> 2.788038 | H136: =H154*H147 -> 3.1966854 | I136: =I154*I147 -> 3.6869088 | J136: =J154*J147 -> 4.1417024 | K136: =K154*K147 -> 4.5283453 | L136: =L154*L147 -> 4.8152325
C137: =C76 -> Accrued Expenses & Other | F137: =F76 -> 2.057908 | G137: =G76 -> 3.202031 | H137: =H155*H147 -> 3.2317637 | I137: =I155*I147 -> 3.7273664 | J137: =J155*J147 -> 4.1871506 | K137: =K155*K147 -> 4.5780363 | L137: =L155*L147 -> 4.8680716
C138: Non-Debt Current Liabilities | F138: =SUM(F135:F137) -> 7.247658 | G138: =SUM(G135:G137) -> 8.350779 | H138: =SUM(H135:H137) -> 9.6659794 | I138: =SUM(I135:I137) -> 11.148292 | J138: =SUM(J135:J137) -> 12.523475 | K138: =SUM(K135:K137) -> 13.692587 | L138: =SUM(L135:L137) -> 14.560062
...

Sheet Step 6
C2: Athena Modeling Exercise
C3: Step 6 - Debt - Getting Started
J5: Black font = Calculation
C6: YELLOWS ARE FILLS | F6: SKIP FOR NOW | J6: Blue font = Hardcoded Input/Assumption
J7: Green font = Pulled from another Sheet
B8: x | C8: Income Statement
F10: MRY | G10: MRY | H10: Fiscal Years Ending December 31,
C11: ($ in millions) | F11: =EOMONTH(G11,-12) -> 45291 | G11: 45657 | H11: =EOMONTH(G11,12) -> 46022 | I11: =EOMONTH(H11,12) -> 46387 | J11: =EOMONTH(I11,12) -> 46752 | K11: =EOMONTH(J11,12) -> 47118 | L11: =EOMONTH(K11,12) -> 47483
C13: Total Revenue | F13: ='Financials from CIP'!D13/1000 -> 78.565676 | G13: ='Financials from CIP'!E13/1000 -> 90.614008 | H13: =(1+H41)*G13 -> 104.51 | I13: =(1+I41)*H13 -> 120.53698 | J13: =(1+J41)*I13 -> 135.40566 | K13: =(1+K41)*J13 -> 148.04627 | L13: =(1+L41)*K13 -> 157.42554
C14: COGS | F14: =SUM('Financials from CIP'!D15:D17)/1000 -> 51.562189 | G14: =SUM('Financials from CIP'!E15:E17)/1000 -> 61.618676 | H14: =H43*H13 -> 69.828708 | I14: =I43*I13 -> 80.537195 | J14: =J43*J13 -> 90.47175 | K14: =K43*K13 -> 98.917617 | L14: =L43*L13 -> 105.18441
C15: Gross Profit | F15: =F13-F14 -> 27.003487 | G15: =G13-G14 -> 28.995332 | H15: =H13-H14 -> 34.681287 | I15: =I13-I14 -> 39.999789 | J15: =J13-J14 -> 44.933908 | K15: =K13-K14 -> 49.128652 | L15: =L13-L14 -> 52.24113
C16: Gross Margin (%) | F16: =IFERROR(F15/F$13,"N/M") -> 0.34370591 | G16: =IFERROR(G15/G$13,"N/M") -> 0.3199873 | H16: =IFERROR(H15/H$13,"N/M") -> 0.33184661 | I16: =IFERROR(I15/I$13,"N/M") -> 0.33184661 | J16: =IFERROR(J15/J$13,"N/M") -> 0.33184661 | K16: =IFERROR(K15/K$13,"N/M") -> 0.33184661 | L16: =IFERROR(L15/L$13,"N/M") -> 0.33184661
C17: SG&A | F17: =SUM('Financials from CIP'!D23:D24,'Financials from CIP'!D28)/1000 -> 14.179915 | G17: =SUM('Financials from CIP'!E23:E24,'Financials from CIP'!E28)/1000 -> 15.436689 | H17: =H44*H13 -> 18.333217 | I17: =I44*I13 -> 21.144682 | J17: =J44*J13 -> 23.752955 | K17: =K44*K13 -> 25.97038 | L17: =L44*L13 -> 27.615698
C18: EBITDA | F18: =F15-F17 -> 12.823572 | G18: =G15-G17 -> 13.558643 | H18: =H15-H17 -> 16.348071 | I18: =I15-I17 -> 18.855107 | J18: =J15-J17 -> 21.180953 | K18: =K15-K17 -> 23.158272 | L18: =L15-L17 -> 24.625432
C19: EBITDA Margin (%) | F19: =IFERROR(F18/F$13,"N/M") -> 0.16322105 | G19: =IFERROR(G18/G$13,"N/M") -> 0.14963076 | H19: =IFERROR(H18/H$13,"N/M") -> 0.15642591 | I19: =IFERROR(I18/I$13,"N/M") -> 0.15642591 | J19: =IFERROR(J18/J$13,"N/M") -> 0.15642591 | K19: =IFERROR(K18/K$13,"N/M") -> 0.15642591 | L19: =IFERROR(L18/L$13,"N/M") -> 0.15642591
C20: Depreciation | F20: ='Financials from CIP'!D25/1000 -> 1.1801621 | G20: ='Financials from CIP'!E25/1000 -> 1.1617643 | H20: =H194 -> 5.8293926 | I20: =I194 -> 6.1302958 | J20: =J194 -> 6.4683165 | K20: =K194 -> 6.8378927 | L20: =L194 -> 7.2308829
C21: Amortization | F21: ='Financials from CIP'!D26/1000 -> 0.208264 | G21: ='Financials from CIP'!E26/1000 -> 0.237952 | H21: =MIN(G21,G69) -> 0.237952 | I21: =MIN(H21,H69) -> 0.237952 | J21: =MIN(I21,I69) -> 0.237952 | K21: =MIN(J21,J69) -> 0.237952 | L21: =MIN(K21,K69) -> 0.237952
C22: EBIT | F22: =F18-SUM(F20:F21) -> 11.435146 | G22: =G18-SUM(G20:G21) -> 12.158927 | H22: =H18-SUM(H20:H21) -> 10.280726 | I22: =I18-SUM(I20:I21) -> 12.486859 | J22: =J18-SUM(J20:J21) -> 14.474684 | K22: =K18-SUM(K20:K21) -> 16.082427 | L22: =L18-SUM(L20:L21) -> 17.156597
C23: Interest (Income) / Expense
C24: Revolver – Interest
C25: Revolver – Undrawn Commitment Fee
C26: =+C79 -> Term Loan A
C27: =+C80 -> Subordinated - Note 1
C28: =+C81 -> Subordinated - Note 2
C29: Interest (Income) / Expense | F29: ='Financials from CIP'!D27/1000 -> 2.224955 | G29: ='Financials from CIP'!E27/1000 -> 1.472763 | H29: =SUM(H24:H28) -> 0 | I29: =SUM(I24:I28) -> 0 | J29: =SUM(J24:J28) -> 0 | K29: =SUM(K24:K28) -> 0 | L29: =SUM(L24:L28) -> 0
C30: Other (Income) / Expense | F30: ='Financials from CIP'!D32/1000 -> 0.147371 | G30: ='Financials from CIP'!E32/1000 -> 0.273439 | H30: 0 | I30: 0 | J30: 0 | K30: 0 | L30: 0
C31: Income Before Taxes | F31: =F22-F29-F30 -> 9.0628199 | G31: =G22-G29-G30 -> 10.412725 | H31: =H22-H29-H30 -> 10.280726 | I31: =I22-I29-I30 -> 12.486859 | J31: =J22-J29-J30 -> 14.474684 | K31: =K22-K29-K30 -> 16.082427 | L31: =L22-L29-L30 -> 17.156597
C32: Provision for Tax | F32: ='Financials from CIP'!D29/1000 -> 3.201039 | G32: ='Financials from CIP'!E29/1000 -> 2.809107 | H32: =H46*H31 -> 3.2023536 | I32: =I46*I31 -> 3.8895441 | J32: =J46*J31 -> 4.5087338 | K32: =K46*K31 -> 5.0095311 | L32: =L46*L31 -> 5.3441256
C33: Net Income | F33: =F31-F32 -> 5.8617809 | G33: =G31-G32 -> 7.6036178 | H33: =H31-H32 -> 7.0783725 | I33: =I31-I32 -> 8.5973148 | J33: =J31-J32 -> 9.9659504 | K33: =K31-K32 -> 11.072896 | L33: =L31-L32 -> 11.812472
C34: Profit Margin (%) | F34: =IFERROR(F33/F$13,"N/M") -> 0.074609947 | G34: =IFERROR(G33/G$13,"N/M") -> 0.083912167 | H34: =IFERROR(H33/H$13,"N/M") -> 0.067729144 | I34: =IFERROR(I33/I$13,"N/M") -> 0.07132512 | J34: =IFERROR(J33/J$13,"N/M") -> 0.073600694 | K34: =IFERROR(K33/K$13,"N/M") -> 0.074793481 | L34: =IFERROR(L33/L$13,"N/M") -> 0.075035296
C36: Capital Expenditures | G36: =('Financials from CIP'!E53-'Financials from CIP'!D53+'Financials from CIP'!E25)/1000 -> 2.2620483 | H36: =H48*H13 -> 2.6089416 | I36: =I48*I13 -> 3.0090323 | J36: =J48*J13 -> 3.3802074 | K36: =K48*K13 -> 3.695762 | L36: =L48*L13 -> 3.929902
C39: Key Performance Metrics & Drivers
C41: Sales Growth (%) | G41: =G13/F13-1 -> 0.15335363 | H41: =G41 -> 0.15335363 | I41: =H41 -> 0.15335363 | J41: =I41-3% -> 0.12335363 | K41: =J41-3% -> 0.093353635 | L41: =K41-3% -> 0.063353635
C43: COGS / Sales (%) | F43: =F14/F13 -> 0.65629409 | G43: =G14/G13 -> 0.6800127 | H43: =AVERAGE(F43:G43) -> 0.66815339 | I43: =H43 -> 0.66815339 | J43: =I43 -> 0.66815339 | K43: =J43 -> 0.66815339 | L43: =K43 -> 0.66815339
C44: SG&A / Sales (%) | F44: =F17/F13 -> 0.18048486 | G44: =G17/G13 -> 0.17035654 | H44: =AVERAGE(F44:G44) -> 0.1754207 | I44: =H44 -> 0.1754207 | J44: =I44 -> 0.1754207 | K44: =J44 -> 0.1754207 | L44: =K44 -> 0.1754207
C46: Tax Rate (%) | F46: =F32/F31 -> 0.35320563 | G46: =G32/G31 -> 0.26977636 | H46: =AVERAGE(F46:G46) -> 0.31149099 | I46: =H46 -> 0.31149099 | J46: =I46 -> 0.31149099 | K46: =J46 -> 0.31149099 | L46: =K46 -> 0.31149099
C48: Capex / Sales (%) | G48: =G36/G13 -> 0.024963561 | H48: =G48 -> 0.024963561 | I48: =H48 -> 0.024963561 | J48: =I48 -> 0.024963561 | K48: =J48 -> 0.024963561 | L48: =K48 -> 0.024963561
B53: x | C53: Balance Sheet
F55: MRY | G55: MRY | H55: Fiscal Years Ending December 31,
C56: ($ in millions) | F56: =EOMONTH(G56,-12) -> 45291 | G56: =G$11 -> 45657 | H56: =H$11 -> 46022 | I56: =I$11 -> 46387 | J56: =J$11 -> 46752 | K56: =K$11 -> 47118 | L56: =L$11 -> 47483
C58: Assets
C60: Cash and Equivalents | F60: ='Financials from CIP'!D46/1000 -> 7.105652 | G60: ='Financials from CIP'!E46/1000 -> 2.957992 | H60: =G60+H119 -> 13.005932 | I60: =H60+I119 -> 22.51973 | J60: =I60+J119 -> 33.545552 | K60: =J60+K119 -> 46.071929 | L60: =K60+L119 -> 59.993804
C61: Accounts Receivable, Net | F61: =SUM('Financials from CIP'!D47:D48)/1000 -> 16.781419 | G61: =SUM('Financials from CIP'!E47:E48)/1000 -> 22.284722 | H61: =H130 -> 24.012611 | I61: =I130 -> 27.695032 | J61: =J130 -> 31.111315 | K61: =K130 -> 34.015669 | L61: =L130 -> 36.170685
C62: Inventory | F62: ='Financials from CIP'!D49/1000 -> 0.804901 | G62: ='Financials from CIP'!E49/1000 -> 1.161057 | H62: =H131 -> 1.2029011 | I62: =I131 -> 1.3873704 | J62: =J131 -> 1.5585076 | K62: =K131 -> 1.7039999 | L62: =L131 -> 1.8119545
C63: Prepaids and Other Current Assets | F63: ='Financials from CIP'!D50/1000 -> 0.269784 | G63: ='Financials from CIP'!E50/1000 -> 0.344919 | H63: =H132 -> 0.37922157 | I63: =I132 -> 0.43737657 | J63: =J132 -> 0.49132856 | K63: =K132 -> 0.53719587 | L63: =L132 -> 0.57122918
C64: Total Current Assets | F64: =SUM(F60:F63) -> 24.961756 | G64: =SUM(G60:G63) -> 26.74869 | H64: =SUM(H60:H63) -> 38.600666 | I64: =SUM(I60:I63) -> 52.039509 | J64: =SUM(J60:J63) -> 66.706703 | K64: =SUM(K60:K63) -> 82.328794 | L64: =SUM(L60:L63) -> 98.547673
C65: PP&E, Gross | H65: =G67+H36 -> 58.293926 | I65: =H65+I36 -> 61.302958 | J65: =I65+J36 -> 64.683165 | K65: =J65+K36 -> 68.378927 | L65: =K65+L36 -> 72.308829
C66: ( – ) Accumulated Depreciation | H66: =G66-H20 -> -5.8293926 | I66: =H66-I20 -> -11.959688 | J66: =I66-J20 -> -18.428005 | K66: =J66-K20 -> -25.265898 | L66: =K66-L20 -> -32.496781
C67: PP&E, Net | F67: ='Financials from CIP'!D53/1000 -> 54.5847 | G67: ='Financials from CIP'!E53/1000 -> 55.684984 | H67: =SUM(H65:H66) -> 52.464533 | I67: =SUM(I65:I66) -> 49.34327 | J67: =SUM(J65:J66) -> 46.25516 | K67: =SUM(K65:K66) -> 43.11303 | L67: =SUM(L65:L66) -> 39.812049
C68: Goodwill | F68: 0 | G68: 0 | H68: 0 | I68: 0 | J68: 0 | K68: 0 | L68: 0
C69: Intangible and Long-Term Other Assets | F69: ='Financials from CIP'!D54/1000 -> 4.378482 | G69: ='Financials from CIP'!E54/1000 -> 4.50437 | H69: =G69-H21 -> 4.266418 | I69: =H69-I21 -> 4.028466 | J69: =I69-J21 -> 3.790514 | K69: =J69-K21 -> 3.552562 | L69: =K69-L21 -> 3.31461
C70: Total Assets | F70: =SUM(F64,F67:F69) -> 83.924938 | G70: =SUM(G64,G67:G69) -> 86.938044 | H70: =SUM(H64,H67:H69) -> 95.331617 | I70: =SUM(I64,I67:I69) -> 105.41124 | J70: =SUM(J64,J67:J69) -> 116.75238 | K70: =SUM(K64,K67:K69) -> 128.99439 | L70: =SUM(L64,L67:L69) -> 141.67433
C72: Liabilities & Shareholders' Equity
C74: Accounts Payable | F74: ='Financials from CIP'!D58/1000 -> 2.805817 | G74: ='Financials from CIP'!E58/1000 -> 2.36071 | H74: =H135 -> 3.2375303 | I74: =I135 -> 3.7340173 | J74: =J135 -> 4.1946219 | K74: =K135 -> 4.5862051 | L74: =L135 -> 4.8767579
C75: Wages Payable | F75: ='Financials from CIP'!D59/1000 -> 2.383933 | G75: ='Financials from CIP'!E59/1000 -> 2.788038 | H75: =H136 -> 3.1966854 | I75: =I136 -> 3.6869088 | J75: =J136 -> 4.1417024 | K75: =K136 -> 4.5283453 | L75: =L136 -> 4.8152325
C76: Accrued Expenses & Other | F76: ='Financials from CIP'!D60/1000 -> 2.057908 | G76: ='Financials from CIP'!E60/1000 -> 3.202031 | H76: =H137 -> 3.2317637 | I76: =I137 -> 3.7273664 | J76: =J137 -> 4.1871506 | K76: =K137 -> 4.5780363 | L76: =L137 -> 4.8680716
C77: Total Current Liabilities | F77: =SUM(F74:F76) -> 7.247658 | G77: =SUM(G74:G76) -> 8.350779 | H77: =SUM(H74:H76) -> 9.6659794 | I77: =SUM(I74:I76) -> 11.148292 | J77: =SUM(J74:J76) -> 12.523475 | K77: =SUM(K74:K76) -> 13.692587 | L77: =SUM(L74:L76) -> 14.560062
C78: Revolver | F78: ='Financials from CIP'!D63/1000 -> 0.645883 | G78: ='Financials from CIP'!E63/1000 -> 1.2893 | M78: We are calculating the ENDING balance of the debt in each period, below. Link these lines to the ending balance for each type of debt, respectively, below
C79: Term Loan A | F79: ='Financials from CIP'!D64/1000 -> 18.943222 | G79: ='Financials from CIP'!E64/1000 -> 12.001451 | M79: We are calculating the ENDING balance of the debt in each period, below. Link these lines to the ending balance for each type of debt, respectively, below
C80: Subordinated - Note 1 | F80: ='Financials from CIP'!D65/1000 -> 0.545333 | G80: ='Financials from CIP'!E65/1000 -> 0.085338 | M80: We are calculating the ENDING balance of the debt in each period, below. Link these lines to the ending balance for each type of debt, respectively, below
C81: Subordinated - Note 2 | F81: ='Financials from CIP'!D66/1000 -> 0.092448 | G81: ='Financials from CIP'!E66/1000 -> 0.012667 | M81: We are calculating the ENDING balance of the debt in each period, below. Link these lines to the ending balance for each type of debt, respectively, below
C82: Total Debt | F82: =SUM(F78:F81) -> 20.226886 | G82: =SUM(G78:G81) -> 13.388756 | H82: =SUM(H78:H81) -> 0 | I82: =SUM(I78:I81) -> 0 | J82: =SUM(J78:J81) -> 0 | K82: =SUM(K78:K81) -> 0 | L82: =SUM(L78:L81) -> 0
C83: Other Long-term Liabilities | F83: ='Financials from CIP'!D67/1000 -> 0.417874 | G83: ='Financials from CIP'!E67/1000 -> 0.429888 | H83: =G83 -> 0.429888 | I83: =H83 -> 0.429888 | J83: =I83 -> 0.429888 | K83: =J83 -> 0.429888 | L83: =K83 -> 0.429888
C84: Total liabilities | F84: =SUM(F77,F82:F83) -> 27.892418 | G84: =SUM(G77,G82:G83) -> 22.169423 | H84: =SUM(H77,H82:H83) -> 10.095867 | I84: =SUM(I77,I82:I83) -> 11.57818 | J84: =SUM(J77,J82:J83) -> 12.953363 | K84: =SUM(K77,K82:K83) -> 14.122475 | L84: =SUM(L77,L82:L83) -> 14.98995
C85: Common Stock | F85: ='Financials from CIP'!D71/1000 -> 7.7836338 | G85: ='Financials from CIP'!E71/1000 -> 8.9161157 | H85: =G85 -> 8.9161157 | I85: =H85 -> 8.9161157 | J85: =I85 -> 8.9161157 | K85: =J85 -> 8.9161157 | L85: =K85 -> 8.9161157
C86: Retained Earnings | F86: ='Financials from CIP'!D72/1000 -> 48.248887 | G86: ='Financials from CIP'!E72/1000 -> 55.852505 | H86: =G86+H33 -> 62.930877 | I86: =H86+I33 -> 71.528192 | J86: =I86+J33 -> 81.494142 | K86: =J86+K33 -> 92.567038 | L86: =K86+L33 -> 104.37951
C87: Total Liabilities & Shareholders' Equity | F87: =SUM(F84:F86) -> 83.924939 | G87: =SUM(G84:G86) -> 86.938043 | H87: =SUM(H84:H86) -> 81.94286 | I87: =SUM(I84:I86) -> 92.022488 | J87: =SUM(J84:J86) -> 103.36362 | K87: =SUM(K84:K86) -> 115.60563 | L87: =SUM(L84:L86) -> 128.28558
C89: Check (should be zero) | F89: =F87-F70 -> 8.2790072e-07 | G89: =G87-G70 -> -5.041918e-07 | H89: =H87-H70 -> -13.388757 | I89: =I87-I70 -> -13.388757 | J89: =J87-J70 -> -13.388757 | K89: =K87-K70 -> -13.388757 | L89: =L87-L70 -> -13.388757
B93: x | C93: Cash Flow Statement
F95: MRY | G95: MRY | H95: Fiscal Years Ending December 31,
C96: ($ in millions) | F96: =F$11 -> 45291 | G96: =G$11 -> 45657 | H96: =H$11 -> 46022 | I96: =I$11 -> 46387 | J96: =J$11 -> 46752 | K96: =K$11 -> 47118 | L96: =L$11 -> 47483
C98: Operating Activities
C100: Net Income | H100: =H33 -> 7.0783725 | I100: =I33 -> 8.5973148 | J100: =J33 -> 9.9659504 | K100: =K33 -> 11.072896 | L100: =L33 -> 11.812472
C101: Depreciation | H101: =H20 -> 5.8293926 | I101: =I20 -> 6.1302958 | J101: =J20 -> 6.4683165 | K101: =K20 -> 6.8378927 | L101: =L20 -> 7.2308829
C102: Amortization of Intangibles | H102: =H21 -> 0.237952 | I102: =I21 -> 0.237952 | J102: =J21 -> 0.237952 | K102: =K21 -> 0.237952 | L102: =L21 -> 0.237952
C103: Net Income + Non-Cash Expense Adjustments | H103: =SUM(H100:H102) -> 13.145717 | I103: =SUM(I100:I102) -> 14.965563 | J103: =SUM(J100:J102) -> 16.672219 | K103: =SUM(K100:K102) -> 18.14874 | L103: =SUM(L100:L102) -> 19.281307
C104: (Increase) / Decrease in Working Capital | H104: =-(H141) -> -0.4888351 | I104: =-(I141) -> -2.4427323 | J104: =-(J141) -> -2.2661896 | K104: =-(K141) -> -1.9266021 | L104: =-(L141) -> -1.429529
C105: Cash flow from Operating Activities | H105: =+SUM(H103:H104) -> 12.656882 | I105: =+SUM(I103:I104) -> 12.52283 | J105: =+SUM(J103:J104) -> 14.406029 | K105: =+SUM(K103:K104) -> 16.222138 | L105: =+SUM(L103:L104) -> 17.851778
C107: Investing Activities
C109: Cash flow from Investment Activities - CapEx | H109: =-H36 -> -2.6089416 | I109: =-I36 -> -3.0090323 | J109: =-J36 -> -3.3802074 | K109: =-K36 -> -3.695762 | L109: =-L36 -> -3.929902
C111: Financing Activities
C113: Revolver
C114: =+C79 -> Term Loan A
C115: =+C80 -> Subordinated - Note 1
C116: =+C81 -> Subordinated - Note 2
C117: Cash flow from Financing Activities | H117: =SUM(H113:H116) -> 0 | I117: =SUM(I113:I116) -> 0 | J117: =SUM(J113:J116) -> 0 | K117: =SUM(K113:K116) -> 0 | L117: =SUM(L113:L116) -> 0
C119: Change in Cash | H119: =H117+H109+H105 -> 10.04794 | I119: =I117+I109+I105 -> 9.513798 | J119: =J117+J109+J105 -> 11.025822 | K119: =K117+K109+K105 -> 12.526376 | L119: =L117+L109+L105 -> 13.921876
B123: x | C123: Working Capital
F125: MRY | G125: MRY | H125: Fiscal Years Ending December 31,
C126: ($ in millions) | F126: =F$11 -> 45291 | G126: =G$11 -> 45657 | H126: =H$11 -> 46022 | I126: =I$11 -> 46387 | J126: =J$11 -> 46752 | K126: =K$11 -> 47118 | L126: =L$11 -> 47483
C128: Net Working Capital
C130: =C61 -> Accounts Receivable, Net | F130: =F61 -> 16.781419 | G130: =G61 -> 22.284722 | H130: =(H145/365)*H149 -> 24.012611 | I130: =(I145/365)*I149 -> 27.695032 | J130: =(J145/365)*J149 -> 31.111315 | K130: =(K145/365)*K149 -> 34.015669 | L130: =(L145/365)*L149 -> 36.170685
C131: =C62 -> Inventory | F131: =F62 -> 0.804901 | G131: =G62 -> 1.161057 | H131: =(H146/365)*H150 -> 1.2029011 | I131: =(I146/365)*I150 -> 1.3873704 | J131: =(J146/365)*J150 -> 1.5585076 | K131: =(K146/365)*K150 -> 1.7039999 | L131: =(L146/365)*L150 -> 1.8119545
C132: =C63 -> Prepaids and Other Current Assets | F132: =F63 -> 0.269784 | G132: =G63 -> 0.344919 | H132: =H151*H147 -> 0.37922157 | I132: =I151*I147 -> 0.43737657 | J132: =J151*J147 -> 0.49132856 | K132: =K151*K147 -> 0.53719587 | L132: =L151*L147 -> 0.57122918
C133: Non-Cash Current Assets | F133: =SUM(F130:F132) -> 17.856104 | G133: =SUM(G130:G132) -> 23.790698 | H133: =SUM(H130:H132) -> 25.594734 | I133: =SUM(I130:I132) -> 29.519779 | J133: =SUM(J130:J132) -> 33.161151 | K133: =SUM(K130:K132) -> 36.256865 | L133: =SUM(L130:L132) -> 38.553869
C135: =C74 -> Accounts Payable | F135: =F74 -> 2.805817 | G135: =G74 -> 2.36071 | H135: =(H146/365)*H153 -> 3.2375303 | I135: =(I146/365)*I153 -> 3.7340173 | J135: =(J146/365)*J153 -> 4.1946219 | K135: =(K146/365)*K153 -> 4.5862051 | L135: =(L146/365)*L153 -> 4.8767579
C136: =C75 -> Wages Payable | F136: =F75 -> 2.383933 | G136: =G75 -> 2.788038 | H136: =H154*H147 -> 3.1966854 | I136: =I154*I147 -> 3.6869088 | J136: =J154*J147 -> 4.1417024 | K136: =K154*K147 -> 4.5283453 | L136: =L154*L147 -> 4.8152325
C137: =C76 -> Accrued Expenses & Other | F137: =F76 -> 2.057908 | G137: =G76 -> 3.202031 | H137: =H155*H147 -> 3.2317637 | I137: =I155*I147 -> 3.7273664 | J137: =J155*J147 -> 4.1871506 | K137: =K155*K147 -> 4.5780363 | L137: =L155*L147 -> 4.8680716
C138: Non-Debt Current Liabilities | F138: =SUM(F135:F137) -> 7.247658 | G138: =SUM(G135:G137) -> 8.350779 | H138: =SUM(H135:H137) -> 9.6659794 | I138: =SUM(I135:I137) -> 11.148292 | J138: =SUM(J135:J137) -> 12.523475 | K138: =SUM(K135:K137) -> 13.692587 | L138: =SUM(L135:L137) -> 14.560062
C139: Net Working Capital, without Cash | F139: =F133-F138 -> 10.608446 | G139: =G133-G138 -> 15.439919 | H139: =H133-H138 -> 15.928754 | I139: =I133-I138 -> 18.371486 | J139: =J133-J138 -> 20.637676 | K139: =K133-K138 -> 22.564278 | L139: =L133-L138 -> 23.993807
...

Sheet Step 6 Answer Key
C2: Athena Modeling Exercise
C3: Step 6 - Debt - Getting Started
J5: Black font = Calculation
C6: YELLOWS ARE FILLS | F6: SKIP FOR NOW | J6: Blue font = Hardcoded Input/Assumption
J7: Green font = Pulled from another Sheet
B8: x | C8: Income Statement
F10: MRY | G10: MRY | H10: Fiscal Years Ending December 31,
C11: ($ in millions) | F11: =EOMONTH(G11,-12) -> 45291 | G11: 45657 | H11: =EOMONTH(G11,12) -> 46022 | I11: =EOMONTH(H11,12) -> 46387 | J11: =EOMONTH(I11,12) -> 46752 | K11: =EOMONTH(J11,12) -> 47118 | L11: =EOMONTH(K11,12) -> 47483
C13: Total Revenue | F13: ='Financials from CIP'!D13/1000 -> 78.565676 | G13: ='Financials from CIP'!E13/1000 -> 90.614008 | H13: =(1+H41)*G13 -> 104.51 | I13: =(1+I41)*H13 -> 120.53698 | J13: =(1+J41)*I13 -> 135.40566 | K13: =(1+K41)*J13 -> 148.04627 | L13: =(1+L41)*K13 -> 157.42554
C14: COGS | F14: =SUM('Financials from CIP'!D15:D17)/1000 -> 51.562189 | G14: =SUM('Financials from CIP'!E15:E17)/1000 -> 61.618676 | H14: =H43*H13 -> 69.828708 | I14: =I43*I13 -> 80.537195 | J14: =J43*J13 -> 90.47175 | K14: =K43*K13 -> 98.917617 | L14: =L43*L13 -> 105.18441
C15: Gross Profit | F15: =F13-F14 -> 27.003487 | G15: =G13-G14 -> 28.995332 | H15: =H13-H14 -> 34.681287 | I15: =I13-I14 -> 39.999789 | J15: =J13-J14 -> 44.933908 | K15: =K13-K14 -> 49.128652 | L15: =L13-L14 -> 52.24113
C16: Gross Margin (%) | F16: =IFERROR(F15/F$13,"N/M") -> 0.34370591 | G16: =IFERROR(G15/G$13,"N/M") -> 0.3199873 | H16: =IFERROR(H15/H$13,"N/M") -> 0.33184661 | I16: =IFERROR(I15/I$13,"N/M") -> 0.33184661 | J16: =IFERROR(J15/J$13,"N/M") -> 0.33184661 | K16: =IFERROR(K15/K$13,"N/M") -> 0.33184661 | L16: =IFERROR(L15/L$13,"N/M") -> 0.33184661
C17: SG&A | F17: =SUM('Financials from CIP'!D23:D24,'Financials from CIP'!D28)/1000 -> 14.179915 | G17: =SUM('Financials from CIP'!E23:E24,'Financials from CIP'!E28)/1000 -> 15.436689 | H17: =H44*H13 -> 18.333217 | I17: =I44*I13 -> 21.144682 | J17: =J44*J13 -> 23.752955 | K17: =K44*K13 -> 25.97038 | L17: =L44*L13 -> 27.615698
C18: EBITDA | F18: =F15-F17 -> 12.823572 | G18: =G15-G17 -> 13.558643 | H18: =H15-H17 -> 16.348071 | I18: =I15-I17 -> 18.855107 | J18: =J15-J17 -> 21.180953 | K18: =K15-K17 -> 23.158272 | L18: =L15-L17 -> 24.625432
C19: EBITDA Margin (%) | F19: =IFERROR(F18/F$13,"N/M") -> 0.16322105 | G19: =IFERROR(G18/G$13,"N/M") -> 0.14963076 | H19: =IFERROR(H18/H$13,"N/M") -> 0.15642591 | I19: =IFERROR(I18/I$13,"N/M") -> 0.15642591 | J19: =IFERROR(J18/J$13,"N/M") -> 0.15642591 | K19: =IFERROR(K18/K$13,"N/M") -> 0.15642591 | L19: =IFERROR(L18/L$13,"N/M") -> 0.15642591
C20: Depreciation | F20: ='Financials from CIP'!D25/1000 -> 1.1801621 | G20: ='Financials from CIP'!E25/1000 -> 1.1617643 | H20: =H194 -> 5.8293926 | I20: =I194 -> 6.1302958 | J20: =J194 -> 6.4683165 | K20: =K194 -> 6.8378927 | L20: =L194 -> 7.2308829
C21: Amortization | F21: ='Financials from CIP'!D26/1000 -> 0.208264 | G21: ='Financials from CIP'!E26/1000 -> 0.237952 | H21: =MIN(G21,G69) -> 0.237952 | I21: =MIN(H21,H69) -> 0.237952 | J21: =MIN(I21,I69) -> 0.237952 | K21: =MIN(J21,J69) -> 0.237952 | L21: =MIN(K21,K69) -> 0.237952
C22: EBIT | F22: =F18-SUM(F20:F21) -> 11.435146 | G22: =G18-SUM(G20:G21) -> 12.158927 | H22: =H18-SUM(H20:H21) -> 10.280726 | I22: =I18-SUM(I20:I21) -> 12.486859 | J22: =J18-SUM(J20:J21) -> 14.474684 | K22: =K18-SUM(K20:K21) -> 16.082427 | L22: =L18-SUM(L20:L21) -> 17.156597
C23: Interest (Income) / Expense
C24: Revolver – Interest
C25: Revolver – Undrawn Commitment Fee
C26: =+C79 -> Term Loan A
C27: =+C80 -> Subordinated - Note 1
C28: =+C81 -> Subordinated - Note 2
C29: Interest (Income) / Expense | F29: ='Financials from CIP'!D27/1000 -> 2.224955 | G29: ='Financials from CIP'!E27/1000 -> 1.472763 | H29: =SUM(H24:H28) -> 0 | I29: =SUM(I24:I28) -> 0 | J29: =SUM(J24:J28) -> 0 | K29: =SUM(K24:K28) -> 0 | L29: =SUM(L24:L28) -> 0
C30: Other (Income) / Expense | F30: ='Financials from CIP'!D32/1000 -> 0.147371 | G30: ='Financials from CIP'!E32/1000 -> 0.273439 | H30: 0 | I30: 0 | J30: 0 | K30: 0 | L30: 0
C31: Income Before Taxes | F31: =F22-F29-F30 -> 9.0628199 | G31: =G22-G29-G30 -> 10.412725 | H31: =H22-H29-H30 -> 10.280726 | I31: =I22-I29-I30 -> 12.486859 | J31: =J22-J29-J30 -> 14.474684 | K31: =K22-K29-K30 -> 16.082427 | L31: =L22-L29-L30 -> 17.156597
C32: Provision for Tax | F32: ='Financials from CIP'!D29/1000 -> 3.201039 | G32: ='Financials from CIP'!E29/1000 -> 2.809107 | H32: =H46*H31 -> 3.2023536 | I32: =I46*I31 -> 3.8895441 | J32: =J46*J31 -> 4.5087338 | K32: =K46*K31 -> 5.0095311 | L32: =L46*L31 -> 5.3441256
C33: Net Income | F33: =F31-F32 -> 5.8617809 | G33: =G31-G32 -> 7.6036178 | H33: =H31-H32 -> 7.0783725 | I33: =I31-I32 -> 8.5973148 | J33: =J31-J32 -> 9.9659504 | K33: =K31-K32 -> 11.072896 | L33: =L31-L32 -> 11.812472
C34: Profit Margin (%) | F34: =IFERROR(F33/F$13,"N/M") -> 0.074609947 | G34: =IFERROR(G33/G$13,"N/M") -> 0.083912167 | H34: =IFERROR(H33/H$13,"N/M") -> 0.067729144 | I34: =IFERROR(I33/I$13,"N/M") -> 0.07132512 | J34: =IFERROR(J33/J$13,"N/M") -> 0.073600694 | K34: =IFERROR(K33/K$13,"N/M") -> 0.074793481 | L34: =IFERROR(L33/L$13,"N/M") -> 0.075035296
C36: Capital Expenditures | G36: =('Financials from CIP'!E53-'Financials from CIP'!D53+'Financials from CIP'!E25)/1000 -> 2.2620483 | H36: =H48*H13 -> 2.6089416 | I36: =I48*I13 -> 3.0090323 | J36: =J48*J13 -> 3.3802074 | K36: =K48*K13 -> 3.695762 | L36: =L48*L13 -> 3.929902
C39: Key Performance Metrics & Drivers
C41: Sales Growth (%) | G41: =G13/F13-1 -> 0.15335363 | H41: =G41 -> 0.15335363 | I41: =H41 -> 0.15335363 | J41: =I41-3% -> 0.12335363 | K41: =J41-3% -> 0.093353635 | L41: =K41-3% -> 0.063353635
C43: COGS / Sales (%) | F43: =F14/F13 -> 0.65629409 | G43: =G14/G13 -> 0.6800127 | H43: =AVERAGE(F43:G43) -> 0.66815339 | I43: =H43 -> 0.66815339 | J43: =I43 -> 0.66815339 | K43: =J43 -> 0.66815339 | L43: =K43 -> 0.66815339
C44: SG&A / Sales (%) | F44: =F17/F13 -> 0.18048486 | G44: =G17/G13 -> 0.17035654 | H44: =AVERAGE(F44:G44) -> 0.1754207 | I44: =H44 -> 0.1754207 | J44: =I44 -> 0.1754207 | K44: =J44 -> 0.1754207 | L44: =K44 -> 0.1754207
C46: Tax Rate (%) | F46: =F32/F31 -> 0.35320563 | G46: =G32/G31 -> 0.26977636 | H46: =AVERAGE(F46:G46) -> 0.31149099 | I46: =H46 -> 0.31149099 | J46: =I46 -> 0.31149099 | K46: =J46 -> 0.31149099 | L46: =K46 -> 0.31149099
C48: Capex / Sales (%) | G48: =G36/G13 -> 0.024963561 | H48: =G48 -> 0.024963561 | I48: =H48 -> 0.024963561 | J48: =I48 -> 0.024963561 | K48: =J48 -> 0.024963561 | L48: =K48 -> 0.024963561
B53: x | C53: Balance Sheet
F55: MRY | G55: MRY | H55: Fiscal Years Ending December 31,
C56: ($ in millions) | F56: =EOMONTH(G56,-12) -> 45291 | G56: =G$11 -> 45657 | H56: =H$11 -> 46022 | I56: =I$11 -> 46387 | J56: =J$11 -> 46752 | K56: =K$11 -> 47118 | L56: =L$11 -> 47483
C58: Assets
C60: Cash and Equivalents | F60: ='Financials from CIP'!D46/1000 -> 7.105652 | G60: ='Financials from CIP'!E46/1000 -> 2.957992 | H60: =G60+H119 -> 13.005932 | I60: =H60+I119 -> 22.51973 | J60: =I60+J119 -> 33.545552 | K60: =J60+K119 -> 46.071929 | L60: =K60+L119 -> 59.993804
C61: Accounts Receivable, Net | F61: =SUM('Financials from CIP'!D47:D48)/1000 -> 16.781419 | G61: =SUM('Financials from CIP'!E47:E48)/1000 -> 22.284722 | H61: =H130 -> 24.012611 | I61: =I130 -> 27.695032 | J61: =J130 -> 31.111315 | K61: =K130 -> 34.015669 | L61: =L130 -> 36.170685
C62: Inventory | F62: ='Financials from CIP'!D49/1000 -> 0.804901 | G62: ='Financials from CIP'!E49/1000 -> 1.161057 | H62: =H131 -> 1.2029011 | I62: =I131 -> 1.3873704 | J62: =J131 -> 1.5585076 | K62: =K131 -> 1.7039999 | L62: =L131 -> 1.8119545
C63: Prepaids and Other Current Assets | F63: ='Financials from CIP'!D50/1000 -> 0.269784 | G63: ='Financials from CIP'!E50/1000 -> 0.344919 | H63: =H132 -> 0.37922157 | I63: =I132 -> 0.43737657 | J63: =J132 -> 0.49132856 | K63: =K132 -> 0.53719587 | L63: =L132 -> 0.57122918
C64: Total Current Assets | F64: =SUM(F60:F63) -> 24.961756 | G64: =SUM(G60:G63) -> 26.74869 | H64: =SUM(H60:H63) -> 38.600666 | I64: =SUM(I60:I63) -> 52.039509 | J64: =SUM(J60:J63) -> 66.706703 | K64: =SUM(K60:K63) -> 82.328794 | L64: =SUM(L60:L63) -> 98.547673
C65: PP&E, Gross | H65: =G67+H36 -> 58.293926 | I65: =H65+I36 -> 61.302958 | J65: =I65+J36 -> 64.683165 | K65: =J65+K36 -> 68.378927 | L65: =K65+L36 -> 72.308829
C66: ( – ) Accumulated Depreciation | H66: =G66-H20 -> -5.8293926 | I66: =H66-I20 -> -11.959688 | J66: =I66-J20 -> -18.428005 | K66: =J66-K20 -> -25.265898 | L66: =K66-L20 -> -32.496781
C67: PP&E, Net | F67: ='Financials from CIP'!D53/1000 -> 54.5847 | G67: ='Financials from CIP'!E53/1000 -> 55.684984 | H67: =SUM(H65:H66) -> 52.464533 | I67: =SUM(I65:I66) -> 49.34327 | J67: =SUM(J65:J66) -> 46.25516 | K67: =SUM(K65:K66) -> 43.11303 | L67: =SUM(L65:L66) -> 39.812049
C68: Goodwill | F68: 0 | G68: 0 | H68: 0 | I68: 0 | J68: 0 | K68: 0 | L68: 0
C69: Intangible and Long-Term Other Assets | F69: ='Financials from CIP'!D54/1000 -> 4.378482 | G69: ='Financials from CIP'!E54/1000 -> 4.50437 | H69: =G69-H21 -> 4.266418 | I69: =H69-I21 -> 4.028466 | J69: =I69-J21 -> 3.790514 | K69: =J69-K21 -> 3.552562 | L69: =K69-L21 -> 3.31461
C70: Total Assets | F70: =SUM(F64,F67:F69) -> 83.924938 | G70: =SUM(G64,G67:G69) -> 86.938044 | H70: =SUM(H64,H67:H69) -> 95.331617 | I70: =SUM(I64,I67:I69) -> 105.41124 | J70: =SUM(J64,J67:J69) -> 116.75238 | K70: =SUM(K64,K67:K69) -> 128.99439 | L70: =SUM(L64,L67:L69) -> 141.67433
C72: Liabilities & Shareholders' Equity
C74: Accounts Payable | F74: ='Financials from CIP'!D58/1000 -> 2.805817 | G74: ='Financials from CIP'!E58/1000 -> 2.36071 | H74: =H135 -> 3.2375303 | I74: =I135 -> 3.7340173 | J74: =J135 -> 4.1946219 | K74: =K135 -> 4.5862051 | L74: =L135 -> 4.8767579
C75: Wages Payable | F75: ='Financials from CIP'!D59/1000 -> 2.383933 | G75: ='Financials from CIP'!E59/1000 -> 2.788038 | H75: =H136 -> 3.1966854 | I75: =I136 -> 3.6869088 | J75: =J136 -> 4.1417024 | K75: =K136 -> 4.5283453 | L75: =L136 -> 4.8152325
C76: Accrued Expenses & Other | F76: ='Financials from CIP'!D60/1000 -> 2.057908 | G76: ='Financials from CIP'!E60/1000 -> 3.202031 | H76: =H137 -> 3.2317637 | I76: =I137 -> 3.7273664 | J76: =J137 -> 4.1871506 | K76: =K137 -> 4.5780363 | L76: =L137 -> 4.8680716
C77: Total Current Liabilities | F77: =SUM(F74:F76) -> 7.247658 | G77: =SUM(G74:G76) -> 8.350779 | H77: =SUM(H74:H76) -> 9.6659794 | I77: =SUM(I74:I76) -> 11.148292 | J77: =SUM(J74:J76) -> 12.523475 | K77: =SUM(K74:K76) -> 13.692587 | L77: =SUM(L74:L76) -> 14.560062
C78: Revolver | F78: ='Financials from CIP'!D63/1000 -> 0.645883 | G78: ='Financials from CIP'!E63/1000 -> 1.2893 | H78: =H209 -> 1.2893 | I78: =I209 -> 1.2893 | J78: =J209 -> 1.2893 | K78: =K209 -> 1.2893 | L78: =L209 -> 1.2893 | M78: We are calculating the ENDING balance of the debt in each period, below. Link these lines to the ending balance for each type of debt, respectively, below
C79: Term Loan A | F79: ='Financials from CIP'!D64/1000 -> 18.943222 | G79: ='Financials from CIP'!E64/1000 -> 12.001451 | H79: =H218 -> 9.6011608 | I79: =I218 -> 7.2008706 | J79: =J218 -> 4.8005804 | K79: =K218 -> 2.4002902 | L79: =L218 -> 0 | M79: We are calculating the ENDING balance of the debt in each period, below. Link these lines to the ending balance for each type of debt, respectively, below
C80: Subordinated - Note 1 | F80: ='Financials from CIP'!D65/1000 -> 0.545333 | G80: ='Financials from CIP'!E65/1000 -> 0.085338 | H80: =H224 -> 0.0682704 | I80: =I224 -> 0.0512028 | J80: =J224 -> 0.0341352 | K80: =K224 -> 0.0170676 | L80: =L224 -> 0 | M80: We are calculating the ENDING balance of the debt in each period, below. Link these lines to the ending balance for each type of debt, respectively, below
C81: Subordinated - Note 2 | F81: ='Financials from CIP'!D66/1000 -> 0.092448 | G81: ='Financials from CIP'!E66/1000 -> 0.012667 | H81: =H230 -> 0.01203365 | I81: =I230 -> 0.0114003 | J81: =J230 -> 0.01076695 | K81: =K230 -> 0.0101336 | L81: =L230 -> 0 | M81: We are calculating the ENDING balance of the debt in each period, below. Link these lines to the ending balance for each type of debt, respectively, below
C82: Total Debt | F82: =SUM(F78:F81) -> 20.226886 | G82: =SUM(G78:G81) -> 13.388756 | H82: =SUM(H78:H81) -> 10.970765 | I82: =SUM(I78:I81) -> 8.5527737 | J82: =SUM(J78:J81) -> 6.1347825 | K82: =SUM(K78:K81) -> 3.7167914 | L82: =SUM(L78:L81) -> 1.2893
C83: Other Long-term Liabilities | F83: ='Financials from CIP'!D67/1000 -> 0.417874 | G83: ='Financials from CIP'!E67/1000 -> 0.429888 | H83: =G83 -> 0.429888 | I83: =H83 -> 0.429888 | J83: =I83 -> 0.429888 | K83: =J83 -> 0.429888 | L83: =K83 -> 0.429888
C84: Total liabilities | F84: =SUM(F77,F82:F83) -> 27.892418 | G84: =SUM(G77,G82:G83) -> 22.169423 | H84: =SUM(H77,H82:H83) -> 21.066632 | I84: =SUM(I77,I82:I83) -> 20.130954 | J84: =SUM(J77,J82:J83) -> 19.088145 | K84: =SUM(K77,K82:K83) -> 17.839266 | L84: =SUM(L77,L82:L83) -> 16.27925
C85: Common Stock | F85: ='Financials from CIP'!D71/1000 -> 7.7836338 | G85: ='Financials from CIP'!E71/1000 -> 8.9161157 | H85: =G85 -> 8.9161157 | I85: =H85 -> 8.9161157 | J85: =I85 -> 8.9161157 | K85: =J85 -> 8.9161157 | L85: =K85 -> 8.9161157
C86: Retained Earnings | F86: ='Financials from CIP'!D72/1000 -> 48.248887 | G86: ='Financials from CIP'!E72/1000 -> 55.852505 | H86: =G86+H33 -> 62.930877 | I86: =H86+I33 -> 71.528192 | J86: =I86+J33 -> 81.494142 | K86: =J86+K33 -> 92.567038 | L86: =K86+L33 -> 104.37951
C87: Total Liabilities & Shareholders' Equity | F87: =SUM(F84:F86) -> 83.924939 | G87: =SUM(G84:G86) -> 86.938043 | H87: =SUM(H84:H86) -> 92.913625 | I87: =SUM(I84:I86) -> 100.57526 | J87: =SUM(J84:J86) -> 109.4984 | K87: =SUM(K84:K86) -> 119.32242 | L87: =SUM(L84:L86) -> 129.57488
C89: Check (should be zero) | F89: =F87-F70 -> 8.2790072e-07 | G89: =G87-G70 -> -5.041918e-07 | H89: =H87-H70 -> -2.4179917 | I89: =I87-I70 -> -4.8359828 | J89: =J87-J70 -> -7.253974 | K89: =K87-K70 -> -9.6719651 | L89: =L87-L70 -> -12.099457
B93: x | C93: Cash Flow Statement
F95: MRY | G95: MRY | H95: Fiscal Years Ending December 31,
C96: ($ in millions) | F96: =F$11 -> 45291 | G96: =G$11 -> 45657 | H96: =H$11 -> 46022 | I96: =I$11 -> 46387 | J96: =J$11 -> 46752 | K96: =K$11 -> 47118 | L96: =L$11 -> 47483
C98: Operating Activities
C100: Net Income | H100: =H33 -> 7.0783725 | I100: =I33 -> 8.5973148 | J100: =J33 -> 9.9659504 | K100: =K33 -> 11.072896 | L100: =L33 -> 11.812472
C101: Depreciation | H101: =H20 -> 5.8293926 | I101: =I20 -> 6.1302958 | J101: =J20 -> 6.4683165 | K101: =K20 -> 6.8378927 | L101: =L20 -> 7.2308829
C102: Amortization of Intangibles | H102: =H21 -> 0.237952 | I102: =I21 -> 0.237952 | J102: =J21 -> 0.237952 | K102: =K21 -> 0.237952 | L102: =L21 -> 0.237952
C103: Net Income + Non-Cash Expense Adjustments | H103: =SUM(H100:H102) -> 13.145717 | I103: =SUM(I100:I102) -> 14.965563 | J103: =SUM(J100:J102) -> 16.672219 | K103: =SUM(K100:K102) -> 18.14874 | L103: =SUM(L100:L102) -> 19.281307
C104: (Increase) / Decrease in Working Capital | H104: =-(H141) -> -0.4888351 | I104: =-(I141) -> -2.4427323 | J104: =-(J141) -> -2.2661896 | K104: =-(K141) -> -1.9266021 | L104: =-(L141) -> -1.429529
C105: Cash flow from Operating Activities | H105: =+SUM(H103:H104) -> 12.656882 | I105: =+SUM(I103:I104) -> 12.52283 | J105: =+SUM(J103:J104) -> 14.406029 | K105: =+SUM(K103:K104) -> 16.222138 | L105: =+SUM(L103:L104) -> 17.851778
C107: Investing Activities
C109: Cash flow from Investment Activities - CapEx | H109: =-H36 -> -2.6089416 | I109: =-I36 -> -3.0090323 | J109: =-J36 -> -3.3802074 | K109: =-K36 -> -3.695762 | L109: =-L36 -> -3.929902
C111: Financing Activities
C113: Revolver
C114: =+C79 -> Term Loan A
C115: =+C80 -> Subordinated - Note 1
C116: =+C81 -> Subordinated - Note 2
C117: Cash flow from Financing Activities | H117: =SUM(H113:H116) -> 0 | I117: =SUM(I113:I116) -> 0 | J117: =SUM(J113:J116) -> 0 | K117: =SUM(K113:K116) -> 0 | L117: =SUM(L113:L116) -> 0
C119: Change in Cash | H119: =H117+H109+H105 -> 10.04794 | I119: =I117+I109+I105 -> 9.513798 | J119: =J117+J109+J105 -> 11.025822 | K119: =K117+K109+K105 -> 12.526376 | L119: =L117+L109+L105 -> 13.921876
B123: x | C123: Working Capital
F125: MRY | G125: MRY | H125: Fiscal Years Ending December 31,
C126: ($ in millions) | F126: =F$11 -> 45291 | G126: =G$11 -> 45657 | H126: =H$11 -> 46022 | I126: =I$11 -> 46387 | J126: =J$11 -> 46752 | K126: =K$11 -> 47118 | L126: =L$11 -> 47483
C128: Net Working Capital
C130: =C61 -> Accounts Receivable, Net | F130: =F61 -> 16.781419 | G130: =G61 -> 22.284722 | H130: =(H145/365)*H149 -> 24.012611 | I130: =(I145/365)*I149 -> 27.695032 | J130: =(J145/365)*J149 -> 31.111315 | K130: =(K145/365)*K149 -> 34.015669 | L130: =(L145/365)*L149 -> 36.170685
